Workbook

Sheet Inputs
B2: Gujarat Energy Limited - extracted line items (Consolidated, Rs crore)
B3: Yellow cells are EXTRACTED INPUTS traced to the source in the final column - nothing here is computed. Every downstream ratio references this sheet, so correcting a value here reflows the entire workbook.
B5: Line item | C5: FY2024 | D5: FY2025 | E5: FY2026 | F5: Source
B6: MERGED revenue from operations | D6: 27718 | E6: 24198 | F6: Q4 FY2026 press release 30-May-2026 (MERGED basis)
B7: MERGED EBITDA | D7: 3677 | E7: 3772 | F7: Q4 FY2026 press release 30-May-2026 (MERGED basis)
B8: MERGED profit after tax | E8: 2299 | F8: Q4 FY2026 press release 30-May-2026 (MERGED basis)
B9: MERGED net worth | E9: 18517 | F9: Q4 FY2026 press release 30-May-2026 (MERGED basis) - as on 31-03-2026
B10: MERGED EPS (Rs) | E10: 24.5 | F10: Q4 FY2026 press release 30-May-2026 (MERGED basis)
B11: STANDALONE revenue from ops | C11: 16292.97 | D11: 17184.97 | F11: FY2024-25 annual report (Gujarat Gas STANDALONE, pre-scheme) P&L
B12: STANDALONE other income | C12: 107.75 | D12: 209.97 | F12: FY2024-25 annual report (Gujarat Gas STANDALONE, pre-scheme) P&L
B13: STANDALONE excise duty | C13: 602.78 | D13: 698.02 | F13: FY2024-25 annual report (Gujarat Gas STANDALONE, pre-scheme) - an EXPENSE line
B14: STANDALONE finance costs | C14: 29.31 | D14: 32.49 | F14: FY2024-25 annual report (Gujarat Gas STANDALONE, pre-scheme) P&L
B15: STANDALONE depreciation | C15: 474.3 | D15: 510.64 | F15: FY2024-25 annual report (Gujarat Gas STANDALONE, pre-scheme) P&L
B16: STANDALONE profit before tax | C16: 1536.21 | D16: 1546.6 | F16: FY2024-25 annual report (Gujarat Gas STANDALONE, pre-scheme) P&L
B17: STANDALONE profit after tax | C17: 1142.77 | D17: 1145.51 | F17: FY2024-25 annual report (Gujarat Gas STANDALONE, pre-scheme) P&L
B18: STANDALONE borrowings | C18: 0 | D18: 0 | F18: FY2024-25 annual report (Gujarat Gas STANDALONE, pre-scheme) BS - NIL both years
B19: STANDALONE lease liabilities | C19: 117.77 | D19: 115.16 | F19: FY2024-25 annual report (Gujarat Gas STANDALONE, pre-scheme) BS
B20: STANDALONE cash + bank | C20: 926.12 | D20: 359.4 | F20: FY2024-25 annual report (Gujarat Gas STANDALONE, pre-scheme) BS
B21: STANDALONE total equity | C21: 7689.26 | D21: 8453.65 | F21: FY2024-25 annual report (Gujarat Gas STANDALONE, pre-scheme) BS
B22: STANDALONE total assets | C22: 11658.35 | D22: 12615.12 | F22: FY2024-25 annual report (Gujarat Gas STANDALONE, pre-scheme) BS
B23: VOLUME CGD segment (mmscmd) | E23: 8.69 | F23: Q4 FY2026 press release 30-May-2026 (MERGED basis)
B24: VOLUME gas trading (mmscmd) | E24: 4.94 | F24: Q4 FY2026 press release 30-May-2026 (MERGED basis)
B25: VOLUME CNG (mmscmd) | E25: 3.43 | F25: Q4 FY2026 press release 30-May-2026 (MERGED basis)
B26: CNG stations (no.) | E26: 839 | F26: Q4 FY2026 press release 30-May-2026 (MERGED basis)
B27: PNG households (lakh) | E27: 24.18 | F27: Q4 FY2026 press release 30-May-2026 (MERGED basis)

Sheet RatioSuite
B2: Gujarat Energy Limited - ratio suite (Consolidated, Rs crore; agency conventions applied)
B3: Every value is a LIVE FORMULA referencing the Inputs sheet - click any cell to see the arithmetic. 'Calculation' states the same formula in words; 'Convention' records the definitional choice (lease treatment, normalisation, netting) so the basis is auditable.
B5: Ratio | C5: FY2024 | D5: FY2025 | E5: FY2026 | F5: Calculation | G5: Convention / note
B6: MERGED EBITDA margin (%) | C6: =Inputs!C7/Inputs!C6 | D6: =Inputs!D7/Inputs!D6 -> 0.13265748 | E6: =Inputs!E7/Inputs!E6 -> 0.15588065 | F6: Expanded 232bps as low-margin gas TRADING revenue shrank - a mix effect, not pricing
B7: MERGED revenue growth (%) | C7: =Inputs!C6/OFFSET(Inputs!C6,0,-1)-1 | D7: =Inputs!D6/OFFSET(Inputs!D6,0,-1)-1 | E7: =Inputs!E6/OFFSET(Inputs!E6,0,-1)-1 | F7: FELL 12.7% - but EBITDA rose. Read with the margin row above
B8: MERGED EBITDA growth (%) | C8: =Inputs!C7/OFFSET(Inputs!C7,0,-1)-1 | D8: =Inputs!D7/OFFSET(Inputs!D7,0,-1)-1 | E8: =Inputs!E7/OFFSET(Inputs!E7,0,-1)-1 | F8: Rose 2.6% on 12.7% lower revenue
B9: STANDALONE PBILDT | C9: =Inputs!C16+Inputs!C14+Inputs!C15-Inputs!C12 -> 1932.07 | D9: =Inputs!D16+Inputs!D14+Inputs!D15-Inputs!D12 -> 1879.76 | E9: =Inputs!E16+Inputs!E14+Inputs!E15-Inputs!E12 -> 0 | F9: CareEdge earnings measure on the standalone basis
B10: STANDALONE adjusted debt (leases only) | C10: =Inputs!C18+Inputs!C19 -> 117.77 | D10: =Inputs!D18+Inputs!D19 -> 115.16 | E10: =Inputs!E18+Inputs!E19 -> 0 | F10: Borrowings are NIL - adjusted debt is lease liabilities alone
B11: STANDALONE net cash | C11: =Inputs!C20-Inputs!C18-Inputs!C19 -> 808.35 | D11: =Inputs!D20-Inputs!D18-Inputs!D19 -> 244.24 | E11: =Inputs!E20-Inputs!E18-Inputs!E19 -> 0 | F11: POSITIVE = net cash. The dominant rating consideration
B12: STANDALONE overall gearing (x) [KEY] | C12: =(Inputs!C18+Inputs!C19)/Inputs!C21 -> 0.015316168 | D12: =(Inputs!D18+Inputs!D19)/Inputs!D21 -> 0.013622518 | E12: =(Inputs!E18+Inputs!E19)/Inputs!E21 | F12: 0.014x. No leverage threshold is remotely in play
B13: STANDALONE interest coverage (x) | C13: =(Inputs!C16+Inputs!C14+Inputs!C15-Inputs!C12)/Inputs!C14 -> 65.918458 | D13: =(Inputs!D16+Inputs!D14+Inputs!D15-Inputs!D12)/Inputs!D14 -> 57.856571 | E13: =(Inputs!E16+Inputs!E14+Inputs!E15-Inputs!E12)/Inputs!E14 | F13: 57.9x FY2025, 65.9x FY2024
B14: STANDALONE TOL / TNW (x) | C14: =(Inputs!C22-Inputs!C21)/Inputs!C21 -> 0.51618621 | D14: =(Inputs!D22-Inputs!D21)/Inputs!D21 -> 0.49226902 | E14: =(Inputs!E22-Inputs!E21)/Inputs!E21 | F14: Total outside liabilities to net worth
B15: STANDALONE revenue net of excise | C15: =Inputs!C11-Inputs!C13 -> 15690.19 | D15: =Inputs!D11-Inputs!D13 -> 16486.95 | E15: =Inputs!E11-Inputs!E13 -> 0 | F15: Excise is an expense line, so reported revenue is GROSS of excise
B16: VOLUME total (mmscmd) [SECTOR-DEFINING] | C16: =Inputs!C23+Inputs!C24 -> 0 | D16: =Inputs!D23+Inputs!D24 -> 0 | E16: =Inputs!E23+Inputs!E24 -> 13.63 | F16: CGD 8.69 + trading 4.94 = 13.63, matching the published total
B17: VOLUME CNG share of CGD (%) | C17: =Inputs!C25/Inputs!C23 | D17: =Inputs!D25/Inputs!D23 | E17: =Inputs!E25/Inputs!E23 -> 0.39470656 | F17: CNG is the fastest-growing CGD category, +12% YoY to a record 3.60 mmscmd in Q4

Sheet TieOut
B2: Gujarat Energy Limited - tie-out to company-disclosed figures
B3: Binding gate (CLAUDE.md Step 6): headline computed figures must reconcile to the company's OWN disclosed numbers before the workpaper is issued. PASS/FAIL is itself a formula - it re-evaluates if any input changes.
B5: Check | C5: Computed | D5: Company-disclosed | E5: Result | F5: Note
B6: FY25 standalone total income | C6: =Inputs!E11+Inputs!E12 -> 0 | D6: 17394.94 | E6: =IF(ABS(C6-D6)<=MAX(1,ABS(D6)*0.005),"PASS","CHECK") | F6: Reported total income - exact
B7: FY25 standalone borrowings are NIL | C7: =Inputs!E18 -> 0 | D7: 0 | E7: =IF(ABS(C7-D7)<=MAX(1,ABS(D7)*0.005),"PASS","CHECK") | F7: Nil in both FY2024 and FY2025 - the defining fact of this credit
B8: FY25 standalone net cash is POSITIVE | C8: =Inputs!E20-Inputs!E18-Inputs!E19 -> 0 | D8: 244.24 | E8: =IF(ABS(C8-D8)<=MAX(1,ABS(D8)*0.005),"PASS","CHECK") | F8: Cash 359.40 less lease liabilities 115.16 - the company is in net cash
B9: FY26 volumes reconcile | C9: =Inputs!F23+Inputs!F24 | D9: 13.63 | E9: =IF(ABS(C9-D9)<=MAX(1,ABS(D9)*0.005),"PASS","CHECK") | F9: 8.69 + 4.94 against the published total of 13.63 mmscmd
B10: BASIS GAP: merged FY25 vs standalone FY25 | C10: =Inputs!E6-(Inputs!E11+Inputs!E12) -> 24198 | D10: 10323.06 | E10: =IF(ABS(C10-D10)<=MAX(1,ABS(D10)*0.005),"PASS","CHECK") | F10: Rs 10,323 cr - the incoming trading/E&P/wind businesses. PROOF the two bases differ and must never be spliced into one series
B12: Tolerance: 0.5% of the disclosed figure, floor Rs 1 - tighter than rounding, loose enough for basis differences.

Sheet RatingScore
B2: Gujarat Energy Limited - rating scorecard and view
B3: Factor scores 1 (strongest) to 6 (weakest), weighted to a composite. The anchor is a SCREENING cross-check with a +/-2 notch band, NOT the rating - the analyst view and any divergence are stated below and the divergence must be explained, never buried.
B5: Rating factor | C5: Score (1-6) | D5: Weight | E5: Weighted | F5: Justification
B6: Capital structure | C6: 1 | D6: 0.35 | E6: =C6*D6 -> 0.35 | F6: BORROWINGS ARE NIL in FY2024 and FY2025. Adjusted debt is lease liabilities of Rs 115.16 cr against equity of Rs 8,453.65 cr - gearing 0.014x - and the company is in net cash of Rs 244.24 cr with interest coverage of 57.9x. Net worth grew entirely through accrual. This is the dominant rating consideration.
B7: Market position | C7: 1 | D7: 0.25 | E7: =C7*D7 -> 0.25 | F7: India's largest city gas distribution company. FY2026 CGD volume 8.69 mmscmd, total 13.63 mmscmd including trading. 839 CNG stations and 24.18 lakh PNG households give the position durability; CNG volume hit a record 3.60 mmscmd in Q4, +12% YoY.
B8: Ownership and group linkage | C8: 1 | D8: 0.2 | E8: =C8*D8 -> 0.2 | F8: Gujarat state government company (CIN ...SGC...), IAS officers as Chairman and Managing Director, within the GSPC group. All three rating agencies hold the issuer at the highest long-term grade per the issuer's own disclosure.
B9: Profitability and volume growth | C9: 2 | D9: 0.1 | E9: =C9*D9 -> 0.2 | F9: Merged-basis EBITDA Rs 3,772 cr, margin expanding 232bps to 15.59% as low-margin gas trading contracted. PAT Rs 2,299 cr, EPS Rs 24.50, highest-ever dividend recommended. Morbi cluster consumption grew from 0.36 to 7.8 MMSCMD.
B10: Sector and structural risk | C10: 3 | D10: 0.1 | E10: =C10*D10 -> 0.3 | F10: Gas price and availability volatility with lagged pass-through; PNGRB tariff regulation; and the composite scheme effective 01-May-2026, AFTER the balance-sheet date, so the merged-entity capital structure and residual post-demerger obligations are not yet evidenced. That is the principal open question in this assessment.
B11: Weight check (must be 100%) | D11: =SUM(D6:D10) -> 1 | E11: =SUM(E6:E10) -> 1.3 | F11: =IF(ABS(D11-1)<0.001,"weights sum to 100%","ERROR: weights must sum to 100%")
B13: Weighted composite score | C13: =E11 -> 1.3
B14: Indicative anchor grade (screening only, +/-2 band) | C14: AAA band (composite 1.35)
B15: ANALYST RATING VIEW | C15: CARE AAA; Stable / CARE A1+
B16: Divergence from anchor - explanation | C16: No divergence. The issuer's FY2024-25 annual report discloses CARE AAA; Stable / CARE A1+ (09-09-2024), IND AAA/Stable / IND A1+ and CRISIL AAA/Stable - all three agencies at the highest long-term grade, and the FY2022-23 report records an upgrade TO AAA/Stable. A CareEdge rationale for Gujarat Gas Limited (29-Sep-2025) exists in the reference library and was NOT opened before this view was formed; the view rests on the debt-free balance sheet and the issuer's own Step 7b disclosure.
