Workbook

Sheet Assumptions
B2: JSW Steel Limited - 5-yr model assumptions (Rs crore) - every driver sourced
B4: Driver | C4: FY27E | D4: FY28E | E4: FY29E | F4: FY30E | G4: FY31E
B5: Revenue growth % | C5: -0.04 | D5: 0.09 | E5: 0.09 | F5: 0.09 | G5: 0.08 | H5: FY27: BPSL deconsolidated end-FY26 (~11-12% of consol; MOSL: BPSL FY25 rev Rs214bn/EBITDA Rs22bn; Centrum cut FY27E EBITDA ~6%) offset by volume growth + safeguard-duty pricing; FY28-31: capacity ramp (co roadmap 31.9->48.8 mtpa by FY30; ICICI vol CAGR ~10% FY25-28) - analyst judgment on those sources
B6: EBITDA margin % | C6: 0.165 | D6: 0.168 | E6: 0.17 | F6: 0.173 | G6: 0.175 | H6: FY26 actual 16.1%; ICICI EBITDA/t Rs8.8k->10.8k FY26-28E; integration (captive iron ore ~50MT, coking coal 25% by FY31) - judgment on those sources
B7: Capex | C7: 23000 | D7: 25000 | E7: 26000 | F7: 26000 | G7: 26000 | H7: Company Q4 deck: FY27 guidance Rs22,000-24,000 cr (mid used); programme Rs1,26,161 cr over 4-5 yrs
B8: Net new debt +/(repay) | C8: 2000 | D8: 6000 | E8: 6000 | F8: 4000 | G8: 2000 | H8: Judgment: capex part-debt-funded within mgmt net-debt/EBITDA cap 3.0x; JFE tranche-2 Rs7,880 cr inflow (Centrum) offsets FY27
B9: Avg interest rate % | C9: 0.0875 | D9: 0.0875 | E9: 0.0875 | F9: 0.0875 | G9: 0.0875 | H9: FY26 effective ~9.2% (interest 9,102 / avg debt); deleveraged mix - judgment
B10: Tax rate % | C10: 0.25 | D10: 0.25 | E10: 0.25 | F10: 0.25 | G10: 0.25 | H10: Standard corporate rate; FY26 effective in this range
B11: Dividends | C11: 1737 | D11: 1876 | E11: 2026 | F11: 2188 | G11: 2363 | H11: FY26 declared Rs7.1/sh (Q4 deck) x ~244.7 cr shares ~ Rs1,737 cr; grown ~8%/yr with earnings - judgment
B12: JFE tranche-2 equity inflow | C12: 7880 | D12: 0 | E12: 0 | F12: 0 | G12: 0 | H12: Centrum 15-May-26: ~Rs78.8bn by end-Jun-26
B14: STRESS CASE deltas (Iron & Steel methodology variables: realisation/margin, volume):
B15: Stress revenue growth delta (pp) | C15: -0.05 | H15: Volume/realisation stress: growth 5pp lower every year
B16: Stress EBITDA margin delta (pp) | C16: -0.025 | H16: Margin stress: -250bps (coking-coal spike / realisation fall; FY25 trough was 13.6%)

Sheet Revenue Model
B2: Revenue build (condensed: volume x blended realisation; Rs crore)
C4: FY25A | D4: FY26A | E4: FY27E | F4: FY28E | G4: FY29E | H4: FY30E | I4: FY31E
B5: Steel sales volume (mt) | C5: 24.9 | D5: 26.5 | E5: 30.1 | F5: =E5*(1+Assumptions!C5*0.7) | G5: =F5*(1+Assumptions!D5*0.7) | H5: =G5*(1+Assumptions!E5*0.7) | I5: =H5*(1+Assumptions!F5*0.7) | J5: =I5*(1+Assumptions!G5*0.7) | K5: FY25 26.5 mt / FY28E 35.2 mt per ICICI Direct; FY26 ~30.1 mt (AR/workpaper); FY24 approx
B6: Blended realisation (Rs/tonne) | C6: =C7*10000000/(C5*1000000) | D6: =D7*10000000/(D5*1000000) | E6: =E7*10000000/(E5*1000000) | F6: =F7*10000000/(F5*1000000) | G6: =G7*10000000/(G5*1000000) | H6: =H7*10000000/(H5*1000000) | I6: =I7*10000000/(I5*1000000) | J6: =J7*10000000/(J5*1000000) | K6: Derived: revenue / volume (display only)
B7: TOTAL REVENUE | C7: 175006 | D7: 168824 | E7: 185470 | F7: =E7*(1+Assumptions!C5) | G7: =F7*(1+Assumptions!D5) | H7: =G7*(1+Assumptions!E5) | I7: =H7*(1+Assumptions!F5) | J7: =I7*(1+Assumptions!G5) | K7: FY24-26 audited consolidated (ARs; compute_ratios.py); FY27E-31E from Assumptions growth
B8: YoY growth % | C8: n.a. | D8: =D7/C7-1 | E8: =E7/D7-1 | F8: =F7/E7-1 | G8: =G7/F7-1 | H8: =H7/G7-1 | I8: =I7/H7-1 | J8: =J7/I7-1
B10: Segment colour (AR: 5 reporting segments; steel dominates; ~10% exports). BPSL (4.5 mtpa) deconsolidated 27-Mar-26 -> FY27E base excludes it.

Sheet Income Statement
B2: Income statement (consolidated, Rs crore)
C4: FY25A | D4: FY26A | E4: FY27E | F4: FY28E | G4: FY29E | H4: FY30E | I4: FY31E
B5: Revenue (<- Revenue Model) | C5: ='Revenue Model'!C7 | D5: ='Revenue Model'!D7 | E5: ='Revenue Model'!E7 | F5: ='Revenue Model'!F7 | G5: ='Revenue Model'!G7 | H5: ='Revenue Model'!H7 | I5: ='Revenue Model'!I7 | J5: ='Revenue Model'!J7
B6: EBITDA (OPBDITA) | C6: 28236 | D6: 22904 | E6: 29821 | F6: ='Revenue Model'!F7*Assumptions!C6 | G6: ='Revenue Model'!G7*Assumptions!D6 | H6: ='Revenue Model'!H7*Assumptions!E6 | I6: ='Revenue Model'!I7*Assumptions!F6 | J6: ='Revenue Model'!J7*Assumptions!G6
B7: EBITDA margin % | C7: =C6/C5 | D7: =D6/D5 | E7: =E6/E5 | F7: =F6/F5 | G7: =G6/G5 | H7: =H6/H5 | I7: =I6/I5 | J7: =J6/J5
B8: Depreciation & amortisation | C8: 8172 | D8: 9309 | E8: 9601 | F8: =E8+Assumptions!C7*0.05 | G8: =F8+Assumptions!D7*0.05 | H8: =G8+Assumptions!E7*0.05 | I8: =H8+Assumptions!F7*0.05 | J8: =I8+Assumptions!G7*0.05 | K8: Forward: prior + 5% of capex commissioning - judgment
B9: EBIT | C9: =C6-C8 | D9: =D6-D8 | E9: =E6-E8 | F9: =F6-F8 | G9: =G6-G8 | H9: =H6-H8 | I9: =I6-I8 | J9: =J6-J8
B10: Interest expense | C10: 8105 | D10: 8412 | E10: 9102 | F10: =AVERAGE('Balance Sheet'!E5,'Balance Sheet'!F5)*Assumptions!C9 | G10: =AVERAGE('Balance Sheet'!F5,'Balance Sheet'!G5)*Assumptions!D9 | H10: =AVERAGE('Balance Sheet'!G5,'Balance Sheet'!H5)*Assumptions!E9 | I10: =AVERAGE('Balance Sheet'!H5,'Balance Sheet'!I5)*Assumptions!F9 | J10: =AVERAGE('Balance Sheet'!I5,'Balance Sheet'!J5)*Assumptions!G9
B11: PBT (pre-exceptional) | C11: =C9-C10 | D11: =D9-D10 | E11: =E9-E10 | F11: =F9-F10 | G11: =G9-G10 | H11: =H9-H10 | I11: =I9-I10 | J11: =J9-J10
B12: Exceptional gain (BPSL JV, non-cash) | C12: 0 | D12: 0 | E12: 18051 | F12: 0 | G12: 0 | H12: 0 | I12: 0 | J12: 0 | K12: AR FY26 Note 48 - slump-sale gain, excluded from run-rate
B13: Tax (25% on pre-exceptional PBT fwd) | C13: 3735 | D13: 1732 | E13: 5236 | F13: =MAX(F11,0)*Assumptions!C10 | G13: =MAX(G11,0)*Assumptions!D10 | H13: =MAX(H11,0)*Assumptions!E10 | I13: =MAX(I11,0)*Assumptions!F10 | J13: =MAX(J11,0)*Assumptions!G10 | K13: Historical tax = balancing to reported PAT (approx); forward 25%
B14: PAT - NORMALISED (pre-exceptional) | C14: 8973 | D14: 3504 | E14: 8698 | F14: =F11-F13 | G14: =G11-G13 | H14: =H11-H13 | I14: =I11-I13 | J14: =J11-J13 | K14: FY26 normalised Rs8,698 cr = company-stated ex-exceptionals (Q4 deck); FY24/25 reported (no exceptionals of size)
B15: PAT - reported (owners) | C15: 8973 | D15: 3504 | E15: 22316 | F15: =F14 | G15: =G14 | H15: =H14 | I15: =I14 | J15: =J14
B16: Gross cash accruals (norm PAT + D&A) | C16: =C14+C8 | D16: =D14+D8 | E16: =E14+E8 | F16: =F14+F8 | G16: =G14+G8 | H16: =H14+H8 | I16: =I14+I8 | J16: =J14+J8

Sheet Balance Sheet
B2: Balance sheet (key credit lines, consolidated, Rs crore)
C4: FY25A | D4: FY26A | E4: FY27E | F4: FY28E | G4: FY29E | H4: FY30E | I4: FY31E
B5: Total debt (borrowings + leases, excl acceptances) | C5: 87984 | D5: 98752 | E5: 99310 | F5: =E5+Assumptions!C8 | G5: =F5+Assumptions!D8 | H5: =G5+Assumptions!E8 | I5: =H5+Assumptions!F8 | J5: =I5+Assumptions!G8
B6: Acceptances (buyer's credit) | C6: 17654 | D6: 20534 | E6: 19817 | F6: =E6 | G6: =E6 | H6: =E6 | I6: =E6 | J6: =E6 | K6: Held flat forward - judgment
B7: Cash & liquid investments | C7: 12351 | D7: 19104 | E7: 41507 | F7: =E7+'Income Statement'!F16-Assumptions!C7-Assumptions!C11+Assumptions!C8+Assumptions!C12 | G7: =F7+'Income Statement'!G16-Assumptions!D7-Assumptions!D11+Assumptions!D8 | H7: =G7+'Income Statement'!H16-Assumptions!E7-Assumptions!E11+Assumptions!E8 | I7: =H7+'Income Statement'!I16-Assumptions!F7-Assumptions!F11+Assumptions!F8 | J7: =I7+'Income Statement'!J16-Assumptions!G7-Assumptions!G11+Assumptions!G8 | K7: Roll: prior + GCA - capex - dividends + net new debt (+ JFE tranche-2 in FY27)
B8: NET DEBT (excl acceptances) | C8: =C5-C7 | D8: =D5-D7 | E8: =E5-E7 | F8: =F5-F7 | G8: =G5-G7 | H8: =H5-H7 | I8: =I5-I7 | J8: =J5-J7
B9: Tangible net worth (incl NCI) | C9: 79776 | D9: 81666 | E9: 105475 | F9: =E9+'Income Statement'!F14-Assumptions!C11+Assumptions!C12 | G9: =F9+'Income Statement'!G14-Assumptions!D11 | H9: =G9+'Income Statement'!H14-Assumptions!E11 | I9: =H9+'Income Statement'!I14-Assumptions!F11 | J9: =I9+'Income Statement'!J14-Assumptions!G11 | K9: Roll: prior + normalised PAT - dividends (+ JFE equity in FY27); FY26 jump incl exceptional gain
B10: Total outside liabilities (TA - equity) | C10: 148422 | D10: 159076 | E10: 164201 | F10: n.a. | G10: n.a. | H10: n.a. | I10: n.a. | J10: n.a.
B11: Current assets / Current liabilities | C11: 64,534 / 66,065 | D11: 70,736 / 60,626 | E11: 103,435 / 69,377 | K11: AR consolidated balance sheets; forward WC not modelled line-by-line (see caveats)
B13: CHECK net debt/EBITDA | C13: =C8/'Income Statement'!C6 | D13: =D8/'Income Statement'!D6 | E13: =E8/'Income Statement'!E6 | F13: =F8/'Income Statement'!F6 | G13: =G8/'Income Statement'!G6 | H13: =H8/'Income Statement'!H6 | I13: =I8/'Income Statement'!I6 | J13: =J8/'Income Statement'!J6 | K13: Mgmt ceiling 3.0x (tightened guidance); covenant cap 3.75x (AR)

Sheet Debt Breakup
B2: JSW Steel - consolidated debt breakup (Rs crore) - derived from FY2025-26 AR, reconciled to screener.in
B4: A. Balance-sheet borrowings (statutory) | C4: FY2024 | D4: FY2025 | E4: FY2026
B5: Long-term borrowings | C5: 67354 | D5: 81983 | E5: 75608 | F5: Balance-sheet borrowings note (ties to screener.in consolidated)
B6: Short-term borrowings (incl current maturities) | C6: 18221 | D6: 13974 | E6: 19924 | F6: Same
B7: Lease liabilities | C7: 2409 | D7: 2795 | E7: 3778 | F7: Same
B8: Preference capital / other | C8: 0 | D8: 0 | E8: 0 | F8: Pref 36/64/48 net of 'other borrowings' -36/-64/-48 per screener = nil
B9: TOTAL DEBT (incl leases) - used in model/scorecard | C9: =SUM(C5:C8) | D9: =SUM(D5:D8) | E9: =SUM(E5:E8) | F9: Totals 87,984 / 98,752 / 99,310 - tie EXACTLY to screener.in consolidated borrowings
B11: B. Instrument-type view, FY2026 (AR disclosures) | E11: FY2026
B12: Bonds & debentures (26% of gross debt - incl USD bonds) | E12: =0.26*E9 | F12: AR funding-mix chart: 'Bonds and debentures 26% / Loans and others 74%'
B13: of which: domestic NCDs outstanding (standalone) | E13: 6750 | F13: AR: 'outstanding NCDs aggregate to Rs6,750 crore, all listed on BSE'
B14: Loans & others (74% - bank term loans, ECBs, WC) | E14: =0.74*E9 | F14: AR funding-mix chart; incl US$1.8bn syndicated ECBs raised over past 24 months
B15: Foreign currency share (64%) | E15: =0.64*E9 | F15: AR: 'INR debt 36% / Foreign currency debt 64%'
B16: Acceptances (NOT in borrowings; debt-like sensitivity) | E16: 19817 | F16: Trade payables note; treated per steel-sector practice
B18: C. AR net-debt bridge & reconciliation, FY2026
B19: Opening net debt (FY25) | E19: 76563 | F19: AR net-debt movement chart
B20: Closing net debt (FY26) - AR headline | E20: 53870 | F20: AR: net debt 53,870; cash & equivalents 41,662; ND/Equity 0.51x; ND/EBITDA 1.81x
B21: = Borrowings excl leases (75,608+19,924=95,532) - cash 41,662 | E21: 53870 | F21: Arithmetic check = 53,870: TIES
B22: Net debt incl leases (model basis: 99,310 - 41,507 model cash) | E22: 57803 | F22: Model uses cash & CURRENT liquid investments 41,507 (slightly narrower than AR cash 41,662)
B23: BPSL-JFE deleveraging - total programme | E23: 37250 | F23: AR: '~Rs37,250 crore of deleveraging' in two phases
B24: tranche-2 expected June 2026 | E24: 7875 | F24: AR (company figure; broker note said 7,880 - AR prevails)
B25: Weighted average interest rate Mar-26 (India ops) | E25: 0.0617 | F25: AR: 6.17% vs 7.12% Mar-25 (-92bps)
B27: D. REFERENCE ONLY - CRA-published limits (NOT data; excluded from report tables per user directive)
B28: ICRA 2025 action rated-limit total (reference/context only - not company-disclosed) | E28: 94660 | F28: CRA publications are craft/context references only; limits await issuer confirmation (term sheets)
B29: Drawn borrowings FY26 (statutory, above) | E29: =E9 | F29: The two differ by undrawn non-fund-based/unallocated limits + timing (rated table is a 2025 action)

Sheet Cash Flow
B2: Cash flow (derived, Rs crore)
C4: FY25A | D4: FY26A | E4: FY27E | F4: FY28E | G4: FY29E | H4: FY30E | I4: FY31E
B5: Gross cash accruals (norm PAT + D&A) | C5: ='Income Statement'!C16 | D5: ='Income Statement'!D16 | E5: ='Income Statement'!E16 | F5: ='Income Statement'!F16 | G5: ='Income Statement'!G16 | H5: ='Income Statement'!H16 | I5: ='Income Statement'!I16 | J5: ='Income Statement'!J16
B6: Capex | C6: n.a. | D6: n.a. | E6: 15595 | F6: =Assumptions!C7 | G6: =Assumptions!D7 | H6: =Assumptions!E7 | I6: =Assumptions!F7 | J6: =Assumptions!G7 | K6: FY26 actual Rs15,595 cr (Q4 deck); FY24/25 consolidated capex not extracted
B7: Dividends | C7: n.a. | D7: n.a. | E7: 1462 | F7: =Assumptions!C11 | G7: =Assumptions!D11 | H7: =Assumptions!E11 | I7: =Assumptions!F11 | J7: =Assumptions!G11 | K7: FY26 approx (prior-year Rs6.0/sh paid); forward per assumptions
B8: FREE CASH FLOW (GCA - capex - dividends) | C8: n.a. | D8: n.a. | E8: =E5-E6-E7 | F8: =F5-F6-F7 | G8: =G5-G6-G7 | H8: =H5-H6-H7 | I8: =I5-I6-I7 | J8: =J5-J6-J7
B10: Note: working-capital deltas not modelled line-by-line; FY26 CFO per AR reconciles with GCA less WC build. FCF here = pre-WC financing surplus.

Sheet Scenarios
B2: Scenarios - Base vs Stress (methodology variables: realisation/margin + volume)
B4: Metric | C4: Base FY28E | D4: Base FY31E | E4: Stress FY28E | F4: Stress FY31E
B5: Revenue | C5: ='Revenue Model'!G7 | D5: ='Revenue Model'!J7 | E5: ='Revenue Model'!E7*(1+Assumptions!C5+Assumptions!$C$15)*(1+Assumptions!D5+Assumptions!$C$15) | F5: =E5*(1+Assumptions!E5+Assumptions!$C$15)*(1+Assumptions!F5+Assumptions!$C$15)*(1+Assumptions!G5+Assumptions!$C$15)
B6: EBITDA | C6: ='Income Statement'!G6 | D6: ='Income Statement'!J6 | E6: =E5*(Assumptions!D6+Assumptions!$C$16) | F6: =F5*(Assumptions!G6+Assumptions!$C$16)
B7: Interest (approx, base debt path) | C7: ='Income Statement'!G10 | D7: ='Income Statement'!J10 | E7: ='Income Statement'!G10 | F7: ='Income Statement'!J10
B8: Interest coverage (x) | C8: =C6/C7 | D8: =D6/D7 | E8: =E6/E7 | F8: =F6/F7
B9: Net debt/EBITDA (x, base debt path) | C9: ='Balance Sheet'!G8/C6 | D9: ='Balance Sheet'!J8/D6 | E9: ='Balance Sheet'!G8/E6 | F9: ='Balance Sheet'!J8/F6
B11: Reading: under stress (growth -5pp, margin -250bps) FY28E coverage stays ~2.5-3x and net leverage ~2.5-3x - inside the covenant cap 3.75x but above mgmt ceiling 3.0x; capex flexibility (defer/phase) is the lever. FY25 trough (13.6% margin, 3.5x net) is the historical analogue.

Sheet DCF Inputs
B2: DCF inputs (hands off to valuation; used for financial flexibility only)
B4: Rs crore | C4: FY27E | D4: FY28E | E4: FY29E | F4: FY30E | G4: FY31E
B5: EBIT | C5: ='Income Statement'!F9 | D5: ='Income Statement'!G9 | E5: ='Income Statement'!H9 | F5: ='Income Statement'!I9 | G5: ='Income Statement'!J9
B6: NOPAT (25%) | C6: =C5*0.75 | D6: =D5*0.75 | E6: =E5*0.75 | F6: =F5*0.75 | G6: =G5*0.75
B7: + D&A - Capex | C7: ='Income Statement'!F8-Assumptions!C7 | D7: ='Income Statement'!G8-Assumptions!D7 | E7: ='Income Statement'!H8-Assumptions!E7 | F7: ='Income Statement'!I8-Assumptions!F7 | G7: ='Income Statement'!J8-Assumptions!G7
B8: UNLEVERED FCF (pre-WC) | C8: =C6+C7 | D8: =D6+D7 | E8: =E6+E7 | F8: =F6+F7 | G8: =G6+G7

Sheet Credit Ratios
B2: Credit ratios - CRISIL conventions (adjusted; acceptances shown both ways)
C4: FY25A | D4: FY26A | E4: FY27E | F4: FY28E | G4: FY29E | H4: FY30E | I4: FY31E
B5: Revenue growth % | C5: n.a. | D5: ='Revenue Model'!D8 | E5: ='Revenue Model'!E8 | F5: ='Revenue Model'!F8 | G5: ='Revenue Model'!G8 | H5: ='Revenue Model'!H8 | I5: ='Revenue Model'!I8 | J5: ='Revenue Model'!J8
B6: EBITDA margin % | C6: ='Income Statement'!C7 | D6: ='Income Statement'!D7 | E6: ='Income Statement'!E7 | F6: ='Income Statement'!F7 | G6: ='Income Statement'!G7 | H6: ='Income Statement'!H7 | I6: ='Income Statement'!I7 | J6: ='Income Statement'!J7
B7: EBIT margin % | C7: ='Income Statement'!C9/'Income Statement'!C5 | D7: ='Income Statement'!D9/'Income Statement'!D5 | E7: ='Income Statement'!E9/'Income Statement'!E5 | F7: ='Income Statement'!F9/'Income Statement'!F5 | G7: ='Income Statement'!G9/'Income Statement'!G5 | H7: ='Income Statement'!H9/'Income Statement'!H5 | I7: ='Income Statement'!I9/'Income Statement'!I5 | J7: ='Income Statement'!J9/'Income Statement'!J5
B8: Interest coverage - EBITDA/interest (x) | C8: ='Income Statement'!C6/'Income Statement'!C10 | D8: ='Income Statement'!D6/'Income Statement'!D10 | E8: ='Income Statement'!E6/'Income Statement'!E10 | F8: ='Income Statement'!F6/'Income Statement'!F10 | G8: ='Income Statement'!G6/'Income Statement'!G10 | H8: ='Income Statement'!H6/'Income Statement'!H10 | I8: ='Income Statement'!I6/'Income Statement'!I10 | J8: ='Income Statement'!J6/'Income Statement'!J10
B9: Gearing - Total debt/TNW (x) | C9: ='Balance Sheet'!C5/'Balance Sheet'!C9 | D9: ='Balance Sheet'!D5/'Balance Sheet'!D9 | E9: ='Balance Sheet'!E5/'Balance Sheet'!E9 | F9: ='Balance Sheet'!F5/'Balance Sheet'!F9 | G9: ='Balance Sheet'!G5/'Balance Sheet'!G9 | H9: ='Balance Sheet'!H5/'Balance Sheet'!H9 | I9: ='Balance Sheet'!I5/'Balance Sheet'!I9 | J9: ='Balance Sheet'!J5/'Balance Sheet'!J9
B10: Total debt/EBITDA (x) | C10: ='Balance Sheet'!C5/'Income Statement'!C6 | D10: ='Balance Sheet'!D5/'Income Statement'!D6 | E10: ='Balance Sheet'!E5/'Income Statement'!E6 | F10: ='Balance Sheet'!F5/'Income Statement'!F6 | G10: ='Balance Sheet'!G5/'Income Statement'!G6 | H10: ='Balance Sheet'!H5/'Income Statement'!H6 | I10: ='Balance Sheet'!I5/'Income Statement'!I6 | J10: ='Balance Sheet'!J5/'Income Statement'!J6
B11: Total debt incl acceptances/EBITDA (x) | C11: =('Balance Sheet'!C5+'Balance Sheet'!C6)/'Income Statement'!C6 | D11: =('Balance Sheet'!D5+'Balance Sheet'!D6)/'Income Statement'!D6 | E11: =('Balance Sheet'!E5+'Balance Sheet'!E6)/'Income Statement'!E6 | F11: =('Balance Sheet'!F5+'Balance Sheet'!F6)/'Income Statement'!F6 | G11: =('Balance Sheet'!G5+'Balance Sheet'!G6)/'Income Statement'!G6 | H11: =('Balance Sheet'!H5+'Balance Sheet'!H6)/'Income Statement'!H6 | I11: =('Balance Sheet'!I5+'Balance Sheet'!I6)/'Income Statement'!I6 | J11: =('Balance Sheet'!J5+'Balance Sheet'!J6)/'Income Statement'!J6
B12: Net debt/EBITDA (x) | C12: ='Balance Sheet'!C8/'Income Statement'!C6 | D12: ='Balance Sheet'!D8/'Income Statement'!D6 | E12: ='Balance Sheet'!E8/'Income Statement'!E6 | F12: ='Balance Sheet'!F8/'Income Statement'!F6 | G12: ='Balance Sheet'!G8/'Income Statement'!G6 | H12: ='Balance Sheet'!H8/'Income Statement'!H6 | I12: ='Balance Sheet'!I8/'Income Statement'!I6 | J12: ='Balance Sheet'!J8/'Income Statement'!J6
B13: NCA (GCA)/Total debt (x) | C13: ='Income Statement'!C16/'Balance Sheet'!C5 | D13: ='Income Statement'!D16/'Balance Sheet'!D5 | E13: ='Income Statement'!E16/'Balance Sheet'!E5 | F13: ='Income Statement'!F16/'Balance Sheet'!F5 | G13: ='Income Statement'!G16/'Balance Sheet'!G5 | H13: ='Income Statement'!H16/'Balance Sheet'!H5 | I13: ='Income Statement'!I16/'Balance Sheet'!I5 | J13: ='Income Statement'!J16/'Balance Sheet'!J5
B14: Net cash accruals (GCA) | C14: ='Income Statement'!C16 | D14: ='Income Statement'!D16 | E14: ='Income Statement'!E16 | F14: ='Income Statement'!F16 | G14: ='Income Statement'!G16 | H14: ='Income Statement'!H16 | I14: ='Income Statement'!I16 | J14: ='Income Statement'!J16
B15: Net debt | C15: ='Balance Sheet'!C8 | D15: ='Balance Sheet'!D8 | E15: ='Balance Sheet'!E8 | F15: ='Balance Sheet'!F8 | G15: ='Balance Sheet'!G8 | H15: ='Balance Sheet'!H8 | I15: ='Balance Sheet'!I8 | J15: ='Balance Sheet'!J8
B16: TOL/TNW (x) - historical only | C16: =1.86 | D16: =1.95 | E16: =1.56 | F16: n.a. | G16: n.a. | H16: n.a. | I16: n.a. | J16: n.a. | K16: From workpaper (TOL = TA - equity); forward TOL not modelled
B18: CRISIL labels: EBITDA (not OPBDIT/PBILDT); adjusted debt incl leases; acceptances shown both ways (agencies typically treat as debt for steel). RoCE FY26 10.5% per workpaper.
