Workbook

Sheet Inputs
B2: TVS Credit Services Limited - extracted line items (Consolidated, Rs crore)
B3: Yellow cells are EXTRACTED INPUTS traced to the source in the final column - nothing here is computed. Every downstream ratio references this sheet, so correcting a value here reflows the entire workbook.
B5: Line item | C5: FY2024 | D5: FY2025 | E5: FY2026 | F5: Source
B6: Interest income | C6: 5112.58 | D6: 5775.97 | E6: 6213.35 | F6: FY2026 AR L3115; FY24 FY2025 AR L2821
B7: Total income | C7: 5795.19 | D7: 6608.68 | E7: 7196 | F7: FY2026 AR L3120; FY24 FY2025 AR L2827
B8: Finance costs | D8: 1863.32 | E8: 1934.29 | F8: FY2026 AR L3122
B9: Fees and commission expense | D9: 527.16 | E9: 473.14 | F9: FY2026 AR L3123
B10: Impairment (credit cost) | C10: 1127.05 | D10: 1295.36 | E10: 1156.59 | F10: FY2026 AR L3124; FY24 FY2025 AR L2831
B11: Employee benefits expense | D11: 1135.58 | E11: 1274.23 | F11: FY2026 AR L3125
B12: Depreciation | D12: 46.2 | E12: 56.12 | F12: FY2026 AR L3126
B13: Other expenses | D13: 715.62 | E13: 1054.7 | F13: FY2026 AR L3127
B14: Total expenses | D14: 5583.24 | E14: 5949.07 | F14: FY2026 AR L3128
B15: PBT before exceptional | D15: 1025.44 | E15: 1246.93 | F15: FY2026 AR L3129
B16: Exceptional items | D16: 0 | E16: 8.61 | F16: FY2026 AR L7670 CONSOLIDATED. Standalone line reads '861' - OCR dropped the decimal point.
B17: Profit after tax | C17: 571.83 | D17: 767.25 | E17: 913.17 | F17: FY2026 AR L3133; FY24 FY2025 AR L2842
B18: Total assets | C18: 28137.55 | D18: 31043.7 | E18: 35068.09 | F18: FY2026 AR L3063; FY24 FY2025 AR L2762
B19: Total equity (net worth) | D19: 4947.92 | E19: 6067.63 | F19: FY2026 AR L5940
B20: Total borrowings | D20: 24687.17 | E20: 27667.87 | F20: FY2026 AR L5903
B21: Net debt | D21: 21103.76 | E21: 24340.37 | F21: FY2026 AR L5939
B22: CRAR (%) | D22: 20.3 | E22: 19.44 | F22: FY2026 AR L6325 - per RBI guidelines
B23: Tier I CRAR (%) | D23: 15.84 | E23: 16.49 | F23: FY2026 AR L6326
B24: Tier II CRAR (%) | D24: 4.46 | E24: 2.95 | F24: FY2026 AR L6327
B25: Top-10 borrowings / total (%) | D25: 77.34 | E25: 70.68 | F25: FY2026 AR L6761
B26: PDI as % of Tier I | D26: 2.25 | E26: 1.84 | F26: FY2026 AR L6946
B27: Parent shareholding (%) | E27: 85.63 | F27: FY2026 AR - TVS Motor Company Ltd

Sheet RatioSuite
B2: TVS Credit Services Limited - ratio suite (Consolidated, Rs crore; agency conventions applied)
B3: Every value is a LIVE FORMULA referencing the Inputs sheet - click any cell to see the arithmetic. 'Calculation' states the same formula in words; 'Convention' records the definitional choice (lease treatment, normalisation, netting) so the basis is auditable.
B5: Ratio | C5: FY2024 | D5: FY2025 | E5: FY2026 | F5: Calculation | G5: Convention / note
B6: Net interest income | C6: =Inputs!C6-Inputs!C8 -> 5112.58 | D6: =Inputs!D6-Inputs!D8 -> 3912.65 | E6: =Inputs!E6-Inputs!E8 -> 4279.06 | F6: Interest income less finance costs
B7: NII / avg total assets (%) | C7: =(Inputs!C6-Inputs!C8)/AVERAGE(Inputs!C18,OFFSET(Inputs!C18,0,-1)) | D7: =(Inputs!D6-Inputs!D8)/AVERAGE(Inputs!D18,OFFSET(Inputs!D18,0,-1)) | E7: =(Inputs!E6-Inputs!E8)/AVERAGE(Inputs!E18,OFFSET(Inputs!E18,0,-1)) | F7: Spread earned on the book - high, reflecting two-wheeler/used-vehicle/tractor yields
B8: RoAA (%) [SECTOR-DEFINING] | C8: =Inputs!C17/AVERAGE(Inputs!C18,OFFSET(Inputs!C18,0,-1)) | D8: =Inputs!D17/AVERAGE(Inputs!D18,OFFSET(Inputs!D18,0,-1)) | E8: =Inputs!E17/AVERAGE(Inputs!E18,OFFSET(Inputs!E18,0,-1)) | F8: Return on average assets - the core NBFC profitability metric
B9: RoAE (%) | C9: =Inputs!C17/AVERAGE(Inputs!C19,OFFSET(Inputs!C19,0,-1)) | D9: =Inputs!D17/AVERAGE(Inputs!D19,OFFSET(Inputs!D19,0,-1)) | E9: =Inputs!E17/AVERAGE(Inputs!E19,OFFSET(Inputs!E19,0,-1)) | F9: Return on average net worth
B10: Credit cost / avg assets (%) [SECTOR-DEFINING] | C10: =Inputs!C10/AVERAGE(Inputs!C18,OFFSET(Inputs!C18,0,-1)) | D10: =Inputs!D10/AVERAGE(Inputs!D18,OFFSET(Inputs!D18,0,-1)) | E10: =Inputs!E10/AVERAGE(Inputs!E18,OFFSET(Inputs!E18,0,-1)) | F10: Impairment charge over average assets - the key asset-quality proxy
B11: Gearing - borrowings / net worth (x) [SECTOR-DEFINING] | C11: =Inputs!C20/Inputs!C19 | D11: =Inputs!D20/Inputs!D19 -> 4.9894036 | E11: =Inputs!E20/Inputs!E19 -> 4.5599138 | F11: Leverage. For a wholesale-funded NBFC this carries the weight CASA does for a bank
B12: Net debt / equity (x) | C12: =Inputs!C21/Inputs!C19 | D12: =Inputs!D21/Inputs!D19 -> 4.2651781 | E12: =Inputs!E21/Inputs!E19 -> 4.0115119 | F12: Reproduces the company's own published measure - a tie-out on the extraction
B13: Operating expenses | C13: =Inputs!C11+Inputs!C12+Inputs!C13 -> 0 | D13: =Inputs!D11+Inputs!D12+Inputs!D13 -> 1897.4 | E13: =Inputs!E11+Inputs!E12+Inputs!E13 -> 2385.05 | F13: Employee + depreciation + other expenses
B14: Net total income | C14: =Inputs!C7-Inputs!C8-Inputs!C9 -> 5795.19 | D14: =Inputs!D7-Inputs!D8-Inputs!D9 -> 4218.2 | E14: =Inputs!E7-Inputs!E8-Inputs!E9 -> 4788.57 | F14: Income net of funding and origination costs
B15: Cost-to-income (%) | C15: =(Inputs!C11+Inputs!C12+Inputs!C13)/(Inputs!C7-Inputs!C8-Inputs!C9) -> 0 | D15: =(Inputs!D11+Inputs!D12+Inputs!D13)/(Inputs!D7-Inputs!D8-Inputs!D9) -> 0.44981272 | E15: =(Inputs!E11+Inputs!E12+Inputs!E13)/(Inputs!E7-Inputs!E8-Inputs!E9) -> 0.49807145 | F15: THE FY2026 NEGATIVE: rose to 49.81% from 44.98%
B16: CRAR cross-check (Tier I + Tier II) | C16: =Inputs!C23+Inputs!C24 -> 0 | D16: =Inputs!D23+Inputs!D24 -> 20.3 | E16: =Inputs!E23+Inputs!E24 -> 19.44 | F16: Must equal reported CRAR - independent reconstruction of the capital stack
B17: CRAR buffer over RBI 15% minimum (pp) | C17: =Inputs!C22-15 -> -15 | D17: =Inputs!D22-15 -> 5.3 | E17: =Inputs!E22-15 -> 4.44 | F17: Reported CRAR less the 15% minimum applicable to the company
B18: Total income growth (%) | C18: =Inputs!C7/OFFSET(Inputs!C7,0,-1)-1 | D18: =Inputs!D7/OFFSET(Inputs!D7,0,-1)-1 | E18: =Inputs!E7/OFFSET(Inputs!E7,0,-1)-1 | F18: YoY growth in total income
B19: PAT growth (%) | C19: =Inputs!C17/OFFSET(Inputs!C17,0,-1)-1 | D19: =Inputs!D17/OFFSET(Inputs!D17,0,-1)-1 | E19: =Inputs!E17/OFFSET(Inputs!E17,0,-1)-1 | F19: YoY growth in profit after tax

Sheet TieOut
B2: TVS Credit Services Limited - tie-out to company-disclosed figures
B3: Binding gate (CLAUDE.md Step 6): headline computed figures must reconcile to the company's OWN disclosed numbers before the workpaper is issued. PASS/FAIL is itself a formula - it re-evaluates if any input changes.
B5: Check | C5: Computed | D5: Company-disclosed | E5: Result | F5: Note
B6: FY26 CRAR = Tier I + Tier II | C6: =Inputs!E23+Inputs!E24 -> 19.44 | D6: 19.44 | E6: =IF(ABS(C6-D6)<=MAX(1,ABS(D6)*0.005),"PASS","CHECK") | F6: 16.49 + 2.95; reported CRAR 19.44% - exact reconstruction of the capital stack
B7: FY26 total expenses = sum of components | C7: =Inputs!E8+Inputs!E9+Inputs!E10+Inputs!E11+Inputs!E12+Inputs!E13 -> 5949.07 | D7: 5949.07 | E7: =IF(ABS(C7-D7)<=MAX(1,ABS(D7)*0.005),"PASS","CHECK") | F7: Six expense lines rebuild the reported total exactly
B8: FY26 PBT = total income - total expenses | C8: =Inputs!E7-Inputs!E14 -> 1246.93 | D8: 1246.93 | E8: =IF(ABS(C8-D8)<=MAX(1,ABS(D8)*0.005),"PASS","CHECK") | F8: Reported PBT before exceptional items - exact
B9: FY26 net debt / equity | C9: =Inputs!E21/Inputs!E19 -> 4.0115119 | D9: 4.01 | E9: =IF(ABS(C9-D9)<=MAX(1,ABS(D9)*0.005),"PASS","CHECK") | F9: Reproduces the company's own published 4.01x
B10: FY25 net debt / equity | C10: =Inputs!D21/Inputs!D19 -> 4.2651781 | D10: 4.27 | E10: =IF(ABS(C10-D10)<=MAX(1,ABS(D10)*0.005),"PASS","CHECK") | F10: Reproduces the company's own published 4.27x
B11: FY26 exceptional item / PBT | C11: =Inputs!E16/Inputs!E15 -> 0.0069049586 | D11: 0.0069 | E11: =IF(ABS(C11-D11)<=MAX(1,ABS(D11)*0.005),"PASS","CHECK") | F11: 0.69% of PBT - immaterial. Confirms the standalone '861' is an OCR decimal-point loss, not a Rs 861 crore item
B13: Tolerance: 0.5% of the disclosed figure, floor Rs 1 - tighter than rounding, loose enough for basis differences.

Sheet RatingScore
B2: TVS Credit Services Limited - rating scorecard and view
B3: Factor scores 1 (strongest) to 6 (weakest), weighted to a composite. The anchor is a SCREENING cross-check with a +/-2 notch band, NOT the rating - the analyst view and any divergence are stated below and the divergence must be explained, never buried.
B5: Rating factor | C5: Score (1-6) | D5: Weight | E5: Weighted | F5: Justification
B6: Parent support - TVS Motor Company Limited | C6: 1 | D6: 0.4 | E6: =C6*D6 -> 0.4 | F6: TVS Motor held 85.63% as on 31-Mar-2026. Captive financing arm of the TVS group: shared brand, dealer-network origination, and a strategic role in supporting vehicle sales. Support expected on an ongoing basis and in distress. This factor, not the standalone profile, is what carries the rating into the AA category.
B7: Profitability | C7: 2 | D7: 0.2 | E7: =C7*D7 -> 0.4 | F7: RoAA improved to 2.76% from 2.59%; PAT Rs 913.17 crore, up 19.02% after 34.17% growth in FY2025. NII of Rs 4,279.06 crore is 12.94% of average assets. Strong in absolute terms, but the quality of the FY2026 improvement is mixed - it came from a falling credit cost while the operating cost ratio deteriorated.
B8: Capitalisation and leverage | C8: 2 | D8: 0.2 | E8: =C8*D8 -> 0.4 | F8: Gearing down to 4.56x from 4.99x; net worth Rs 6,067.63 crore. Tier I CRAR up to 16.49% from 15.84%, against a 15% total-CRAR regulatory minimum. Perpetual instruments are only 1.84% of Tier I, so the base is high quality. Total CRAR nonetheless eased to 19.44% from 20.30% as Tier II amortised.
B9: Asset quality | C9: 3 | D9: 0.1 | E9: =C9*D9 -> 0.3 | F9: Credit cost 3.50% of average assets, improved from 4.38% but high in absolute terms and structural to two-wheeler, used-vehicle and tractor lending. Gross/net stage 3 ratios were NOT located in the documents reviewed, so this factor is scored on the impairment charge alone - a genuine evidence gap, recorded rather than filled with an assumption.
B10: Funding profile | C10: 3 | D10: 0.1 | E10: =C10*D10 -> 0.3 | F10: Wholesale funded with no deposit franchise. Top-10 borrowings 70.68% of total, improved from 77.34% but still concentrated. ECB and NCD issuance during FY2026 is diversifying the mix.
B11: Weight check (must be 100%) | D11: =SUM(D6:D10) -> 1 | E11: =SUM(E6:E10) -> 1.8 | F11: =IF(ABS(D11-1)<0.001,"weights sum to 100%","ERROR: weights must sum to 100%")
B13: Weighted composite score | C13: =E11 -> 1.8
B14: Indicative anchor grade (screening only, +/-2 band) | C14: AA band (composite 1.80)
B15: ANALYST RATING VIEW | C15: [ICRA]AA+ (Stable) / [ICRA]A1+; perpetual debt [ICRA]AA (Stable)
B16: Divergence from anchor - explanation | C16: No divergence. The issuer's own FY2026 annual report discloses ICRA's outstanding ratings as AA+ (Stable) on long-term bank facilities and subordinated debt, A1+ on short-term facilities and commercial paper, and AA (Stable) on perpetual debt - matching this assessment including the one-notch hybrid notch-down, which was applied here BEFORE the disclosure table was read, on the SBI Additional Tier 1 precedent from 14-Aug-2026. No TVS Credit rationale exists in the reference library; the anchor is the issuer's own Step 7b disclosure.
