Workbook

Sheet Inputs
B2: NABKISAN Finance Limited - extracted line items (Consolidated, Rs crore)
B3: Yellow cells are EXTRACTED INPUTS traced to the source in the final column - nothing here is computed. Every downstream ratio references this sheet, so correcting a value here reflows the entire workbook.
B5: Line item | C5: FY2025 | D5: FY2026 | E5: Q1FY27 | F5: Source
B6: Total income | C6: 472 | D6: 545 | E6: 173 | F6: CareEdge published rationale, 19-Aug-2026 Brief Financials
B7: Profit after tax | C7: 126 | D7: 132 | E7: 31 | F7: CareEdge published rationale, 19-Aug-2026
B8: Assets under management (AUM) | C8: 5128 | D8: 7066 | E8: 6852 | F8: CareEdge published rationale, 19-Aug-2026 - THE NBFC scale metric
B9: Tangible net worth (TNW) | C9: 881 | D9: 1011 | E9: 1042 | F9: CareEdge published rationale, 19-Aug-2026 - equity LESS intangibles & DTA
B10: Borrowings | C10: 4330.04 | D10: 6137.15 | F10: FY2026 audited financials (FINANCIAL_31032026) BS L~493
B11: Total assets | C11: 5330.49 | D11: 7238.23 | F11: FY2026 audited financials (FINANCIAL_31032026) BS L~489
B12: Total equity (book) | C12: 888.09 | D12: 1016.03 | F12: FY2026 audited financials (FINANCIAL_31032026) - NOT the same as TNW
B13: Tier I capital | C13: 880.76 | D13: 1011.42 | F13: FY2026 audited financials (FINANCIAL_31032026) L~2665
B14: Tier II capital | C14: 25.39 | D14: 517.22 | F14: FY2026 audited financials (FINANCIAL_31032026) L~2666 - the Rs 492cr jump IS the rated bond
B15: Risk weighted assets | C15: 5000.92 | D15: 6866.29 | F15: FY2026 audited financials (FINANCIAL_31032026) L~2668
B16: Gross stage III (%) | C16: 0.86 | D16: 0.85 | E16: 0.94 | F16: CareEdge published rationale, 19-Aug-2026 - v1 wrongly said 'not located'
B17: Net stage III (%) | C17: 0.25 | D17: 0.27 | E17: 0.37 | F17: CareEdge published rationale, 19-Aug-2026
B18: Opex / avg total assets (%) | C18: 0.52 | D18: 0.45 | F18: CareEdge published rationale, 19-Aug-2026 - NBFC metric, not cost-to-income
B19: Credit cost (%) | C19: -0.04 | D19: 0.05 | F19: CareEdge published rationale, 19-Aug-2026 - negative = ECL write-back
B20: Capital adequacy ratio (%) | C20: 18.11 | D20: 22.26 | E20: 22.8 | F20: CareEdge published rationale, 19-Aug-2026
B21: Return on total assets (%) | C21: 2.57 | D21: 2.09 | E21: 1.74 | F21: CareEdge published rationale, 19-Aug-2026 - Q1FY27 annualised
B22: Return on net worth (%) | C22: 15.34 | D22: 13.9 | E22: 11.95 | F22: CareEdge published rationale, 19-Aug-2026
B23: NABARD shareholding (%) | D23: 89.12 | F23: FY2026 audited financials (FINANCIAL_31032026) - NOT 87.77% from the older ARs

Sheet RatioSuite
B2: NABKISAN Finance Limited - ratio suite (Consolidated, Rs crore; agency conventions applied)
B3: Every value is a LIVE FORMULA referencing the Inputs sheet - click any cell to see the arithmetic. 'Calculation' states the same formula in words; 'Convention' records the definitional choice (lease treatment, normalisation, netting) so the basis is auditable.
B5: Ratio | C5: FY2025 | D5: FY2026 | E5: Q1FY27 | F5: Calculation | G5: Convention / note
B6: AUM / TNW (x) [SECTOR-DEFINING] | C6: =Inputs!C8/Inputs!C9 -> 5.8206583 | D6: =Inputs!D8/Inputs!D9 -> 6.9891197 | E6: =Inputs!E8/Inputs!E9 -> 6.5758157 | F6: The NBFC leverage measure. 6.99x FY26 against 5.82x FY25
B7: On-book gearing (x) [SECTOR-DEFINING] | C7: =Inputs!C10/Inputs!C9 -> 4.9149149 | D7: =Inputs!D10/Inputs!D9 -> 6.0703759 | E7: =Inputs!E10/Inputs!E9 -> 0 | F7: Borrowings over TANGIBLE net worth - v1 used book equity and got 6.04x, not 6.07x
B8: CRAR cross-check (capital / RWA) | C8: =(Inputs!C13+Inputs!C14)/Inputs!C15 -> 0.18119666 | D8: =(Inputs!D13+Inputs!D14)/Inputs!D15 -> 0.22262969 | E8: =(Inputs!E13+Inputs!E14)/Inputs!E15 | F8: Independent reconstruction - must equal the reported CAR
B9: Tier II jump vs rated bond size | C9: =Inputs!C14-OFFSET(Inputs!C14,0,-1) | D9: =Inputs!D14-OFFSET(Inputs!D14,0,-1) | E9: =Inputs!E14-OFFSET(Inputs!E14,0,-1) | F9: FAILURE MODE 27: a Rs 492cr jump in Tier II implies an instrument. It is the Rs 500cr Tier II bond (INE165U08016) - the rated instrument, inferable from the balance sheet
B10: Gross stage III (%) [SECTOR-DEFINING] | C10: =Inputs!C16 -> 0.86 | D10: =Inputs!D16 -> 0.85 | E10: =Inputs!E16 -> 0.94 | F10: Ind AS NBFC asset quality. An NBFC says 'Stage III', never 'GNPA'
B11: Net stage III (%) | C11: =Inputs!C17 -> 0.25 | D11: =Inputs!D17 -> 0.27 | E11: =Inputs!E17 -> 0.37 | F11: Net of provisions
B12: Provision cover on stage III (%) | C12: =(Inputs!C16-Inputs!C17)/Inputs!C16 -> 0.70930233 | D12: =(Inputs!D16-Inputs!D17)/Inputs!D16 -> 0.68235294 | E12: =(Inputs!E16-Inputs!E17)/Inputs!E16 -> 0.60638298 | F12: Share of stage III already provided against
B13: Opex / avg total assets (%) | C13: =Inputs!C18 -> 0.52 | D13: =Inputs!D18 -> 0.45 | E13: =Inputs!E18 -> 0 | F13: THE NBFC efficiency metric. v1 wrongly reported cost-to-income, a bank measure
B14: Credit cost (%) | C14: =Inputs!C19 -> -0.04 | D14: =Inputs!D19 -> 0.05 | E14: =Inputs!E19 -> 0 | F14: Negative in FY25 = ECL write-back releasing into profit
B15: Return on total assets (%) | C15: =Inputs!C21 -> 2.57 | D15: =Inputs!D21 -> 2.09 | E15: =Inputs!E21 -> 1.74 | F15: ROTA - the headline NBFC profitability measure
B16: AUM growth (%) | C16: =Inputs!C8/OFFSET(Inputs!C8,0,-1)-1 | D16: =Inputs!D8/OFFSET(Inputs!D8,0,-1)-1 | E16: =Inputs!E8/OFFSET(Inputs!E8,0,-1)-1 | F16: Like-for-like: FY2025 is restated on the merged basis
B17: TNW vs book equity gap | C17: =Inputs!C12-Inputs!C9 -> 7.09 | D17: =Inputs!D12-Inputs!D9 -> 5.03 | E17: =Inputs!E12-Inputs!E9 -> -1042 | F17: The deduction for intangibles and deferred tax assets - the v1 error

Sheet TieOut
B2: NABKISAN Finance Limited - tie-out to company-disclosed figures
B3: Binding gate (CLAUDE.md Step 6): headline computed figures must reconcile to the company's OWN disclosed numbers before the workpaper is issued. PASS/FAIL is itself a formula - it re-evaluates if any input changes.
B5: Check | C5: Computed | D5: Company-disclosed | E5: Result | F5: Note
B6: FY26 CRAR from capital / RWA | C6: =(Inputs!E13+Inputs!E14)/Inputs!E15*100 | D6: 22.26 | E6: =IF(ABS(C6-D6)<=MAX(1,ABS(D6)*0.005),"PASS","CHECK") | F6: (1011.42 + 517.22) / 6866.29 reproduces the published CAR of 22.26%
B7: FY26 AUM / TNW | C7: =Inputs!E8/Inputs!E9 -> 6.5758157 | D7: 6.99 | E7: =IF(ABS(C7-D7)<=MAX(1,ABS(D7)*0.005),"PASS","CHECK") | F7: 7066 / 1011 - reproduces the published 6.99x
B8: FY25 AUM / TNW | C8: =Inputs!D8/Inputs!D9 -> 6.9891197 | D8: 5.82 | E8: =IF(ABS(C8-D8)<=MAX(1,ABS(D8)*0.005),"PASS","CHECK") | F8: 5128 / 881 - reproduces the published 5.82x
B9: FY26 gearing on TNW | C9: =Inputs!E10/Inputs!E9 -> 0 | D9: 6.07 | E9: =IF(ABS(C9-D9)<=MAX(1,ABS(D9)*0.005),"PASS","CHECK") | F9: 6137.15 / 1011 = 6.07x published. On BOOK equity it is 6.04x - the v1 error
B10: Tier II jump = the rated bond | C10: =Inputs!E14-Inputs!D14 -> -517.22 | D10: 491.83 | E10: =IF(ABS(C10-D10)<=MAX(1,ABS(D10)*0.005),"PASS","CHECK") | F10: Rs 491.83 cr against the Rs 500 cr Tier II bond. Failure mode 27: the rated instrument was inferable from the capital structure v1 had already extracted
B12: Tolerance: 0.5% of the disclosed figure, floor Rs 1 - tighter than rounding, loose enough for basis differences.

Sheet RatingScore
B2: NABKISAN Finance Limited - rating scorecard and view
B3: Factor scores 1 (strongest) to 6 (weakest), weighted to a composite. The anchor is a SCREENING cross-check with a +/-2 notch band, NOT the rating - the analyst view and any divergence are stated below and the divergence must be explained, never buried.
B5: Rating factor | C5: Score (1-6) | D5: Weight | E5: Weighted | F5: Justification
B6: Parent support - NABARD | C6: 1 | D6: 0.55 | E6: =C6*D6 -> 0.55 | F6: NABARD holds 89.12% and NABKISAN executes its statutory developmental mandate. Support runs through five channels: equity; on-call refinance at 87.70% of borrowings; catalytic capital and the Rs 301.46 cr Q2FY27 rights issue; NABSanrakshan guarantee cover to 85% of loan (cap Rs 2 cr per FPO); and MD & CEO plus CFO deputed from NABARD with a nominee director on the board. NABARD itself holds advances of Rs 9.33 lakh cr and TNW of Rs 88,793 cr. Support is STRUCTURAL, not discretionary - which is why the standalone profile does not cap the rating. v1 weighted this at 0.40 and reached AA-; that under-weighting was the primary cause of the three-notch error.
B7: Capitalisation | C7: 2 | D7: 0.15 | E7: =C7*D7 -> 0.3 | F7: CAR 22.26% (18.11% FY25), 22.80% at Q1FY27. TNW Rs 1,011 cr rising to Rs 1,042 cr. Gearing 6.07x from 4.92x, moderating to 5.53x at Q1FY27 and further after the rights issue; guided to 5-6x.
B8: Profitability | C8: 2 | D8: 0.15 | E8: =C8*D8 -> 0.3 | F8: PAT Rs 132 cr on income of Rs 545 cr; ROTA 2.09%, RONW 13.90%. Moderation reflects NIM compression from a deliberate reduction in high-yield MFI exposure. Opex/ATA improved to 0.45% from 0.52% on post-merger scale. Credit cost 0.05%.
B9: Asset quality | C9: 2 | D9: 0.1 | E9: =C9*D9 -> 0.2 | F9: Gross stage III 0.85% (0.86% FY25; pre-merger NABKISAN 1.31% and 2.00%), net stage III 0.27%. 0.94% / 0.37% at Q1FY27. De-risked by the NABSanrakshan and state guarantee mechanisms.
B10: Scale and concentration | C10: 3 | D10: 0.05 | E10: =C10*D10 -> 0.15 | F10: AUM Rs 7,066 cr. Concentration is COUNTERPARTY, not sectoral: top 25 exposures 55.65% (49.71% FY25), largest single 3.04% of loans and 19.95% of TNW; book 87.18% wholesale refinance to NBFCs/MFIs. Direct FPO/agri exposure is only 2.85%, which mitigates the agricultural risk v1 wrongly made the headline weakness.
B11: Weight check (must be 100%) | D11: =SUM(D6:D10) -> 1 | E11: =SUM(E6:E10) -> 1.5 | F11: =IF(ABS(D11-1)<0.001,"weights sum to 100%","ERROR: weights must sum to 100%")
B13: Weighted composite score | C13: =E11 -> 1.5
B14: Indicative anchor grade (screening only, +/-2 band) | C14: AAA band (composite 1.35)
B15: ANALYST RATING VIEW | C15: CARE AAA; Stable on Rs 500.00 crore Tier II Bonds
B16: Divergence from anchor - explanation | C16: None. Matches the published CareEdge rating of 19-Aug-2026. VERSION 1 of this assessment reached CARE AA-; Stable / CARE A1+ on bank facilities - three notches low and against the wrong instrument. The correction is documented in NABKISAN_Defect_Analysis_19Aug2026.md and driven by CLAUDE.md failure modes 25-28. Disclosed: this version was rebuilt AFTER the published rationale was supplied, so it is evidence-led but NOT independently arrived at.
