Workbook

Sheet Inputs
B2: Yasho Industries Limited - extracted line items (Consolidated, Rs crore)
B3: Yellow cells are EXTRACTED INPUTS traced to the source in the final column - nothing here is computed. Every downstream ratio references this sheet, so correcting a value here reflows the entire workbook.
B5: Line item | C5: FY2024 | D5: FY2025 | E5: FY2026 | F5: Source
B6: Revenue from operations | C6: 595.7 | D6: 675.64 | E6: 830.03 | F6: FY26 AR, consolidated/standalone as noted P&L L8550 (consol); FY24 standalone
B7: EBITDA (as disclosed) | C7: 106.67 | D7: 119.4 | E7: 144.46 | F7: FY26 AR MD&A 'Key Financials' L1226-1276; FY24 derived PBT+D+I
B8: Profit before tax | C8: 76.34 | D8: 8.34 | E8: 33.97 | F8: FY26 AR, consolidated/standalone as noted consolidated P&L
B9: PAT (consolidated) | C9: 57.12 | D9: 6.02 | E9: 25.26 | F9: FY26 AR, consolidated/standalone as noted consolidated P&L L8589
B10: Depreciation & amortisation | C10: 15.62 | D10: 50.06 | E10: 54.77 | F10: FY26 AR, consolidated/standalone as noted P&L L5261
B11: Finance costs | C11: 14.71 | D11: 58.81 | E11: 55.56 | F11: FY26 AR, consolidated/standalone as noted P&L
B12: Borrowings - non current | C12: 333.65 | D12: 324.45 | E12: 289.13 | F12: FY26 AR, consolidated/standalone as noted BS Note 15
B13: Borrowings - current | C13: 214.79 | D13: 234.07 | E13: 251.81 | F13: FY26 AR, consolidated/standalone as noted BS Note 20
B14: Lease liabilities - non current | C14: 21.11 | D14: 12.48 | E14: 6.74 | F14: FY26 AR, consolidated/standalone as noted BS
B15: Lease liabilities - current | C15: 9.49 | D15: 11.56 | E15: 10.25 | F15: FY26 AR, consolidated/standalone as noted BS
B16: Total equity (networth) | C16: 293.36 | D16: 420.6 | E16: 441.31 | F16: FY26 AR, consolidated/standalone as noted BS; FY25 incl Rs 125cr pref allotment
B17: Total assets | C17: 991.68 | D17: 1093.34 | E17: 1160.12 | F17: FY26 AR, consolidated/standalone as noted BS
... B22: Capital expenditure (cash) | C22: 336.99 | D22: 11.15 | E22: 73.84 | F22: FY26 AR, consolidated/standalone as noted CFS investing; FY24 = Pakhajan greenfield
B23: Director/KMP unsecured loans | D23: 48.51 | E23: 47 | F23: FY26 AR, consolidated/standalone as noted RPT note - CRISIL Box 1 treatment applies
B24: Capacity utilisation (Pakhajan) | E24: 0.6 | F24: Q4FY26 deck narrative ~60%; >65% in Q1FY27

Sheet RatioSuite
B2: Yasho Industries Limited - ratio suite (Consolidated, Rs crore; agency conventions applied)
B3: Every value is a LIVE FORMULA referencing the Inputs sheet - click any cell to see the arithmetic. 'Calculation' states the same formula in words; 'Convention' records the definitional choice (lease treatment, normalisation, netting) so the basis is auditable.
B5: Ratio | C5: FY2024 | D5: FY2025 | E5: FY2026 | F5: Calculation | G5: Convention / note
B6: EBITDA margin % | C6: =Inputs!C7/Inputs!C6 -> 0.17906664 | D6: =Inputs!D7/Inputs!D6 -> 0.17672133 | E6: =Inputs!E7/Inputs!E6 -> 0.1740419 | F6: EBITDA / operating revenue
B7: PAT margin % | C7: =Inputs!C9/Inputs!C6 -> 0.095887192 | D7: =Inputs!D9/Inputs!D6 -> 0.0089100705 | E7: =Inputs!E9/Inputs!E6 -> 0.030432635 | F7: PAT / operating revenue - CRISIL's KI-table convention
B8: Borrowings (excl leases) | C8: =(Inputs!C12+Inputs!C13) -> 548.44 | D8: =(Inputs!D12+Inputs!D13) -> 558.52 | E8: =(Inputs!E12+Inputs!E13) -> 540.94 | F8: Non-current + current borrowings
B9: Lease liabilities | C9: =(Inputs!C14+Inputs!C15) -> 30.6 | D9: =(Inputs!D14+Inputs!D15) -> 24.04 | E9: =(Inputs!E14+Inputs!E15) -> 16.99 | F9: Ind AS 116 lease liabilities
B10: CRISIL adjusted debt | C10: =((Inputs!C12+Inputs!C13)+(Inputs!C14+Inputs!C15)) -> 579.04 | D10: =((Inputs!D12+Inputs!D13)+(Inputs!D14+Inputs!D15)) -> 582.56 | E10: =((Inputs!E12+Inputs!E13)+(Inputs!E14+Inputs!E15)) -> 557.93 | F10: CRISIL adjusted-debt convention includes lease liabilities
B11: Gearing (adj debt / adj NW) x | C11: =((Inputs!C12+Inputs!C13)+(Inputs!C14+Inputs!C15))/Inputs!C16 -> 1.9738206 | D11: =((Inputs!D12+Inputs!D13)+(Inputs!D14+Inputs!D15))/Inputs!D16 -> 1.3850689 | E11: =((Inputs!E12+Inputs!E13)+(Inputs!E14+Inputs!E15))/Inputs!E16 -> 1.2642587 | F11: CRISIL core ratio 1: adjusted total debt / adjusted networth
B12: TOL / TNW x | C12: =(Inputs!C17-Inputs!C16)/Inputs!C16 -> 2.38042 | D12: =(Inputs!D17-Inputs!D16)/Inputs!D16 -> 1.5994769 | E12: =(Inputs!E17-Inputs!E16)/Inputs!E16 -> 1.6288097 | F12: CRISIL core ratio 2: total outside liabilities / adjusted networth
B13: Adjusted debt / EBITDA x | C13: =((Inputs!C12+Inputs!C13)+(Inputs!C14+Inputs!C15))/Inputs!C7 -> 5.4283304 | D13: =((Inputs!D12+Inputs!D13)+(Inputs!D14+Inputs!D15))/Inputs!D7 -> 4.879062 | E13: =((Inputs!E12+Inputs!E13)+(Inputs!E14+Inputs!E15))/Inputs!E7 -> 3.8621764 | F13: CRISIL case-to-case alternative to NCATD
B14: Interest coverage (PBDIT/int) x | C14: =Inputs!C7/Inputs!C11 -> 7.2515296 | D14: =Inputs!D7/Inputs!D11 -> 2.030267 | E14: =Inputs!E7/Inputs!E11 -> 2.600072 | F14: CRISIL core ratio 3: PBDIT / interest and finance charges
B15: EBIT / interest x [MD&A basis] | C15: =(Inputs!C7-Inputs!C10)/Inputs!C11 -> 6.1896669 | D15: =(Inputs!D7-Inputs!D10)/Inputs!D11 -> 1.1790512 | E15: =(Inputs!E7-Inputs!E10)/Inputs!E11 -> 1.6142909 | F15: Company's own MD&A convention - reconciles to disclosed 1.61x FY26
B16: NCATD % | C16: =(Inputs!C9+Inputs!C10)/((Inputs!C12+Inputs!C13)+(Inputs!C14+Inputs!C15)) -> 0.12562172 | D16: =(Inputs!D9+Inputs!D10)/((Inputs!D12+Inputs!D13)+(Inputs!D14+Inputs!D15)) -> 0.096264762 | E16: =(Inputs!E9+Inputs!E10)/((Inputs!E12+Inputs!E13)+(Inputs!E14+Inputs!E15)) -> 0.14344093 | F16: CRISIL core ratio: net cash accrual / adjusted total debt
B17: RoCE % | C17: =(Inputs!C7-Inputs!C10)/(((Inputs!C12+Inputs!C13)+(Inputs!C14+Inputs!C15))+Inputs!C16) -> 0.10436726 | D17: =(Inputs!D7-Inputs!D10)/(((Inputs!D12+Inputs!D13)+(Inputs!D14+Inputs!D15))+Inputs!D16) -> 0.069121576 | E17: =(Inputs!E7-Inputs!E10)/(((Inputs!E12+Inputs!E13)+(Inputs!E14+Inputs!E15))+Inputs!E16) -> 0.089758216 | F17: PBIT / (total debt + adjusted networth)
B18: Receivable days | C18: =365*Inputs!C18/Inputs!C6 -> 76.412876 | D18: =365*Inputs!D18/Inputs!D6 -> 79.651294 | E18: =365*Inputs!E18/Inputs!E6 -> 88.797333 | F18: 365 x trade receivables / revenue
B19: Inventory days | C19: =365*Inputs!C19/Inputs!C6 -> 76.566057 | D19: =365*Inputs!D19/Inputs!D6 -> 132.42622 | E19: =365*Inputs!E19/Inputs!E6 -> 103.36163 | F19: 365 x inventories / revenue
B20: Payable days | C20: =365*Inputs!C20/Inputs!C6 -> 29.331123 | D20: =365*Inputs!D20/Inputs!D6 -> 33.915547 | E20: =365*Inputs!E20/Inputs!E6 -> 42.747431 | F20: 365 x trade payables / revenue
B21: Net working capital days | C21: =365*(Inputs!C18+Inputs!C19-Inputs!C20)/Inputs!C6 -> 123.64781 | D21: =365*(Inputs!D18+Inputs!D19-Inputs!D20)/Inputs!D6 -> 178.16196 | E21: =365*(Inputs!E18+Inputs!E19-Inputs!E20)/Inputs!E6 -> 149.41153 | F21: THE sector-critical metric - working capital intensity (company: 190->143 days Q1FY27)
B22: Free cash flow | C22: =Inputs!C21-Inputs!C22 -> -247 | D22: =Inputs!D21-Inputs!D22 -> 33.88 | E22: =Inputs!E21-Inputs!E22 -> 77.24 | F22: CFO less cash capex
B23: Capex / revenue % | C23: =Inputs!C22/Inputs!C6 -> 0.56570421 | D23: =Inputs!D22/Inputs!D6 -> 0.016502871 | E23: =Inputs!E22/Inputs!E6 -> 0.08896064 | F23: Capital intensity - FY24 spike is the Pakhajan greenfield

Sheet TieOut
B2: Yasho Industries Limited - tie-out to company-disclosed figures
B3: Binding gate (CLAUDE.md Step 6): headline computed figures must reconcile to the company's OWN disclosed numbers before the workpaper is issued. PASS/FAIL is itself a formula - it re-evaluates if any input changes.
B5: Check | C5: Computed | D5: Company-disclosed | E5: Result | F5: Note
B6: FY26 gearing vs MD&A 'Debt/Equity 1.26' | C6: =(Inputs!E12+Inputs!E13+Inputs!E14+Inputs!E15)/Inputs!E16 -> 1.2642587 | D6: 1.26 | E6: =IF(ABS(C6-D6)<=MAX(1,ABS(D6)*0.005),"PASS","CHECK") | F6: Company's own MD&A ratio table - exact match
B7: FY26 EBIT/interest vs MD&A 'Interest Coverage 1.61' | C7: =(Inputs!E7-Inputs!E10)/Inputs!E11 -> 1.6142909 | D7: 1.61 | E7: =IF(ABS(C7-D7)<=MAX(1,ABS(D7)*0.005),"PASS","CHECK") | F7: Company's own MD&A ratio table - exact match, confirms EBITDA and depreciation
B8: FY26 borrowings vs Q4FY26 deck bar chart | C8: =Inputs!E12+Inputs!E13 -> 540.94 | D8: 540.94 | E8: =IF(ABS(C8-D8)<=MAX(1,ABS(D8)*0.005),"PASS","CHECK") | F8: Deck shows LT 305.2 + ST 235.7 = Rs 540.9 cr - balance sheet ties to the deck
B9: FY26 revenue vs Q4FY26 deck | C9: =Inputs!E6 -> 830.03 | D9: 830.03 | E9: =IF(ABS(C9-D9)<=MAX(1,ABS(D9)*0.005),"PASS","CHECK") | F9: Company-disclosed FY26 consolidated revenue
B10: FY26 EBITDA vs Q4FY26 deck | C10: =Inputs!E7 -> 144.46 | D10: 144.46 | E10: =IF(ABS(C10-D10)<=MAX(1,ABS(D10)*0.005),"PASS","CHECK") | F10: Deck EBITDA Rs 144.46 cr; independently derived PBT+D+I gives 144.29 - 0.1% variance
B12: Tolerance: 0.5% of the disclosed figure, floor Rs 1 - tighter than rounding, loose enough for basis differences.

Sheet RatingScore
B2: Yasho Industries Limited - rating scorecard and view
B3: Factor scores 1 (strongest) to 6 (weakest), weighted to a composite. The anchor is a SCREENING cross-check with a +/-2 notch band, NOT the rating - the analyst view and any divergence are stated below and the divergence must be explained, never buried.
B5: Rating factor | C5: Score (1-6) | D5: Weight | E5: Weighted | F5: Justification
B6: Industry / operating environment | C6: 3 | D6: 0.2 | E6: =C6*D6 -> 0.6 | F6: Speciality chemicals: CRISIL's chemical-industry criteria favours speciality over bulk (proprietary technology, sticky post-qualification customer relationships, low share of customer's cost base, less pronounced cycles). Offset by exposure to crude-linked raw material volatility, Chinese competition on price, and export-market tariff risk which demonstrably suppressed utilisation through Q2-Q3 FY26.
B7: Market position | C7: 3 | D7: 0.2 | E7: =C7*D7 -> 0.6 | F7: Rs 830 crore revenue (FY26) across 140+ products in five verticals; ~62-65% exports to USA, Europe, Asia, Middle East. Two plants (Vapi, Pakhajan) with combined peak revenue capacity of Rs 1,450-1,550 crore. Positive: a 15-year lubricant-additives supply agreement with a global MNC, fully customer-funded (Rs 85-90 crore project cost, Rs 98 crore of advances received). Negative: customer-concentration percentages are NOT disclosed in any supplied document, and the Consumer division has compressed from 17% to 11% of revenue in two years without management explanation.
B8: Financial risk profile | C8: 4 | D8: 0.45 | E8: =C8*D8 -> 1.8 | F8: The binding constraint. Gearing 1.26x and TOL/TNW 1.63x remain elevated; adjusted debt/EBITDA 3.86x (FY26) and interest coverage of just 2.60x (PBDIT basis) / 1.61x (EBIT basis) are weak for the mid-BBB/A- boundary. Working capital is heavy - 152 net days FY26, receivable days deteriorating 76->80->90. Mitigants are real and improving: FY26 CFO of Rs 151 crore, positive FCF of Rs 77 crore, adjusted debt down Rs 25 crore, and a Rs 125 crore FY25 equity infusion. Q1FY27 marks a step-change - Rs 307.74 crore revenue (48% annualised run-rate uplift), 24.2% EBITDA margin, company-reported debt/EBITDA of 1.86x, working capital cut to 143 days.
B9: Management & governance | C9: 3 | D9: 0.15 | E9: =C9*D9 -> 0.45 | F9: Promoter-led (Jhaveri family, 67.91%), three decades of sector operating history, unmodified audit opinions in all three years with no Emphasis of Matter. Watch items: recurring director/KMP unsecured loans of Rs 47 crore (CRISIL Box 1 - treated as debt here, not equity, absent evidence of formal subordination); CSR consistently underspent and deferred to the statutory unspent account in both FY25 and FY26; FY26 Scope 1/2 GHG emissions marked 'Under Process' in the company's own BRSR, a latest-year disclosure gap.
B10: Weight check (must be 100%) | D10: =SUM(D6:D9) -> 1 | E10: =SUM(E6:E9) -> 3.45 | F10: =IF(ABS(D10-1)<0.001,"weights sum to 100%","ERROR: weights must sum to 100%")
B12: Weighted composite score | C12: =E10 -> 3.45
B13: Indicative anchor grade (screening only, +/-2 band) | C13: BBB+ / A- boundary (weighted composite 3.45 - upper-BBB, transitioning)
B14: ANALYST RATING VIEW | C14: Crisil A-/Stable · Crisil A2+
B15: Divergence from anchor - explanation | C15: None against the CURRENT agency action. CRITICAL STEP-14 NOTE: the reference library's CRISIL file (11-Feb-2026 Credit Bulletin) shows Crisil BBB+/Positive and Crisil A2 - this is SUPERSEDED. The issuer's own Q1FY27 investor presentation states verbatim: 'Bank Loan Ratings of the Company has been upgraded/assigned by CRISIL and ICRA from BBB+ to A-.' The current CRISIL rating is therefore A-, and this assessment converges on it independently: the FY26 deleveraging (gearing 1.97->1.26x, adj debt/EBITDA 5.43->3.86x), the swing to positive FCF, and the Q1FY27 step-change in scale and margin together support a one-notch upgrade from BBB+. Had the superseded library file been taken as the anchor, this report would have published BBB+ - repeating the Indus Towers failure exactly (CLAUDE.md failure mode 24).
