Workbook

Sheet Assumptions
A1: Equitas Small Finance Bank - standalone lending model (Rs crore). Base case on the statement tabs; Scenarios tab carries Stress and Tail. Generated by build_model.py from compute_ratios.py.
A3: Driver | B3: FY2027E | C3: FY2028E | D3: FY2029E | E3: FY2030E | F3: FY2031E | G3: Source / basis
A4: Gross advances growth (%) - Base | B4: 18 | C4: 18 | D4: 17 | E4: 16 | F4: 15 | G4: ANALYST JUDGMENT. FY2026 +18.0% (RBI gross advances 36,922.42 -> 43,580.10, asset-quality note); FY2025 +17.5%. Moderates as the base grows. Stress/Tail slow growth to conserve capital.
A5: Gross advances growth (%) - Stress (MFI-type shock) | B5: 10 | C5: 8 | D5: 12 | E5: 15 | F5: 15
A6: Gross advances growth (%) - Tail (Utkarsh-type shock) | B6: 5 | C6: 5 | D6: 10 | E6: 15 | F6: 15
A7: NIM on average total assets (%) - Base | B7: 6 | C7: 6.1 | D7: 6.2 | E7: 6.2 | F7: 6.2 | G7: ANALYST JUDGMENT anchored on FY2026 5.98% (CareEdge basis, engine) and FY2025 6.63%. The microfinance book (~10% of advances, down from 18%) earns the highest yield; its shrinkage caps the recovery. Stress compresses NIM via interest reversals on slippages.
A8: NIM on average total assets (%) - Stress (MFI-type shock) | B8: 5.6 | C8: 5.5 | D8: 5.8 | E8: 6 | F8: 6.1
A9: NIM on average total assets (%) - Tail (Utkarsh-type shock) | B9: 5.6 | C9: 5.5 | D9: 5.8 | E9: 6 | F9: 6.1
A10: Other income / avg total assets (%) - Base | B10: 1.8 | C10: 1.8 | D10: 1.8 | E10: 1.8 | F10: 1.8 | G10: FY2026 actual 1.89% (engine); includes PSLC fees and recoveries from written-off accounts.
A11: Other income / avg total assets (%) - Stress (MFI-type shock) | B11: 1.6 | C11: 1.5 | D11: 1.7 | E11: 1.8 | F11: 1.8
A12: Other income / avg total assets (%) - Tail (Utkarsh-type shock) | B12: 1.6 | C12: 1.5 | D12: 1.7 | E12: 1.8 | F12: 1.8
A13: Opex / avg total assets (%) - Base | B13: 5.5 | C13: 5.4 | D13: 5.3 | E13: 5.2 | F13: 5.1 | G13: FY2026 actual 5.64% (engine); gradual operating leverage assumed (1,060 branches already built).
A14: Opex / avg total assets (%) - Stress (MFI-type shock) | B14: 5.6 | C14: 5.7 | D14: 5.5 | E14: 5.3 | F14: 5.2
A15: Opex / avg total assets (%) - Tail (Utkarsh-type shock) | B15: 5.6 | C15: 5.7 | D15: 5.5 | E15: 5.3 | F15: 5.2
A16: Credit cost / avg total assets (%) - Base | B16: 1.2 | C16: 1.1 | D16: 1.1 | E16: 1.1 | F16: 1.1 | G16: ANALYST JUDGMENT. FY2026 2.00%, FY2025 2.31% (engine). Base normalises as the MFI stress passes: Q1 FY2027 PBT Rs 244.07 crore vs a Rs 297.48 crore loss in Q1 FY2026 (segment note). Stress repeats FY2025-26-type costs; Tail is a severe shock (peer Utkarsh: GNPA 12.42%).
A17: Credit cost / avg total assets (%) - Stress (MFI-type shock) | B17: 3 | C17: 2.5 | D17: 1.6 | E17: 1.2 | F17: 1.1
A18: Credit cost / avg total assets (%) - Tail (Utkarsh-type shock) | B18: 5 | C18: 3.5 | D18: 2 | E18: 1.3 | F18: 1.1
A19: Dividend payout (% of PAT) - Base | B19: 0 | C19: 10 | D19: 10 | E19: 10 | F19: 10 | G19: No dividend for FY2025 or FY2026 (Board). Base resumes 10% from FY2028; none under stress.
A20: Dividend payout (% of PAT) - Stress (MFI-type shock) | B20: 0 | C20: 0 | D20: 0 | E20: 0 | F20: 0
A21: Dividend payout (% of PAT) - Tail (Utkarsh-type shock) | B21: 0 | C21: 0 | D21: 0 | E21: 0 | F21: 0
A23: FY2026 asset mix held: advances / investments / cash / other (% of total assets) | B23: 70.5 / 16.7 / 9.3 / 3.4 | G23: balance sheet FY2026
A24: RWA density (RWA / total assets, %) | B24: 52.84 | G24: FY2026: 32,028.39 / 60,610.36
A25: Tier II capital held at FY2026 level (Rs crore) | B25: 1161.35 | G25: assumes the two Rs 500 crore 9.6% Lower Tier II bonds (maturity 2030) are refinanced as Basel II discounting begins - analyst assumption
A26: Borrowings held flat (Rs crore) | B26: 5772.55 | G26: deposits are the funding plug
A27: Tax rate (%) | B27: 25.17 | G27: statutory; FY2026 effective 19.6% on a small PBT
A28: Breakeven FY2027 credit cost for CRAR = 15% (% of avg total assets) | B28: 3.99 | G28: solved in code, base-case other drivers, no dividend

Sheet Lending P&L
A1: Rs crore | B1: FY2023 | C1: FY2024 | D1: FY2025 | E1: FY2026 | F1: FY2027E | G1: FY2028E | H1: FY2029E | I1: FY2030E | J1: FY2031E | K1: Source / note
A2: Net interest income | B2: 2544.7242 | C2: 3079.7606 | D2: 3251.6126 | E2: 3391.1694 | F2: 3963.9174 | G2: 4755.3796 | H2: 5677.1752 | I2: 6611.6853 | J2: 7634.0477 | K2: Interest earned - interest expended (P&L)
A3: Other income | B3: 669.5857 | C3: 798.6706 | D3: 911.4891 | E3: 1073.5472 | F3: 1189.1752 | G3: 1403.2268 | H3: 1648.2121 | I3: 1919.5215 | J3: 2216.3364 | K3: P&L
A4: Operating expenses | B4: 2038.3024 | C4: 2501.0668 | D4: 2828.8345 | E4: 3199.748 | F4: 3633.591 | G4: 4209.6803 | H4: 4853.0691 | I4: 5545.2844 | J4: 6279.6199 | K4: P&L
A5: Pre-provision operating profit | B5: 1176.0075 | C5: 1377.3644 | D5: 1334.2672 | E5: 1264.9686 | F5: 1519.5017 | G5: 1948.9261 | H5: 2472.3182 | I5: 2985.9224 | J5: 3570.7643 | K5: ties to MD&A operating profit
A6: Credit cost (provisions & write-offs excl. tax) | B6: 407.197 | C6: 314.2342 | D6: 1135.4173 | E6: 1136.8358 | F6: 792.7835 | G6: 857.5275 | H6: 1007.2408 | I6: 1173.0409 | J6: 1354.4278 | K6: note 18.14(f) less tax
A7: Profit before tax | B7: 768.8105 | C7: 1063.1302 | D7: 198.8499 | E7: 128.1328 | F7: 726.7182 | G7: 1091.3986 | H7: 1465.0775 | I7: 1812.8815 | J7: 2216.3364
A8: Tax | B8: 195.22 | C8: 264.17 | D8: 51.8 | E8: 25.05 | F8: 182.915 | G8: 274.705 | H8: 368.76 | I8: 456.3023 | J8: 557.8519 | K8: note 18.14(f) tax + deferred tax
A9: PROFIT AFTER TAX | B9: 573.5905 | C9: 798.9602 | D9: 147.0499 | E9: 103.0828 | F9: 543.8032 | G9: 816.6936 | H9: 1096.3175 | I9: 1356.5792 | J9: 1658.4846 | K9: P&L (tied)
A10: Dividend | B10: 0 | C10: 0 | D10: 0 | E10: 0 | F10: 0 | G10: 81.6694 | H10: 109.6317 | I10: 135.6579 | J10: 165.8485 | K10: none declared FY2025-26

Sheet Balance Sheet
A1: Rs crore | B1: FY2023 | C1: FY2024 | D1: FY2025 | E1: FY2026 | F1: FY2027E | G1: FY2028E | H1: FY2029E | I1: FY2030E | J1: FY2031E | K1: Source / note
A2: Advances (net) | B2: 25798.557 | C2: 30964.3 | D2: 36208.888 | E2: 42751.288 | F2: 50446.519 | G2: 59526.893 | H2: 69646.465 | I2: 80789.899 | J2: 92908.384
A3: Investments | B3: 6664.5624 | C3: 9065.2723 | D3: 9288.6851 | E3: 10148.827 | F3: 11975.616 | G3: 14131.227 | H3: 16533.535 | I3: 19178.901 | J3: 22055.736
A4: Cash, RBI and bank balances | B4: 1244.2577 | C4: 3578.9516 | D4: 5536.2993 | E4: 5666.2847 | F4: 6686.2159 | G4: 7889.7348 | H4: 9230.9897 | I4: 10707.948 | J4: 12314.14
A5: Fixed and other assets | B5: 1250.7519 | C5: 1695.3461 | D5: 1801.7619 | E5: 2043.959 | F5: 2411.8716 | G5: 2846.0085 | H5: 3329.83 | I5: 3862.6028 | J5: 4441.9932
A6: TOTAL ASSETS | B6: 34958.129 | C6: 45303.87 | D6: 52835.634 | E6: 60610.358 | F6: 71520.223 | G6: 84393.863 | H6: 98740.82 | I6: 114539.35 | J6: 131720.25
A7: Net worth | B7: 5157.9477 | C7: 5968.7019 | D7: 6072.5203 | E7: 6124.8326 | F7: 6668.6358 | G7: 7403.66 | H7: 8390.3458 | I7: 9611.267 | J7: 11103.903
A8: Tangible net worth (less DTA and software) | B8: 4796.8452 | C8: 5537.3749 | D8: 5592.5733 | E8: 5582.455 | F8: 6126.2582 | G8: 6861.2824 | H8: 7847.9682 | I8: 9068.8894 | J8: 10561.525 | K8: balance sheet / tangible net worth tied to Reg 52(4)
A9: Deposits | B9: 25348.483 | C9: 36129.202 | D9: 43102.313 | E9: 46533.089 | F9: 56506.77 | G9: 68182.378 | H9: 81026.653 | I9: 95036.059 | J9: 110106.4
A10: Borrowings (incl. Lower Tier II bonds) | B10: 2973.76 | C10: 1787.53 | D10: 2136.99 | E10: 5772.55 | F10: 5772.55 | G10: 5772.55 | H10: 5772.55 | I10: 5772.55 | J10: 5772.55
A11: Other liabilities and provisions | B11: 1477.9383 | C11: 1418.4358 | D11: 1523.8114 | E11: 2179.887 | F11: 2572.2667 | G11: 3035.2747 | H11: 3551.2714 | I11: 4119.4748 | J11: 4737.396
A12: Check: assets - (net worth + deposits + borrowings + other liabilities) | B12: 0 | C12: 0 | D12: 0 | E12: 0 | F12: 0 | G12: 0 | H12: 0 | I12: 0 | J12: 0 | K12: must be zero

Sheet Capital
A1: Rs crore | B1: FY2023 | C1: FY2024 | D1: FY2025 | E1: FY2026 | F1: FY2027E | G1: FY2028E | H1: FY2029E | I1: FY2030E | J1: FY2031E | K1: Source / note
A2: Tier I capital (CET1) | B2: 4583.58 | C2: 5128.39 | D2: 5273.89 | E2: 5342.21 | F2: 5886.0132 | G2: 6621.0374 | H2: 7607.7232 | I2: 8828.6444 | J2: 10321.281 | K2: regulatory capital note; projected = + retained profit
A3: Tier II capital | B3: 143.67 | C3: 244.32 | D3: 814.95 | E3: 1161.35 | F3: 1161.35 | G3: 1161.35 | H3: 1161.35 | I3: 1161.35 | J3: 1161.35 | K3: regulatory capital note
A4: Risk-weighted assets | B4: 19864.32 | C4: 24761.88 | D4: 29558.14 | E4: 32028.39 | F4: 37793.5 | G4: 44596.33 | H4: 52177.706 | I4: 60526.139 | J4: 69605.06 | K4: regulatory capital note; projected at FY2026 density

Sheet Credit Ratios
A1: CareEdge financial-sector ratios (formulas) | B1: FY2023 | C1: FY2024 | D1: FY2025 | E1: FY2026 | F1: FY2027E | G1: FY2028E | H1: FY2029E | I1: FY2030E | J1: FY2031E | K1: Source / note
A2: NIM - NII / avg total assets (%) | C2: =100*'Lending P&L'!C2/(('Balance Sheet'!C6+'Balance Sheet'!B6)/2) -> 7.6742684 | D2: =100*'Lending P&L'!D2/(('Balance Sheet'!D6+'Balance Sheet'!C6)/2) -> 6.6265112 | E2: =100*'Lending P&L'!E2/(('Balance Sheet'!E6+'Balance Sheet'!D6)/2) -> 5.9784737 | F2: =100*'Lending P&L'!F2/(('Balance Sheet'!F6+'Balance Sheet'!E6)/2) -> 5.9999999 | G2: =100*'Lending P&L'!G2/(('Balance Sheet'!G6+'Balance Sheet'!F6)/2) -> 6.1 | H2: =100*'Lending P&L'!H2/(('Balance Sheet'!H6+'Balance Sheet'!G6)/2) -> 6.2 | I2: =100*'Lending P&L'!I2/(('Balance Sheet'!I6+'Balance Sheet'!H6)/2) -> 6.2 | J2: =100*'Lending P&L'!J2/(('Balance Sheet'!J6+'Balance Sheet'!I6)/2) -> 6.2
A3: ROTA - PAT / avg total assets (%) | C3: =100*'Lending P&L'!C9/(('Balance Sheet'!C6+'Balance Sheet'!B6)/2) -> 1.9908804 | D3: =100*'Lending P&L'!D9/(('Balance Sheet'!D6+'Balance Sheet'!C6)/2) -> 0.29967524 | E3: =100*'Lending P&L'!E9/(('Balance Sheet'!E6+'Balance Sheet'!D6)/2) -> 0.18173017 | F3: =100*'Lending P&L'!F9/(('Balance Sheet'!F6+'Balance Sheet'!E6)/2) -> 0.82312996 | G3: =100*'Lending P&L'!G9/(('Balance Sheet'!G6+'Balance Sheet'!F6)/2) -> 1.04762 | H3: =100*'Lending P&L'!H9/(('Balance Sheet'!H6+'Balance Sheet'!G6)/2) -> 1.19728 | I3: =100*'Lending P&L'!I9/(('Balance Sheet'!I6+'Balance Sheet'!H6)/2) -> 1.27211 | J3: =100*'Lending P&L'!J9/(('Balance Sheet'!J6+'Balance Sheet'!I6)/2) -> 1.34694
A4: RONW - PAT / avg tangible net worth (%) | C4: =100*'Lending P&L'!C9/(('Balance Sheet'!C8+'Balance Sheet'!B8)/2) -> 15.462419 | D4: =100*'Lending P&L'!D9/(('Balance Sheet'!D8+'Balance Sheet'!C8)/2) -> 2.6424184 | E4: =100*'Lending P&L'!E9/(('Balance Sheet'!E8+'Balance Sheet'!D8)/2) -> 1.8448777 | F4: =100*'Lending P&L'!F9/(('Balance Sheet'!F8+'Balance Sheet'!E8)/2) -> 9.2888636 | G4: =100*'Lending P&L'!G9/(('Balance Sheet'!G8+'Balance Sheet'!F8)/2) -> 12.576571 | H4: =100*'Lending P&L'!H9/(('Balance Sheet'!H8+'Balance Sheet'!G8)/2) -> 14.906504 | I4: =100*'Lending P&L'!I9/(('Balance Sheet'!I8+'Balance Sheet'!H8)/2) -> 16.038194 | J4: =100*'Lending P&L'!J9/(('Balance Sheet'!J8+'Balance Sheet'!I8)/2) -> 16.897092
A5: Credit cost / avg total assets (%) | C5: =100*'Lending P&L'!C6/(('Balance Sheet'!C6+'Balance Sheet'!B6)/2) -> 0.78302112 | D5: =100*'Lending P&L'!D6/(('Balance Sheet'!D6+'Balance Sheet'!C6)/2) -> 2.3138843 | E5: =100*'Lending P&L'!E6/(('Balance Sheet'!E6+'Balance Sheet'!D6)/2) -> 2.0041886 | F5: =100*'Lending P&L'!F6/(('Balance Sheet'!F6+'Balance Sheet'!E6)/2) -> 1.2 | G5: =100*'Lending P&L'!G6/(('Balance Sheet'!G6+'Balance Sheet'!F6)/2) -> 1.1 | H5: =100*'Lending P&L'!H6/(('Balance Sheet'!H6+'Balance Sheet'!G6)/2) -> 1.1 | I5: =100*'Lending P&L'!I6/(('Balance Sheet'!I6+'Balance Sheet'!H6)/2) -> 1.1 | J5: =100*'Lending P&L'!J6/(('Balance Sheet'!J6+'Balance Sheet'!I6)/2) -> 1.1
A6: Opex / avg total assets (%) | C6: =100*'Lending P&L'!C4/(('Balance Sheet'!C6+'Balance Sheet'!B6)/2) -> 6.2322565 | D6: =100*'Lending P&L'!D4/(('Balance Sheet'!D6+'Balance Sheet'!C6)/2) -> 5.7649252 | E6: =100*'Lending P&L'!E4/(('Balance Sheet'!E6+'Balance Sheet'!D6)/2) -> 5.6410067 | F6: =100*'Lending P&L'!F4/(('Balance Sheet'!F6+'Balance Sheet'!E6)/2) -> 5.5 | G6: =100*'Lending P&L'!G4/(('Balance Sheet'!G6+'Balance Sheet'!F6)/2) -> 5.4 | H6: =100*'Lending P&L'!H4/(('Balance Sheet'!H6+'Balance Sheet'!G6)/2) -> 5.3 | I6: =100*'Lending P&L'!I4/(('Balance Sheet'!I6+'Balance Sheet'!H6)/2) -> 5.2 | J6: =100*'Lending P&L'!J4/(('Balance Sheet'!J6+'Balance Sheet'!I6)/2) -> 5.1
A7: Cost to income - opex / (NII + other income) (%) | B7: =100*'Lending P&L'!B4/('Lending P&L'!B2+'Lending P&L'!B3) -> 63.413375 | C7: =100*'Lending P&L'!C4/('Lending P&L'!C2+'Lending P&L'!C3) -> 64.486558 | D7: =100*'Lending P&L'!D4/('Lending P&L'!D2+'Lending P&L'!D3) -> 67.950166 | E7: =100*'Lending P&L'!E4/('Lending P&L'!E2+'Lending P&L'!E3) -> 71.667438 | F7: =100*'Lending P&L'!F4/('Lending P&L'!F2+'Lending P&L'!F3) -> 70.512822 | G7: =100*'Lending P&L'!G4/('Lending P&L'!G2+'Lending P&L'!G3) -> 68.35443 | H7: =100*'Lending P&L'!H4/('Lending P&L'!H2+'Lending P&L'!H3) -> 66.25 | I7: =100*'Lending P&L'!I4/('Lending P&L'!I2+'Lending P&L'!I3) -> 65 | J7: =100*'Lending P&L'!J4/('Lending P&L'!J2+'Lending P&L'!J3) -> 63.75
A8: CRAR - (Tier I + Tier II) / RWA (%) | B8: =100*('Capital'!B2+'Capital'!B3)/'Capital'!B4 -> 23.797694 | C8: =100*('Capital'!C2+'Capital'!C3)/'Capital'!C4 -> 21.697504 | D8: =100*('Capital'!D2+'Capital'!D3)/'Capital'!D4 -> 20.599537 | E8: =100*('Capital'!E2+'Capital'!E3)/'Capital'!E4 -> 20.30561 | F8: =100*('Capital'!F2+'Capital'!F3)/'Capital'!F4 -> 18.647024 | G8: =100*('Capital'!G2+'Capital'!G3)/'Capital'!G4 -> 17.450735 | H8: =100*('Capital'!H2+'Capital'!H3)/'Capital'!H4 -> 16.806168 | I8: =100*('Capital'!I2+'Capital'!I3)/'Capital'!I4 -> 16.505256 | J8: =100*('Capital'!J2+'Capital'!J3)/'Capital'!J4 -> 16.496833
A9: Tier I / RWA (%) | B9: =100*'Capital'!B2/'Capital'!B4 -> 23.074437 | C9: =100*'Capital'!C2/'Capital'!C4 -> 20.710826 | D9: =100*'Capital'!D2/'Capital'!D4 -> 17.842429 | E9: =100*'Capital'!E2/'Capital'!E4 -> 16.679608 | F9: =100*'Capital'!F2/'Capital'!F4 -> 15.574142 | G9: =100*'Capital'!G2/'Capital'!G4 -> 14.846597 | H9: =100*'Capital'!H2/'Capital'!H4 -> 14.580409 | I9: =100*'Capital'!I2/'Capital'!I4 -> 14.586498 | J9: =100*'Capital'!J2/'Capital'!J4 -> 14.828348
A10: Overall gearing - (deposits + borrowings) / TNW (x) | B10: =('Balance Sheet'!B9+'Balance Sheet'!B10)/'Balance Sheet'!B8 -> 5.9043478 | C10: =('Balance Sheet'!C9+'Balance Sheet'!C10)/'Balance Sheet'!C8 -> 6.8474201 | D10: =('Balance Sheet'!D9+'Balance Sheet'!D10)/'Balance Sheet'!D8 -> 8.0891747 | E10: =('Balance Sheet'!E9+'Balance Sheet'!E10)/'Balance Sheet'!E8 -> 9.3696481 | F10: =('Balance Sheet'!F9+'Balance Sheet'!F10)/'Balance Sheet'!F8 -> 10.165964 | G10: =('Balance Sheet'!G9+'Balance Sheet'!G10)/'Balance Sheet'!G8 -> 10.778587 | H10: =('Balance Sheet'!H9+'Balance Sheet'!H10)/'Balance Sheet'!H8 -> 11.060086 | I10: =('Balance Sheet'!I9+'Balance Sheet'!I10)/'Balance Sheet'!I8 -> 11.115871 | J10: =('Balance Sheet'!J9+'Balance Sheet'!J10)/'Balance Sheet'!J8 -> 10.971801
A11: Credit / deposit (%) | B11: =100*'Balance Sheet'!B2/'Balance Sheet'!B9 -> 101.77555 | C11: =100*'Balance Sheet'!C2/'Balance Sheet'!C9 -> 85.704356 | D11: =100*'Balance Sheet'!D2/'Balance Sheet'!D9 -> 84.006834 | E11: =100*'Balance Sheet'!E2/'Balance Sheet'!E9 -> 91.872877 | F11: =100*'Balance Sheet'!F2/'Balance Sheet'!F9 -> 89.275177 | G11: =100*'Balance Sheet'!G2/'Balance Sheet'!G9 -> 87.305392 | H11: =100*'Balance Sheet'!H2/'Balance Sheet'!H9 -> 85.955007 | I11: =100*'Balance Sheet'!I2/'Balance Sheet'!I9 -> 85.009732 | J11: =100*'Balance Sheet'!J2/'Balance Sheet'!J9 -> 84.380545
A13: SFB regulatory minimum: CRAR 15%, Tier I 7.5% (Basel II); leverage ratio 4.5% (CareEdge Banks methodology, March 2025).

Sheet Scenarios
A1: Scenario / metric | B1: FY2027E | C1: FY2028E | D1: FY2029E | E1: FY2030E | F1: FY2031E
A2: BASE
A3: Gross advances growth (%) | B3: 18 | C3: 18 | D3: 17 | E3: 16 | F3: 15
A4: PAT | B4: 543.8 | C4: 816.69 | D4: 1096.32 | E4: 1356.58 | F4: 1658.48
A5: ROTA (%) | B5: 0.82 | C5: 1.05 | D5: 1.2 | E5: 1.27 | F5: 1.35
A6: Credit cost / ATA (%) | B6: 1.2 | C6: 1.1 | D6: 1.1 | E6: 1.1 | F6: 1.1
A7: Tier I (%) | B7: 15.57 | C7: 14.85 | D7: 14.58 | E7: 14.59 | F7: 14.83
A8: CRAR (%) | B8: 18.65 | C8: 17.45 | D8: 16.81 | E8: 16.51 | F8: 16.5
A9: Tangible net worth | B9: 6126.26 | C9: 6861.28 | D9: 7847.97 | E9: 9068.89 | F9: 10561.53
A10: STRESS (MFI-TYPE SHOCK)
A11: Gross advances growth (%) | B11: 10 | C11: 8 | D11: 12 | E11: 15 | F11: 15
A12: PAT | B12: -666.71 | C12: -622.63 | D12: 228.46 | E12: 843.35 | F12: 1193.67
A13: ROTA (%) | B13: -1.05 | C13: -0.9 | D13: 0.3 | E13: 0.97 | F13: 1.2
A14: Credit cost / ATA (%) | B14: 3 | C14: 2.5 | D14: 1.6 | E14: 1.2 | F14: 1.1
A15: Tier I (%) | B15: 13.27 | C15: 10.65 | D15: 10.05 | E15: 10.46 | F15: 11.21
A16: CRAR (%) | B16: 16.57 | C16: 13.7 | D16: 12.77 | E16: 12.83 | F16: 13.27
A17: Tangible net worth | B17: 4915.74 | C17: 4293.11 | D17: 4521.57 | E17: 5364.92 | F17: 6558.59
A18: TAIL (UTKARSH-TYPE SHOCK)
A19: Gross advances growth (%) | B19: 5 | C19: 5 | D19: 10 | E19: 15 | F19: 15
A20: PAT | B20: -1580.61 | C20: -1073.89 | D20: 0 | E20: 709.55 | F20: 1087.98
A21: ROTA (%) | B21: -2.54 | C21: -1.65 | D21: 0 | E21: 0.9 | F21: 1.2
A22: Credit cost / ATA (%) | B22: 5 | C22: 3.5 | D22: 2 | E22: 1.3 | F22: 1.1
A23: Tier I (%) | B23: 11.19 | C23: 7.61 | D23: 6.92 | E23: 7.61 | F23: 8.73
A24: CRAR (%) | B24: 14.64 | C24: 10.9 | D24: 9.91 | E24: 10.21 | F24: 10.99
A25: Tangible net worth | B25: 4001.84 | C25: 2927.96 | D25: 2927.96 | E25: 3637.51 | F25: 4725.49
A27: Breakeven: FY2027 credit cost that takes CRAR to the 15% minimum = 3.99% of average total assets (FY2026 actual 2.00%; FY2025 2.31%).

Sheet Debt Breakup
A1: (i) FUNDING MIX (Rs crore) | B1: FY2024 | C1: FY2025 | D1: FY2026 | E1: Source
A2: Demand - from banks | B2: 65.24 | C2: 13.8 | D2: 11.03 | E2: Schedule 3
A3: Demand - from others | B3: 1149.78 | C3: 1629.83 | D3: 1525.31 | E3: Schedule 3
A4: Savings bank | B4: 10337.38 | C4: 10762.18 | D4: 10661.9 | E4: Schedule 3
A5: Term - from banks | B5: 6686.51 | C5: 7833.01 | D5: 8448.13 | E5: Schedule 3
A6: Term - from others | B6: 17890.28 | C6: 22863.49 | D6: 25886.71 | E6: Schedule 3
A7: TOTAL DEPOSITS | B7: 36129.2 | C7: 43102.31 | D7: 46533.09 | E7: Schedule 3 total (engine tie-out)
A8: CASA ratio (%) | B8: 31.98 | C8: 28.78 | D8: 26.21 | E8: (demand + savings) / deposits
A9: Borrowings | B9: 1787.53 | C9: 2136.99 | D9: 5772.55 | E9: Schedule 4: all from 'other institutions and agencies'; Lower Tier II bonds Rs 500 crore (Dec-2024) + Rs 500 crore (Jul-2025) inside; split of the remainder not disclosed
A10: Total borrowings / total assets (%) | B10: 3.95 | C10: 4.04 | D10: 9.52 | E10: bank prints 4.04% / 9.52% (Reg 52(4))
A11: Top-20 depositors (% of deposits) | C11: 17.6 | D11: 20.61 | E11: concentration note
A13: (ii) INSTRUMENTS (bank's own documents)
A14: Lower Tier II bond INE063P08112 | D14: 500 | E14: allotted 05-Dec-2024; 9.6% p.a.; maturity 05-Dec-2030 (FY2025 AR)
A15: Lower Tier II bond INE063P08120 | D15: 500 | E15: allotted 31-Jul-2025; 9.6% p.a.; maturity 31-Jul-2030 (FY2026 AR)
A16: Inter-bank participation certificates (IBPC) issued | C16: 0 | D16: 2000 | E16: Schedule 9 footnote; maturities 2 days-2 months (ALM note)
A17: Certificates of deposit outstanding | D17: n/d | E17: not disclosed separately in the documents
A19: (iii) RATED LIMITS vs DRAWN | D19: Rs crore
A20: CareEdge rated programme - CRA-PUBLISHED 06-Oct-2025, NOT issuer-confirmed | D20: 2500 | E20: Lower Tier II 500 + 500 (fully issued) + CD 1,500 (programme limit) + issuer rating
A21: Lower Tier II outstanding (drawn) vs rated 1,000 | D21: 1000 | E21: fully utilised

Sheet Valuation
A1: Market data (screener.in, close 09-Oct-2026; third-party, not exchange-verified)
A2: Share price (Rs) | B2: 66
A3: Market capitalisation (Rs crore) | B3: 7554
A4: Price / book (x) on FY2026 net worth 6,124.83 | B4: 1.23
A5: Price / tangible book (x) on FY2026 TNW 5,582.45 | B5: 1.35
A6: Market cap / FY2026 Tier I capital (x) | B6: 1.41
