Workbook

Sheet Assumptions
B2: Balkrishna Industries Limited - forecast drivers (Rs crore; consolidated)
B3: Yellow cells are the DRIVERS. Every one is derived from the company's own documents (annual reports, MD&A, cash flow statement) or from the CRISIL/CareEdge same-issuer rationales dated Feb/Mar-2026, used here only as a cross-reference on FORECAST assumptions - never as a source of historical fact. FY2027E opens on the FY2026 audited actuals (31-Mar-2026), the most recent balance sheet in the document set.
B5: Line | C5: FY2027E | D5: FY2028E | E5: FY2029E | F5: FY2030E | G5: FY2031E | H5: Derivation / source
B6: REVENUE
B7: Revenue growth (%) | C7: 8 | D7: 10 | E7: 10.5 | F7: 10 | G7: 9 | H7: FY2026 actual growth was 3.6% (Rs 10,446.95 cr to Rs 10,823.08 cr), depressed by the North America tariff shock. CRISIL's 27-Feb-2026 rationale (peer-agency cross-reference, not a fact source) guides 'FY27 expected to grow by 7-9%... thereafter revenues are expected to grow at upwards of 10%', driven by continued India OHT volumes, carbon black scale-up and the new CVR/PCR segments. Base case takes 8.0% for FY2027E (low end, since a full tariff resolution is not assumed) and 9-10.5% thereafter as the new segments ramp.
B8: MARGIN
B9: OPBDITA margin (%) | C9: 23.5 | D9: 23.3 | E9: 23.3 | F9: 23.3 | G9: 23.3 | H9: Actuals (add-back convention, failure mode 36): 24.07% (FY2024), 23.52% (FY2025), 23.93% (FY2026) - core operating profitability was RESILIENT through the North America volume shock, not compressed; the FY2026 PAT decline was a non-operating currency swing (a Rs 290.01 cr forex loss against a Rs 267.36 cr gain the prior year), disclosed in compute_ratios.py. ICRA's own 25-Aug-2026 rationale frames the forward path the same way: the rising share of lower-margin on-highway tyres (TBR/PCR/2W, launched/launching through FY2027) 'could result in some moderation in blended profitability' but 'the impact is expected to be largely offset by operating efficiencies'. Base case therefore holds margin NEAR the FY2026 actual rather than modelling either a compression-and-recovery arc or continued expansion - a mild, structural mix-driven give-back (23.93% to ~23.3%) offset by efficiency gains, roughly flat through the forecast horizon.
B10: CAPEX AND WORKING CAPITAL
B11: Capital expenditure (Rs cr) | C11: 1900 | D11: 1200 | E11: 1000 | F11: 1100 | G11: 1150 | H11: The company's own MD&A: 'cumulatively announced a capex outlay of Rs 6,800 crore [since Aug-2024], to be deployed through FY 2028-29' [sic; the AR text elsewhere reads FY2029], of which Rs 2,984 crore (MD&A) / Rs 3,003.29 crore (cash flow) was already spent in FY2026. Capital commitments (AR Note 46) of Rs 2,711.84 crore (FY2026, up from Rs 923.98 crore FY2025) show the NEXT phase is substantially contracted, not merely announced - so FY2027E is set high (Rs 1,900 crore, close to that committed quantum), tapering through FY2029E as the ANNOUNCED programme completes against its Rs 6,800 crore cumulative ceiling (2,984 FY2026 + 1,900 + 1,200 + 1,000 = 7,084 - modestly over the announced figure, since FY2029E also carries normal replacement capex beyond the specific announced tranche). FY2030E-FY2031E are held ABOVE the FY2026 depreciation run-rate (not tapered to a bare maintenance level below it) - a capital-intensive manufacturer replacing newly-built assets and continuing the 'Vision 2030' growth plans the company's own MD&A describes does not structurally shrink its net fixed-asset base once one announced tranche completes; a model that let it do so was an artefact of over-tapering, not a considered forecast, and has been corrected here.
B12: Working capital as % of incremental revenue | C12: 18 | D12: 18 | E12: 18 | F12: 18 | G12: 18 | H12: FY2026 working capital cycle was 111.36 days (RatioSuite); net working capital (current assets less current liabilities excluding cash/debt) as a share of revenue has run 15-20% across FY2023-FY2026. Held at 18%, near the FY2026 level, since the new CVR/PCR segments are not expected to structurally shorten the cycle in their ramp-up years.
B13: FINANCING
B14: Cost of debt on opening balance (%) | C14: 7.5 | D14: 7.5 | E14: 7.5 | F14: 7.5 | G14: 7.5 | H14: FY2026 finance cost / opening total debt = 133.62 / 3,267.45 = 4.09%; FY2025 128.34 / 3,099.44 = 4.14%. These are LOW because a material share of BKT's consolidated debt is working-capital/export-credit lines in foreign subsidiaries at low offshore rates. Set materially higher at 7.50% for the FORECAST debt, which is assumed to be incremental RUPEE term debt/NCD funding raised in India (the company's own Rs 750 crore NCD priced AA+/CARE AA+ in Mar-2026) - conservative, since blending the low-cost offshore stock with new onshore debt would understate interest cost.
B15: Effective tax rate (%) | C15: 24.4 | D15: 24.4 | E15: 24.4 | F15: 24.4 | G15: 24.4 | H15: FY2026: 400.58/1,643.68 = 24.37%. FY2025: 532.43/2,187.39 = 24.34%. Stable across both years; held flat.
B16: Dividend payout (% of PAT, cash-flow basis) | C16: 22 | D16: 22 | E16: 22 | F16: 22 | G16: 22 | H16: FY2026 dividend PAID (consolidated cash flow statement) Rs 309.19 crore / FY2026 PAT Rs 1,243.10 crore = 24.87%; FY2025 Rs 309.51 crore / Rs 1,654.96 crore = 18.70%. The cash-paid figure lags the DECLARED dividend by a year (a dividend declared for FY(t) is paid in FY(t+1)), so it is a smoothing average of two years' declarations rather than a clean current-year payout ratio; held at 22%, the midpoint of the two observed cash-basis ratios.

Sheet P_and_L
B2: Projected profit and loss (Rs crore, consolidated)
B3: Revenue grows off the FY2026 base at the assumed rate; OPBDITA margin phases in toward the assumed level; depreciation grows with the capitalised asset base; interest is priced on OPENING debt to avoid a circular reference through closing debt / retained earnings / PAT (see Balance_Sheet note).
B5: Line | C5: FY2027E | D5: FY2028E | E5: FY2029E | F5: FY2030E | G5: FY2031E | H5: Derivation / source
B6: Revenue from operations | C6: 10823.08 | D6: =C6*(1+Assumptions!D7/100) -> 11905.388 | E6: =D6*(1+Assumptions!E7/100) -> 13155.454 | F6: =E6*(1+Assumptions!F7/100) -> 14470.999 | G6: =F6*(1+Assumptions!G7/100) -> 15773.389 | H6: FY2027E grows off the FY2026 actual of 10,823.08
B7: OPBDITA | C7: =C6*Assumptions!C9/100 -> 2543.4238 | D7: =D6*Assumptions!D9/100 -> 2773.9554 | E7: =E6*Assumptions!E9/100 -> 3065.2207 | F7: =F6*Assumptions!F9/100 -> 3371.7428 | G7: =G6*Assumptions!G9/100 -> 3675.1996
B8: Depreciation and amortisation | C8: 774.96 | D8: =C8+Assumptions!D11*0.12 -> 918.96 | E8: =D8+Assumptions!E11*0.12 -> 1038.96 | F8: =E8+Assumptions!F11*0.12 -> 1170.96 | G8: =F8+Assumptions!G11*0.12 -> 1308.96 | H8: FY2027E opens on the FY2026 actual of 774.96; each year adds 12% of that year's capex as incremental depreciation - roughly the FY2026 actual's ratio of depreciation growth (Rs 94.30 crore added) to capex (Rs 3,003.29 crore) = 3.1%, raised to 12% since a full-year run-rate on assets capitalised only PART-WAY through the prior year is higher in the following full year
B9: Finance costs | C9: =Balance_Sheet!C19*Assumptions!C14/100 -> 308.3115 | D9: =Balance_Sheet!D19*Assumptions!D14/100 -> 0 | E9: =Balance_Sheet!E19*Assumptions!E14/100 -> 0 | F9: =Balance_Sheet!F19*Assumptions!F14/100 -> 0 | G9: =Balance_Sheet!G19*Assumptions!G14/100 -> 0 | H9: OPENING total debt (floored at zero) times cost of debt - priced on the opening balance to avoid a circular reference through closing debt / retained earnings / PAT / finance costs, the same fix applied in the Repco Home Finance lending model built earlier this project. Once the company reaches net cash this line goes to zero rather than an implied interest INCOME, which the model does not attempt to price (a real net-cash position would earn a materially lower rate than the cost of debt, and modelling it symmetrically would overstate the benefit).
B10: Profit before tax | C10: =C7-C8-C9 -> 1460.1523 | D10: =D7-D8-D9 -> 1854.9954 | E10: =E7-E8-E9 -> 2026.2607 | F10: =F7-F8-F9 -> 2200.7828 | G10: =G7-G8-G9 -> 2366.2396
B11: Tax | C11: =-C10*Assumptions!C15/100 -> -356.27716 | D11: =-D10*Assumptions!D15/100 -> -452.61888 | E11: =-E10*Assumptions!E15/100 -> -494.40762 | F11: =-F10*Assumptions!F15/100 -> -536.991 | G11: =-G10*Assumptions!G15/100 -> -577.36247
B12: Profit after tax | C12: =C10+C11 -> 1103.8751 | D12: =D10+D11 -> 1402.3765 | E12: =E10+E11 -> 1531.8531 | F12: =F10+F11 -> 1663.7918 | G12: =G10+G11 -> 1788.8772 | H12: Actuals: 1,471.49 (FY2024), 1,654.96 (FY2025), 1,243.10 (FY2026, the tariff-hit year) - FY2026 fell 24.9% on the North America revenue decline.
B13: Dividend (cash-flow basis, current-year accrual) | C13: =-C12*Assumptions!C16/100 -> -242.85253 | D13: =-D12*Assumptions!D16/100 -> -308.52284 | E13: =-E12*Assumptions!E16/100 -> -337.00768 | F13: =-F12*Assumptions!F16/100 -> -366.03419 | G13: =-G12*Assumptions!G16/100 -> -393.55298
B14: Retained earnings | C14: =C12+C13 -> 861.02261 | D14: =D12+D13 -> 1093.8537 | E14: =E12+E13 -> 1194.8454 | F14: =F12+F13 -> 1297.7576 | G14: =G12+G13 -> 1395.3242

Sheet Balance_Sheet
B2: Projected balance sheet (Rs crore) - debt is the FUNDING GAP, not a trend
B3: Failure mode 18: projected debt is DERIVED from capex less retained accrual, never extrapolated from the historical leverage pattern. Non-debt assets and liabilities scale with revenue via the working-capital assumption; PP&E rolls forward with capex less depreciation; debt is whatever balances the sheet.
B5: Line | C5: FY2027E | D5: FY2028E | E5: FY2029E | F5: FY2030E | G5: FY2031E | H5: Derivation / source
B6: Incremental working capital | C6: =(P_and_L!C6-10823.08)*Assumptions!C12/100 -> 0 | D6: =(P_and_L!D6-P_and_L!C6)*Assumptions!D12/100 -> 194.81544 | E6: =(P_and_L!E6-P_and_L!D6)*Assumptions!E12/100 -> 225.01183 | F6: =(P_and_L!F6-P_and_L!E6)*Assumptions!F12/100 -> 236.79817 | G6: =(P_and_L!G6-P_and_L!F6)*Assumptions!G12/100 -> 234.43019 | H6: revenue growth times the working-capital-intensity assumption; FY2027E measures growth off the FY2026 actual of 10,823.08
B7: Fixed assets (PP&E + CWIP + intangibles, net) | C7: 9881.85 | D7: =C7+Assumptions!D11-P_and_L!D8 -> 10162.89 | E7: =D7+Assumptions!E11-P_and_L!E8 -> 10123.93 | F7: =E7+Assumptions!F11-P_and_L!F8 -> 10052.97 | G7: =F7+Assumptions!G11-P_and_L!G8 -> 9894.01 | H7: FY2027E opens on the FY2026 consolidated total of PP&E 7,326.54 + CWIP 2,472.46 + investment property 55.61 + intangibles 7.32 + right-of-use 19.92 = 9,881.85; each year adds capex and subtracts depreciation
B8: Other non-debt-related assets (investments, tax assets, etc) | C8: 4057.5 | D8: 4057.5 | E8: 4057.5 | F8: 4057.5 | G8: 4057.5 | H8: held flat at the FY2026 total of non-current investments 1,796.48 + other non-current financial assets 38.46 + income tax assets 20.23 + other non-current assets 874.85 + current investments 1,327.48 = 4,057.50 - these are not driven by revenue growth in this model
B9: Cash and bank balances (residual liquidity buffer held flat) | C9: 64.51 | D9: 64.51 | E9: 64.51 | F9: 64.51 | G9: 64.51 | H9: held flat at the FY2026 total of 64.51 - the model treats surplus cash generation as debt reduction, not cash accumulation, which is conservative for a credit view
B10: Total assets | C10: =(C6)+C7+C8+C9 -> 14003.86 | D10: =(C6+D6)+D7+D8+D9 -> 14479.715 | E10: =(C6+D6+E6)+E7+E8+E9 -> 14665.767 | F10: =(C6+D6+E6+F6)+F7+F8+F9 -> 14831.605 | G10: =(C6+D6+E6+F6+G6)+G7+G8+G9 -> 14907.076 | H10: placeholder, patched below to accumulate working capital
B11: FUNDING
B12: Opening net worth | C12: 10955.29 | D12: =C14 -> 11816.313 | E12: =D14 -> 12910.166 | F12: =E14 -> 14105.012 | G12: =F14 -> 15402.769 | H12: FY2027E opens on the FY2026 consolidated total equity of 10,955.29
B13: Add: retained earnings | C13: =P_and_L!C14 -> 861.02261 | D13: =P_and_L!D14 -> 1093.8537 | E13: =P_and_L!E14 -> 1194.8454 | F13: =P_and_L!F14 -> 1297.7576 | G13: =P_and_L!G14 -> 1395.3242 | H13: from P_and_L
B14: Closing net worth | C14: =C12+C13 -> 11816.313 | D14: =D12+D13 -> 12910.166 | E14: =E12+E13 -> 14105.012 | F14: =F12+F13 -> 15402.769 | G14: =G12+G13 -> 16798.094
B15: Non-debt liabilities (trade payables, provisions, DTL, other) | C15: 2700.23 | D15: 2700.23 | E15: 2700.23 | F15: 2700.23 | G15: 2700.23 | H15: held flat at the FY2026 total (Rs 2,700.23 crore) - trade payables move inside the working-capital line above; this captures everything else on the liability side that is not debt and not equity
B16: Implied funding position (assets - net worth - non-debt liabilities) | C16: =C10-C14-C15 -> -512.68261 | D16: =D10-D14-D15 -> -1130.6809 | E16: =E10-E14-E15 -> -2139.4744 | F16: =F10-F14-F15 -> -3271.3939 | G16: =G10-G14-G15 -> -4591.2479 | H16: total assets less closing net worth less non-debt liabilities. NEGATIVE means retained earnings exceed what the assumed asset base needs, implying a net-cash position - a plausible outcome for THIS issuer, not a modelling error: CareEdge's 05-Mar-2026 rationale names 'a net debt free profile' as an achievable POSITIVE rating trigger. Floored at zero on the next row for the debt actually carried; the negative excess is shown separately as net cash below.
B17: Total debt (FUNDING GAP, floored at zero) | C17: =MAX(0,C16) -> 0 | D17: =MAX(0,D16) -> 0 | E17: =MAX(0,E16) -> 0 | F17: =MAX(0,F16) -> 0 | G17: =MAX(0,G16) -> 0 | H17: the debt actually modelled as carried - a company cannot carry negative borrowings, so the implied funding position above is floored here
B18: Net cash position beyond debt-free (0 if still carrying debt) | C18: =MAX(0,-C16) -> 512.68261 | D18: =MAX(0,-D16) -> 1130.6809 | E18: =MAX(0,-E16) -> 2139.4744 | F18: =MAX(0,-F16) -> 3271.3939 | G18: =MAX(0,-G16) -> 4591.2479 | H18: the surplus once the implied funding position turns negative - held as cash/liquid investments in this simplified model rather than reinvested or returned to shareholders, which is itself conservative (it understates the payout or buyback capacity a real net-cash BKT would likely exercise)
B19: Opening total debt | C19: 4110.82 | D19: =C17 -> 0 | E19: =D17 -> 0 | F19: =E17 -> 0 | G19: =F17 -> 0 | H19: FY2027E opens on the FY2026 consolidated total debt of 4,110.82 (NC borrowings 888.00 + NC leases 4.07 + C borrowings 3,217.56 + C leases 1.19)

Sheet Credit_Ratios
B2: Credit ratios on ICRA corporate conventions, every year
B3: The same convention set as compute_ratios.py, so projected years sit on identical definitions to the historical RatioSuite.
B5: Line | C5: FY2027E | D5: FY2028E | E5: FY2029E | F5: FY2030E | G5: FY2031E | H5: Derivation / source
B6: OPBDITA margin % | C6: =100*P_and_L!C7/P_and_L!C6 -> 23.5 | D6: =100*P_and_L!D7/P_and_L!D6 -> 23.3 | E6: =100*P_and_L!E7/P_and_L!E6 -> 23.3 | F6: =100*P_and_L!F7/P_and_L!F6 -> 23.3 | G6: =100*P_and_L!G7/P_and_L!G6 -> 23.3 | H6: Actuals 24.07 / 23.52 / 23.93 (FY2024-FY2026, add-back convention - failure mode 36); core profitability held through the FY2026 currency shock
B7: Gearing (times) | C7: =Balance_Sheet!C17/Balance_Sheet!C14 -> 0 | D7: =Balance_Sheet!D17/Balance_Sheet!D14 -> 0 | E7: =Balance_Sheet!E17/Balance_Sheet!E14 -> 0 | F7: =Balance_Sheet!F17/Balance_Sheet!F14 -> 0 | G7: =Balance_Sheet!G17/Balance_Sheet!G14 -> 0 | H7: Actuals 0.35 / 0.31 / 0.38 (FY2024-FY2026); has stayed in a 0.31x-0.44x band across all four historical years despite the capex programme
B8: Total debt/OPBDITA (times) | C8: =Balance_Sheet!C17/P_and_L!C7 -> 0 | D8: =Balance_Sheet!D17/P_and_L!D7 -> 0 | E8: =Balance_Sheet!E17/P_and_L!E7 -> 0 | F8: =Balance_Sheet!F17/P_and_L!F7 -> 0 | G8: =Balance_Sheet!G17/P_and_L!G7 -> 0 | H8: Actuals 1.37 / 1.33 / 1.79 (FY2024-FY2026)
B9: Interest coverage (times) | C9: =IF(P_and_L!C9<1,"n/m (net cash)",P_and_L!C7/P_and_L!C9) -> 8.2495262 | D9: =IF(P_and_L!D9<1,"n/m (net cash)",P_and_L!D7/P_and_L!D9) -> n/m (net cash) | E9: =IF(P_and_L!E9<1,"n/m (net cash)",P_and_L!E7/P_and_L!E9) -> n/m (net cash) | F9: =IF(P_and_L!F9<1,"n/m (net cash)",P_and_L!F7/P_and_L!F9) -> n/m (net cash) | G9: =IF(P_and_L!G9<1,"n/m (net cash)",P_and_L!G7/P_and_L!G9) -> n/m (net cash) | H9: Actuals 19.98 / 19.15 / 17.22 (FY2024-FY2026) - never below 17x in any historical year including the FY2026 margin-compression year. Guarded: once finance costs fall below Rs 1 crore (the company has become net-cash, see Balance_Sheet), the ratio is marked not-meaningful rather than printing a distorted, exploding multiple as the denominator approaches zero.
B10: TOL/TNW (times) | C10: =(Balance_Sheet!C10-Balance_Sheet!C14)/Balance_Sheet!C14 -> 0.18512944 | D10: =(Balance_Sheet!D10-Balance_Sheet!D14)/Balance_Sheet!D14 -> 0.12157466 | E10: =(Balance_Sheet!E10-Balance_Sheet!E14)/Balance_Sheet!E14 -> 0.039755767 | F10: =(Balance_Sheet!F10-Balance_Sheet!F14)/Balance_Sheet!F14 -> -0.037081895 | G10: =(Balance_Sheet!G10-Balance_Sheet!G14)/Balance_Sheet!G14 -> -0.11257336 | H10: Actuals 0.55 / 0.51 / 0.62 (FY2024-FY2026)
B11: RoCE % (indicative) | C11: =100*(P_and_L!C7-P_and_L!C8)/(Balance_Sheet!C17+Balance_Sheet!C14) -> 14.966292 | D11: =100*(P_and_L!D7-P_and_L!D8)/(Balance_Sheet!D17+Balance_Sheet!D14) -> 14.368486 | E11: =100*(P_and_L!E7-P_and_L!E8)/(Balance_Sheet!E17+Balance_Sheet!E14) -> 14.365537 | F11: =100*(P_and_L!F7-P_and_L!F8)/(Balance_Sheet!F17+Balance_Sheet!F14) -> 14.288228 | G11: =100*(P_and_L!G7-P_and_L!G8)/(Balance_Sheet!G17+Balance_Sheet!G14) -> 14.086358 | H11: Actuals 13.04 / 12.59 / 9.92 (FY2024-FY2026); simplified capital-employed base (debt + equity, excluding deferred tax liability which this model does not separately project) - indicative, not a like-for-like reproduction of the historical RoCE row

Sheet Debt_Breakup
B2: Debt structure - FY2026 actuals and the projected requirement
B3: Statutory decomposition tied to the FY2025-26 AR consolidated balance sheet and the rated-limits-versus-drawn-debt distinction (failure modes 13 and 31).
B5: Line | C5: FY2027E | D5: FY2028E | E5: FY2029E | F5: FY2030E | G5: FY2031E | H5: Derivation / source
B6: ACTUAL DRAWN DEBT AT 31-MAR-2026 (FY2025-26 AR, consolidated)
B7: Non-current borrowings | C7: 888 | H7: AR consolidated balance sheet
B8: Non-current lease liabilities | C8: 4.07 | H8: AR consolidated balance sheet
B9: Current borrowings | C9: 3217.56 | H9: AR consolidated balance sheet
B10: Current lease liabilities | C10: 1.19 | H10: AR consolidated balance sheet
B11: TOTAL DRAWN DEBT | C11: 4110.82 | H11: sum of the four lines above; reconciles to Total debt/total assets of 0.23x published in the company's own Reg 52(4) disclosure (4,110.82 / 17,766.34 = 0.231)
B12: RATED INSTRUMENTS (CRISIL / CareEdge - PEER AGENCY, NOT ICRA)
B13: CRISIL: bank loan facilities | C13: 2000 | H13: CRISIL rationale, 27-Feb-2026: 'Crisil AA+/Stable' (reaffirmed) - PEER-AGENCY REFERENCE ONLY, not ICRA's rated universe
B14: CRISIL: non-convertible debentures | C14: 750 | H14: CRISIL rationale, 27-Feb-2026: 'Crisil AA+/Stable' (assigned)
B15: CRISIL: commercial paper | C15: 500 | H15: CRISIL rationale, 27-Feb-2026: 'Crisil A1+' (reaffirmed)
B16: CareEdge: non-convertible debentures | C16: 750 | H16: CareEdge press release, 05-Mar-2026: 'CARE AA+; Stable' (assigned) - the SAME Rs 750 crore NCD tranche CRISIL also rates; CareEdge rates only this instrument, not bank facilities or CP
B17: ICRA rated amount | H17: NO ICRA RATING EXISTS on this issuer as at the data cutoff - confirmed by a recorded zero-hit search for 'ICRA' across the FY2025-26 AR and the newest quarterly filing. This is a fresh ASSIGNMENT, not a reaffirmation, and the actual ICRA-rated quantum will be set by the mandate/sanction letter, not estimated here.
B18: PROJECTED FUNDING REQUIREMENT
B19: Closing total debt (funding-gap derived) | C19: =Balance_Sheet!C17 -> 0 | D19: =Balance_Sheet!D17 -> 0 | E19: =Balance_Sheet!E17 -> 0 | F19: =Balance_Sheet!F17 -> 0 | G19: =Balance_Sheet!G17 -> 0 | H19: from Balance_Sheet
B20: Incremental borrowing required in the year | C20: =Balance_Sheet!C17-Balance_Sheet!C19 -> -4110.82 | D20: =Balance_Sheet!D17-Balance_Sheet!D19 -> 0 | E20: =Balance_Sheet!E17-Balance_Sheet!E19 -> 0 | F20: =Balance_Sheet!F17-Balance_Sheet!F19 -> 0 | G20: =Balance_Sheet!G17-Balance_Sheet!G19 -> 0 | H20: the annual quantum implied by the capex programme net of internal accrual

Sheet Stress_Case
B2: Stress case - the variables named in ICRA's Corporate and Auto Components methodologies
B3: Commodity-price/raw-material volatility and demand cyclicality are the two variables ICRA's Auto Components methodology names explicitly ('earnings vulnerable to cyclicality in commodity price cycles and automotive demand', per the MRF Limited peer rationale read for craft). NOTE: FY2026 was NOT actually a margin-compression year - core OPBDITA margin held at 23.93%, up from 23.52% (FY2025); the PAT decline that year was a non-operating currency swing, not an operating one (see the Assumptions sheet's margin-row note and compute_ratios.py's failure-mode-36 correction). This scenario is therefore a genuine HYPOTHETICAL departure from the resilient base case - a real margin shock the company has not yet experienced in this dataset - combined with slower revenue growth, not a recreation of anything that already happened.
B5: Line | C5: FY2027E | D5: FY2028E | E5: FY2029E | F5: FY2030E | G5: FY2031E | H5: Derivation / source
B6: Stress OPBDITA margin (%) | C6: 19 | D6: 19 | E6: 19 | F6: 19 | G6: 19 | H6: the corrected FY2026 actual was 23.93%, essentially flat on FY2025's 23.52%; stress assumes a full ~490bps of compression sustained for five years - a shock of a magnitude the company has not shown in FY2023-FY2026, testing resilience to a genuine future risk (a sustained further tariff escalation, or a raw-material spike not passed through) rather than modelling a past event
B7: Stress revenue growth (%) | C7: 3 | D7: 3 | E7: 3 | F7: 3 | G7: 3 | H7: held near the FY2026 actual of 3.6% (itself already a tariff-depressed year) rather than the base case's assumed acceleration to 9-10.5%
B9: Revenue | C9: 10823.08 | D9: =C9*(1+D7/100) -> 11147.772 | E9: =D9*(1+E7/100) -> 11482.206 | F9: =E9*(1+F7/100) -> 11826.672 | G9: =F9*(1+G7/100) -> 12181.472 | H9: FY2027E grows off the FY2026 actual of 10,823.08, same starting point as the base case
B10: OPBDITA | C10: =C9*C6/100 -> 2056.3852 | D10: =D9*D6/100 -> 2118.0768 | E10: =E9*E6/100 -> 2181.6191 | F10: =F9*F6/100 -> 2247.0676 | G10: =G9*G6/100 -> 2314.4797
B11: Depreciation (held at base-case level) | C11: =P_and_L!C8 -> 774.96 | D11: =P_and_L!D8 -> 918.96 | E11: =P_and_L!E8 -> 1038.96 | F11: =P_and_L!F8 -> 1170.96 | G11: =P_and_L!G8 -> 1308.96 | H11: capex commitments already made are not reversible in a demand-side stress
B12: Finance costs (held at base-case level, first-order) | C12: =P_and_L!C9 -> 308.3115 | D12: =P_and_L!D9 -> 0 | E12: =P_and_L!E9 -> 0 | F12: =P_and_L!F9 -> 0 | G12: =P_and_L!G9 -> 0 | H12: a simplification - a true second-order stress would also re-solve for higher debt; shown as a lower bound on the stress impact
B13: Profit before tax | C13: =C10-C11-C12 -> 973.1137 | D13: =D10-D11-D12 -> 1199.1168 | E13: =E10-E11-E12 -> 1142.6591 | F13: =F10-F11-F12 -> 1076.1076 | G13: =G10-G11-G12 -> 1005.5197
B14: Profit after tax | C14: =IF(C13>0,C13*(1-Assumptions!C15/100),C13) -> 735.67396 | D14: =IF(D13>0,D13*(1-Assumptions!D15/100),D13) -> 906.53227 | E14: =IF(E13>0,E13*(1-Assumptions!E15/100),E13) -> 863.85025 | F14: =IF(F13>0,F13*(1-Assumptions!F15/100),F13) -> 813.53737 | G14: =IF(G13>0,G13*(1-Assumptions!G15/100),G13) -> 760.17286
B15: Interest coverage in stress (times) | C15: =IF(C12<1,"n/m (net cash)",C10/C12) -> 6.6698297 | D15: =IF(D12<1,"n/m (net cash)",D10/D12) -> n/m (net cash) | E15: =IF(E12<1,"n/m (net cash)",E10/E12) -> n/m (net cash) | F15: =IF(F12<1,"n/m (net cash)",F10/F12) -> n/m (net cash) | G15: =IF(G12<1,"n/m (net cash)",G10/G12) -> n/m (net cash) | H15: against the historical low of 17.22x (FY2026) - the sector methodology's own concern is margin/demand cyclicality, not a leverage covenant breach, and this row shows why: coverage stays comfortable (or the company is net-cash and the ratio not meaningful) even under a sustained further 225bps margin hit
