Workbook

Sheet Assumptions
A1: Jindal Stainless - model assumptions | B1: FY2023 | C1: FY2024 | D1: FY2025 | E1: FY2026 | F1: FY2027E | G1: FY2028E | H1: FY2029E | I1: FY2030E | J1: FY2031E | K1: Basis / source
A2: DRIVERS (yellow = input)
A3: Finished-goods sales volume (MT) | D3: 2.377 | E3: 2.57 | F3: 2.78 | G3: 3 | H3: 3.25 | I3: 3.45 | J3: 3.6 | K3: FY2026 ~2.57 MT stated in the AR (+8.1% Y-o-Y), which implies FY2025 2.377. The company aspires to 3.5 MT by FY2029; this base case haircuts that to 3.25 MT and reaches 3.5 MT only in FY2031 - a deliberate discount to an aspiration, labelled as such rather than adopted
A4: Net sales realisation (Rs/tonne) | D4: 165385.82 | E4: 167138.75 | F4: =E4*(1+F5) | G4: =F4*(1+G5) | H4: =G4*(1+H5) | I4: =H4*(1+I5) | J4: =I4*(1+J5) | K4: revenue / volume; FY2026 actual is the anchor
A5: NSR growth assumption | F5: 0.01 | G5: 0.015 | H5: 0.015 | I5: 0.015 | J5: 0.015 | K5: stainless realisation is nickel/chrome linked; a low single-digit drift is assumed rather than a price view - flexed on Stress_Case
A6: PBILDT margin | B6: 0.10045906 | C6: 0.12199141 | D6: 0.11870689 | E6: 0.12944882 | F6: 0.128 | G6: 0.13 | H6: 0.132 | I6: 0.132 | J6: 0.131 | K6: FY2026 actual 12.97%; held broadly flat - volume operating leverage assumed to offset a richer but more contested value-added mix
A7: Capital expenditure (Rs crore) | F7: 4000 | G7: 3600 | H7: 3200 | I7: 2700 | J7: 2400 | K7: FY2026 actual capex implied by the net-block roll-forward is ~Rs 4,226 cr (net block 14,876 -> 18,042 plus 1,060 of depreciation). The base case starts AT that run-rate and tapers only gradually: the company is still scaling toward a 3.5 MT sales aspiration, so assuming a sharp capex step-down would manufacture a deleveraging that the growth plan contradicts
A8: Depreciation rate on opening net block | F8: 0.071 | G8: 0.071 | H8: 0.071 | I8: 0.071 | J8: 0.071 | K8: FY2025 7.28% and FY2026 7.13% implied; 7.1% carried forward
A9: Interest rate on OPENING debt | F9: 0.078 | G9: 0.078 | H9: 0.078 | I9: 0.078 | J9: 0.078 | K9: implied FY2026 cost; priced on the OPENING balance so the model stays acyclic
A10: Effective tax rate | F10: 0.25 | G10: 0.25 | H10: 0.25 | I10: 0.25 | J10: 0.25 | K10: FY2026 effective rate 24.9%
A11: Dividend payout | F11: 0.12 | G11: 0.12 | H11: 0.12 | I11: 0.12 | J11: 0.12 | K11: broadly the recent payout
A12: Operating net working capital, % of revenue | B12: 0.11347751 | C12: 0.098706074 | D12: 0.083193237 | E12: 0.070035242 | F12: 0.072 | G12: 0.072 | H12: 0.072 | I12: 0.072 | J12: 0.072 | K12: intensity has fallen 11.3% -> 7.0% over FY2023-FY2026; held at 7.2%, a slight normalisation rather than assuming the improvement continues

Sheet P_and_L
A1: Projected profit and loss (Rs crore) | B1: FY2023 | C1: FY2024 | D1: FY2025 | E1: FY2026 | F1: FY2027E | G1: FY2028E | H1: FY2029E | I1: FY2030E | J1: FY2031E | K1: Basis / source
A2: Revenue from operations | B2: 35697.03 | C2: 38562.47 | D2: 39312.21 | E2: 42954.66 | F2: =Assumptions!F3*Assumptions!F4/10 | G2: =Assumptions!G3*Assumptions!G4/10 | H2: =Assumptions!H3*Assumptions!H4/10 | I2: =Assumptions!I3*Assumptions!I4/10 | J2: =Assumptions!J3*Assumptions!J4/10 | K2: volume (MT) x realisation (Rs/t), expressed in Rs crore
A3: PBILDT | B3: 3586.09 | C3: 4704.29 | D3: 4666.63 | E3: 5560.43 | F3: =F2*Assumptions!F6 | G3: =G2*Assumptions!G6 | H3: =H2*Assumptions!H6 | I3: =I2*Assumptions!I6 | J3: =J2*Assumptions!J6 | K3: revenue x margin assumption
A4: Depreciation | B4: 723.75 | C4: 878.83 | D4: 956.12 | E4: 1060.3 | F4: =Balance_Sheet!F3*Assumptions!F8 | G4: =Balance_Sheet!G3*Assumptions!G8 | H4: =Balance_Sheet!H3*Assumptions!H8 | I4: =Balance_Sheet!I3*Assumptions!I8 | J4: =Balance_Sheet!J3*Assumptions!J8 | K4: OPENING net block x depreciation rate
A5: Finance costs | B5: 324.62 | C5: 554.39 | D5: 611.64 | E5: 567.93 | F5: =Balance_Sheet!F4*Assumptions!F9 | G5: =Balance_Sheet!G4*Assumptions!G9 | H5: =Balance_Sheet!H4*Assumptions!H9 | I5: =Balance_Sheet!I4*Assumptions!I9 | J5: =Balance_Sheet!J4*Assumptions!J9 | K5: OPENING total debt x rate - opening, not average, keeps the model acyclic
A6: Profit before tax | B6: 2664.01 | C6: 3440.19 | D6: 3389.72 | E6: 4283.68 | F6: =F3-F4-F5 | G6: =G3-G4-G5 | H6: =H3-H4-H5 | I6: =I3-I4-I5 | J6: =J3-J4-J5 | K6: PBILDT less depreciation less finance costs; no exceptional item or associate share is projected
A7: Profit after tax | B7: 2083.83 | C7: 2693.48 | D7: 2499.72 | E7: 3184.57 | F7: =F6*(1-Assumptions!F10) | G7: =G6*(1-Assumptions!G10) | H7: =H6*(1-Assumptions!H10) | I7: =I6*(1-Assumptions!I10) | J7: =J6*(1-Assumptions!J10)
A8: Dividend | F8: =F7*Assumptions!F11 | G8: =G7*Assumptions!G11 | H8: =H7*Assumptions!H11 | I8: =I7*Assumptions!I11 | J8: =J7*Assumptions!J11 | K8: payout x PAT
A9: Retained earnings | F9: =F7-F8 | G9: =G7-G8 | H9: =H7-H8 | I9: =I7-I8 | J9: =J7-J8

Sheet Balance_Sheet
A1: Balance sheet - debt DERIVED from the funding gap (Rs crore) | B1: FY2023 | C1: FY2024 | D1: FY2025 | E1: FY2026 | F1: FY2027E | G1: FY2028E | H1: FY2029E | I1: FY2030E | J1: FY2031E | K1: Basis / source
A2: OPENING BALANCES (referenced by P_and_L - do not move these rows)
A3: Opening net fixed assets | C3: 9776.21 | D3: 13141.09 | E3: 14876.46 | F3: =E15 | G3: =F15 | H3: =G15 | I3: =H15 | J3: =I15 | K3: prior year's closing net block
A4: Opening total debt | C4: 3958.17 | D4: 6052.26 | E4: 6401.87 | F4: =E11 | G4: =F11 | H4: =G11 | I4: =H11 | J4: =I11 | K4: prior year's closing debt - the balance finance costs are priced on
A6: FUNDING GAP -> CLOSING DEBT (failure mode 18: derived, never extrapolated)
A7: Add: capital expenditure | F7: =Assumptions!F7 | G7: =Assumptions!G7 | H7: =Assumptions!H7 | I7: =Assumptions!I7 | J7: =Assumptions!J7 | K7: Assumptions
A8: Add: increase in operating working capital | F8: =F16-E16 | G8: =G16-F16 | H8: =H16-G16 | I8: =I16-H16 | J8: =J16-I16 | K8: year-on-year movement in operating net working capital
A9: Add: dividend | F9: =P_and_L!F8 | G9: =P_and_L!G8 | H9: =P_and_L!H8 | I9: =P_and_L!I8 | J9: =P_and_L!J8 | K9: from P_and_L
A10: Less: cash generated (PAT + depreciation) | F10: =P_and_L!F7+P_and_L!F4 | G10: =P_and_L!G7+P_and_L!G4 | H10: =P_and_L!H7+P_and_L!H4 | I10: =P_and_L!I7+P_and_L!I4 | J10: =P_and_L!J7+P_and_L!J4 | K10: internal accrual available to fund the above
A11: CLOSING TOTAL DEBT (derived) | B11: 3958.17 | C11: 6052.26 | D11: 6401.87 | E11: 7460.33 | F11: =MAX(0,F4+F7+F8+F9-F10) | G11: =MAX(0,G4+G7+G8+G9-G10) | H11: =MAX(0,H4+H7+H8+H9-H10) | I11: =MAX(0,I4+I7+I8+I9-I10) | J11: =MAX(0,J4+J7+J8+J9-J10) | K11: opening debt + capex + working-capital build + dividend - internal accrual. Debt is an OUTPUT of this arithmetic, never an input. Floored at zero so a negative funding gap surfaces as net cash below rather than as negative debt
A12: Memo: net cash surplus if the funding gap turns negative | F12: =MAX(0,-(F4+F7+F8+F9-F10)) | G12: =MAX(0,-(G4+G7+G8+G9-G10)) | H12: =MAX(0,-(H4+H7+H8+H9-H10)) | I12: =MAX(0,-(I4+I7+I8+I9-I10)) | J12: =MAX(0,-(J4+J7+J8+J9-J10)) | K12: kept separate so a surplus cannot masquerade as negative debt
A14: CLOSING BALANCE SHEET
A15: Closing net fixed assets | B15: 9776.21 | C15: 13141.09 | D15: 14876.46 | E15: 18041.62 | F15: =F3+F7-P_and_L!F4 | G15: =G3+G7-P_and_L!G4 | H15: =H3+H7-P_and_L!H4 | I15: =I3+I7-P_and_L!I4 | J15: =J3+J7-P_and_L!J4 | K15: opening + capex - depreciation
A16: Operating net working capital | B16: 4050.81 | C16: 3806.35 | D16: 3270.51 | E16: 3008.34 | F16: =P_and_L!F2*Assumptions!F12 | G16: =P_and_L!G2*Assumptions!G12 | H16: =P_and_L!H2*Assumptions!H12 | I16: =P_and_L!I2*Assumptions!I12 | J16: =P_and_L!J2*Assumptions!J12 | K16: revenue x working-capital intensity; excludes short-term debt, which is funding
A17: Tangible net worth | B17: 11009.7 | C17: 13149.16 | D17: 15001.41 | E17: 17900.83 | F17: =E17+P_and_L!F9 | G17: =F17+P_and_L!G9 | H17: =G17+P_and_L!H9 | I17: =H17+P_and_L!I9 | J17: =I17+P_and_L!J9 | K17: prior TNW + retained earnings; no equity issue assumed
A18: Capital employed | B18: =B15+B16 | C18: =C15+C16 | D18: =D15+D16 | E18: =E15+E16 | F18: =F15+F16 | G18: =G15+G16 | H18: =H15+H16 | I18: =I15+I16 | J18: =J15+J16 | K18: closing net fixed assets + operating net working capital

Sheet Credit_Ratios
A1: Credit ratios - CareEdge conventions, by formula off the three statements | B1: FY2023 | C1: FY2024 | D1: FY2025 | E1: FY2026 | F1: FY2027E | G1: FY2028E | H1: FY2029E | I1: FY2030E | J1: FY2031E | K1: Basis / source
A2: PBILDT margin (%) | B2: =100*P_and_L!B3/P_and_L!B2 | C2: =100*P_and_L!C3/P_and_L!C2 | D2: =100*P_and_L!D3/P_and_L!D2 | E2: =100*P_and_L!E3/P_and_L!E2 | F2: =100*P_and_L!F3/P_and_L!F2 | G2: =100*P_and_L!G3/P_and_L!G2 | H2: =100*P_and_L!H3/P_and_L!H2 | I2: =100*P_and_L!I3/P_and_L!I2 | J2: =100*P_and_L!J3/P_and_L!J2
A3: Overall gearing (times) | B3: =Balance_Sheet!B11/Balance_Sheet!B17 | C3: =Balance_Sheet!C11/Balance_Sheet!C17 | D3: =Balance_Sheet!D11/Balance_Sheet!D17 | E3: =Balance_Sheet!E11/Balance_Sheet!E17 | F3: =Balance_Sheet!F11/Balance_Sheet!F17 | G3: =Balance_Sheet!G11/Balance_Sheet!G17 | H3: =Balance_Sheet!H11/Balance_Sheet!H17 | I3: =Balance_Sheet!I11/Balance_Sheet!I17 | J3: =Balance_Sheet!J11/Balance_Sheet!J17 | K3: total debt / tangible net worth; UNADJUSTED (see Conventions in the spreads)
A4: Total debt/PBILDT (times) | B4: =Balance_Sheet!B11/P_and_L!B3 | C4: =Balance_Sheet!C11/P_and_L!C3 | D4: =Balance_Sheet!D11/P_and_L!D3 | E4: =Balance_Sheet!E11/P_and_L!E3 | F4: =Balance_Sheet!F11/P_and_L!F3 | G4: =Balance_Sheet!G11/P_and_L!G3 | H4: =Balance_Sheet!H11/P_and_L!H3 | I4: =Balance_Sheet!I11/P_and_L!I3 | J4: =Balance_Sheet!J11/P_and_L!J3
A5: Interest coverage (times) | B5: =IF(OR(P_and_L!B5<=0,P_and_L!B3/P_and_L!B5>100),"n/m (net cash)",P_and_L!B3/P_and_L!B5) | C5: =IF(OR(P_and_L!C5<=0,P_and_L!C3/P_and_L!C5>100),"n/m (net cash)",P_and_L!C3/P_and_L!C5) | D5: =IF(OR(P_and_L!D5<=0,P_and_L!D3/P_and_L!D5>100),"n/m (net cash)",P_and_L!D3/P_and_L!D5) | E5: =IF(OR(P_and_L!E5<=0,P_and_L!E3/P_and_L!E5>100),"n/m (net cash)",P_and_L!E3/P_and_L!E5) | F5: =IF(OR(P_and_L!F5<=0,P_and_L!F3/P_and_L!F5>100),"n/m (net cash)",P_and_L!F3/P_and_L!F5) | G5: =IF(OR(P_and_L!G5<=0,P_and_L!G3/P_and_L!G5>100),"n/m (net cash)",P_and_L!G3/P_and_L!G5) | H5: =IF(OR(P_and_L!H5<=0,P_and_L!H3/P_and_L!H5>100),"n/m (net cash)",P_and_L!H3/P_and_L!H5) | I5: =IF(OR(P_and_L!I5<=0,P_and_L!I3/P_and_L!I5>100),"n/m (net cash)",P_and_L!I3/P_and_L!I5) | J5: =IF(OR(P_and_L!J5<=0,P_and_L!J3/P_and_L!J5>100),"n/m (net cash)",P_and_L!J3/P_and_L!J5) | K5: guarded twice: at zero finance costs, and above 100x. A ratio of 290x is arithmetically correct but analytically meaningless - once debt approaches nil the coverage ratio stops measuring anything and should say so
A6: PBILDT per tonne (Rs) | B6: =IF(N(Assumptions!B3)=0,"n/a - volume not disclosed",P_and_L!B3*10000000/(Assumptions!B3*1000000)) | C6: =IF(N(Assumptions!C3)=0,"n/a - volume not disclosed",P_and_L!C3*10000000/(Assumptions!C3*1000000)) | D6: =IF(N(Assumptions!D3)=0,"n/a - volume not disclosed",P_and_L!D3*10000000/(Assumptions!D3*1000000)) | E6: =IF(N(Assumptions!E3)=0,"n/a - volume not disclosed",P_and_L!E3*10000000/(Assumptions!E3*1000000)) | F6: =IF(N(Assumptions!F3)=0,"n/a - volume not disclosed",P_and_L!F3*10000000/(Assumptions!F3*1000000)) | G6: =IF(N(Assumptions!G3)=0,"n/a - volume not disclosed",P_and_L!G3*10000000/(Assumptions!G3*1000000)) | H6: =IF(N(Assumptions!H3)=0,"n/a - volume not disclosed",P_and_L!H3*10000000/(Assumptions!H3*1000000)) | I6: =IF(N(Assumptions!I3)=0,"n/a - volume not disclosed",P_and_L!I3*10000000/(Assumptions!I3*1000000)) | J6: =IF(N(Assumptions!J3)=0,"n/a - volume not disclosed",P_and_L!J3*10000000/(Assumptions!J3*1000000)) | K6: the metals-sector unit-economics metric. Guarded: the company discloses sales volume only from FY2025, so FY2023 and FY2024 divide by an empty cell. Unguarded this returned #DIV/0! - reported as not-disclosed rather than left as an error, and never back-filled with an estimate
A7: Return on capital employed (%) | B7: =100*(P_and_L!B3-P_and_L!B4)/Balance_Sheet!B18 | C7: =100*(P_and_L!C3-P_and_L!C4)/Balance_Sheet!C18 | D7: =100*(P_and_L!D3-P_and_L!D4)/Balance_Sheet!D18 | E7: =100*(P_and_L!E3-P_and_L!E4)/Balance_Sheet!E18 | F7: =100*(P_and_L!F3-P_and_L!F4)/Balance_Sheet!F18 | G7: =100*(P_and_L!G3-P_and_L!G4)/Balance_Sheet!G18 | H7: =100*(P_and_L!H3-P_and_L!H4)/Balance_Sheet!H18 | I7: =100*(P_and_L!I3-P_and_L!I4)/Balance_Sheet!I18 | J7: =100*(P_and_L!J3-P_and_L!J4)/Balance_Sheet!J18

Sheet Debt_Breakup
A1: Debt break-up - statutory decomposition, tied to the annual report | B1: FY2023 | C1: FY2024 | D1: FY2025 | E1: FY2026 | F1: FY2027E | G1: FY2028E | H1: FY2029E | I1: FY2030E | J1: FY2031E | K1: Basis / source
A2: Borrowings - non-current | B2: 2791.79 | C2: 4562.76 | D2: 4319.72 | E2: 4935.93 | K2: AR consolidated balance sheet, note 18
A3: Borrowings - current | B3: 1079.64 | C3: 1385.43 | D3: 1978.01 | E3: 2405.66 | K3: AR consolidated balance sheet, note 23
A4: Lease liabilities - non-current | B4: 70.01 | C4: 89.48 | D4: 92.77 | E4: 93.77 | K4: AR note 19
A5: Lease liabilities - current | B5: 16.73 | C5: 14.59 | D5: 11.37 | E5: 24.97 | K5: AR note 19
A6: Total debt (CareEdge convention) | B6: 3958.17 | C6: 6052.26 | D6: 6401.87 | E6: 7460.33 | K6: borrowings + leases; UNADJUSTED - acceptances and group guarantees are not separately disclosed, so CareEdge's adjusted gearing cannot be reproduced
A7: Memo: borrowings excluding leases | B7: 3871.43 | C7: 5948.19 | D7: 6297.73 | E7: 7341.59 | K7: ties exactly to the FY2023-24 AR capital-management note (FY2023 3,871.43; FY2024 5,948.19)
A9: RATED LIMITS vs DRAWN DEBT - different measures, never to be conflated (failure mode 13)
A10: CareEdge rated: long-term bank facilities | B10: 5900 | K10: CareEdge press release, 09-Oct-2025 - CRA-published, not issuer-confirmed
A11: CareEdge rated: short-term bank facilities | B11: 11000 | K11: CareEdge press release, 09-Oct-2025 - CRA-published, not issuer-confirmed
A12: CareEdge rated: NCD | B12: 99 | K12: CareEdge press release, 09-Oct-2025
A13: CareEdge rated: NCD (proposed) | B13: 1000 | K13: CareEdge press release, 09-Oct-2025
A14: Total rated LIMITS | B14: 17999 | K14: lines verified to sum to the published total (failure mode 12); these are LIMITS
A15: Drawn debt at 31-Mar-2026 | B15: 7460.33 | K15: balance-sheet borrowings + leases - a different measure from rated limits, and the two will not agree

Sheet Stress_Case
A1: Stress case - the variables CareEdge's manufacturing criteria name | B1: FY2023 | C1: FY2024 | D1: FY2025 | E1: FY2026 | F1: FY2027E | G1: FY2028E | H1: FY2029E | I1: FY2030E | J1: FY2031E | K1: Basis / source
A2: STRESS APPLIED TO THE BASE CASE
A3: Variable | B3: Base case | E3: Stressed
A4: Sales volume | B4: 2.78 -> 3.60 MT | E4: flat at FY2026's 2.57 MT | K4: a global oversupply / import-pressure scenario; the AR itself notes world stainless melt output growing only 0.3% in CY2026 and 2.2% in CY2027
A5: Net sales realisation | B5: +1.0-1.5% p.a. | E5: -6% in year 1, then flat | K5: nickel and chrome linked realisation shock
A6: PBILDT margin | B6: 12.8-13.2% | E6: 10.5% year 1, recovering to 11.5% | K6: operating deleverage on flat volume plus an unrecovered input-cost move
A7: Capital expenditure | B7: Rs 3,200 cr tapering | E7: held at plan year 1, then cut 40% | K7: committed spend cannot be stopped immediately - year one is largely sunk, which is precisely why a demand shock hits leverage before it hits capex
A9: INDICATIVE STRESSED OUTCOME, YEAR 1 (FY2027)
A10: Revenue (Rs crore) | B10: 40377.38 | K10: flat volume at a 6% lower realisation
A11: PBILDT (Rs crore) | B11: 4239.6249 | K11: at a 10.5% stressed margin
A12: PBILDT margin (%) | B12: 10.5
A13: Total debt/PBILDT (times) | B13: 1.7596674 | K13: on FY2026 closing debt held flat - conservative, since a demand shock also releases working capital
A14: Interest coverage (times) | B14: 7.2857589
A16: Read-across: on this stress the issuer still holds about 1.76x total debt/PBILDT and about 7.3x interest coverage - both computed in the rows above rather than asserted, after an earlier draft of this tab carried 1.9x and 4x that had never been computed from anything. That is a rating-TOLERANCE outcome rather than a rating-transition one, which is the point of running it.
