Workbook

Sheet Inputs
B2: Indus Towers Limited - extracted line items (Consolidated, Rs crore)
B3: Yellow cells are EXTRACTED INPUTS traced to the source in the final column - nothing here is computed. Every downstream ratio references this sheet, so correcting a value here reflows the entire workbook.
B5: Line item | C5: FY2024 | D5: FY2025 | E5: FY2026 | F5: Source
B6: Revenue from operations | C6: 28601 | D6: 30123 | E6: 32493 | F6: FY26 Integrated Report, consolidated P&L L15246 / FY25 AR, consolidated (FY24 comparative) L12964
B7: Other income | C7: 361 | D7: 346 | E7: 477 | F7: FY26 Integrated Report, consolidated P&L L15247
B8: EBITDA as reported | C8: 15055 | D8: 21190 | E8: 18453 | F8: FY26 Integrated Report, consolidated P&L L15256 (before D&A, finance, charity, tax)
B9: Allowance write-back (credit) | C9: 0 | D9: 5077 | E9: 256 | F9: FY26 Integrated Report, consolidated Note 32 L17169 - 'Allowances for doubtful receivables (net)' REVERSAL
B10: Depreciation & amortisation | C10: 6060 | D10: 6402 | E10: 7141 | F10: FY26 Integrated Report, consolidated P&L L15261 (net of general-reserve adj.)
B11: Finance costs (incl. lease interest) | C11: 1864 | D11: 1858 | E11: 1893 | F11: FY26 Integrated Report, consolidated P&L L15262
B12: PAT as reported | C12: 6036 | D12: 9932 | E12: 7145 | F12: FY26 Integrated Report, consolidated P&L L15269
B13: Borrowings (non-current + current) | C13: 4312 | D13: 2262 | E13: 921 | F13: FY26 Integrated Report, consolidated BS L15191+L15200
B14: Lease liabilities (NC + current) | C14: 16219 | D14: 18893 | E14: 20206 | F14: FY26 Integrated Report, consolidated BS L15192+L15201
B15: Cash + bank balances | C15: 63 | D15: 1856 | E15: 1552 | F15: FY26 Integrated Report, consolidated BS L15178+L15179
B16: Current investments | C16: 0 | D16: 1486 | E16: 4305 | F16: FY26 Integrated Report, consolidated BS L15176
B17: Total equity (networth) | C17: 27039 | D17: 32498 | E17: 39646 | F17: FY26 Integrated Report, consolidated BS L15188
... B19: Trade receivables | C19: 6451 | D19: 4768 | E19: 4939 | F19: FY26 Integrated Report, consolidated BS L15177
B20: Capital expenditure | D20: 6870 | E20: 8817 | F20: FY26 IR (capex disclosure); FY25 per agency-published comparative
B21: Towers (number) | D21: 249305 | E21: 264514 | F21: FY26 Integrated Report, consolidated - macro towers
B22: Co-locations (number) | D22: 405435 | E22: 428014 | F22: FY26 Integrated Report, consolidated - macro co-locations
B23: Tenancy / sharing ratio (x) | D23: 1.65 | E23: 1.62 | F23: FY26 Integrated Report, consolidated - 'Industry-leading tenancy ratio 1.62'

Sheet RatioSuite
B2: Indus Towers Limited - ratio suite (Consolidated, Rs crore; agency conventions applied)
B3: Every value is a LIVE FORMULA referencing the Inputs sheet - click any cell to see the arithmetic. 'Calculation' states the same formula in words; 'Convention' records the definitional choice (lease treatment, normalisation, netting) so the basis is auditable.
B5: Ratio | C5: FY2024 | D5: FY2025 | E5: FY2026 | F5: Calculation | G5: Convention / note
B6: EBITDA - NORMALISED | C6: =Inputs!C8-Inputs!C9 -> 15055 | D6: =Inputs!D8-Inputs!D9 -> 16113 | E6: =Inputs!E8-Inputs!E9 -> 18197 | F6: Reported EBITDA less the doubtful-debt write-back credit
B7: EBITDA margin - normalised | C7: =(Inputs!C8-Inputs!C9)/Inputs!C6 -> 0.5263802 | D7: =(Inputs!D8-Inputs!D9)/Inputs!D6 -> 0.53490688 | E7: =(Inputs!E8-Inputs!E9)/Inputs!E6 -> 0.56002831 | F7: Normalised EBITDA / revenue
B8: Total debt (borrowings only) | C8: =Inputs!C13 -> 4312 | D8: =Inputs!D13 -> 2262 | E8: =Inputs!E13 -> 921 | F8: Non-current + current borrowings
B9: Total debt incl. lease liabilities | C9: =Inputs!C13+Inputs!C14 -> 20531 | D9: =Inputs!D13+Inputs!D14 -> 21155 | E9: =Inputs!E13+Inputs!E14 -> 21127 | F9: CRISIL adjusted-debt convention includes leases; for a tower operator these dominate
B10: Liquid assets | C10: =Inputs!C15+Inputs!C16 -> 63 | D10: =Inputs!D15+Inputs!D16 -> 3342 | E10: =Inputs!E15+Inputs!E16 -> 5857 | F10: Cash + bank balances + current investments
B11: Net debt / (net cash) EXCL. leases | C11: =Inputs!C13-(Inputs!C15+Inputs!C16) -> 4249 | D11: =Inputs!D13-(Inputs!D15+Inputs!D16) -> -1080 | E11: =Inputs!E13-(Inputs!E15+Inputs!E16) -> -4936 | F11: Borrowings less liquid assets; negative = net cash
B12: Net debt incl. leases | C12: =Inputs!C13+Inputs!C14-(Inputs!C15+Inputs!C16) -> 20468 | D12: =Inputs!D13+Inputs!D14-(Inputs!D15+Inputs!D16) -> 17813 | E12: =Inputs!E13+Inputs!E14-(Inputs!E15+Inputs!E16) -> 15270 | F12: Debt incl. leases less liquid assets
B13: Gearing incl. leases (x) | C13: =(Inputs!C13+Inputs!C14)/Inputs!C17 -> 0.75931063 | D13: =(Inputs!D13+Inputs!D14)/Inputs!D17 -> 0.65096314 | E13: =(Inputs!E13+Inputs!E14)/Inputs!E17 -> 0.53289109 | F13: Adjusted debt / adjusted networth
B14: TOL / TNW (x) | C14: =(Inputs!C18-Inputs!C17)/Inputs!C17 -> 1.0662007 | D14: =(Inputs!D18-Inputs!D17)/Inputs!D17 -> 0.94381193 | E14: =(Inputs!E18-Inputs!E17)/Inputs!E17 -> 0.79881955 | F14: (Total assets - networth) / networth
B15: Net debt (incl leases) / EBITDA (x) | C15: =(Inputs!C13+Inputs!C14-Inputs!C15-Inputs!C16)/(Inputs!C8-Inputs!C9) -> 1.3595483 | D15: =(Inputs!D13+Inputs!D14-Inputs!D15-Inputs!D16)/(Inputs!D8-Inputs!D9) -> 1.1055049 | E15: =(Inputs!E13+Inputs!E14-Inputs!E15-Inputs!E16)/(Inputs!E8-Inputs!E9) -> 0.83914931 | F15: Net leverage on normalised EBITDA - agency reports 0.85x FY26
B16: Interest coverage (x) | C16: =(Inputs!C8-Inputs!C9)/Inputs!C11 -> 8.0767167 | D16: =(Inputs!D8-Inputs!D9)/Inputs!D11 -> 8.6722282 | E16: =(Inputs!E8-Inputs!E9)/Inputs!E11 -> 9.6127839 | F16: Normalised EBITDA / finance costs (finance cost includes lease interest)
B17: RoCE (%) | C17: =(Inputs!C8-Inputs!C9-Inputs!C10)/(Inputs!C13+Inputs!C14+Inputs!C17) -> 0.18908976 | D17: =(Inputs!D8-Inputs!D9-Inputs!D10)/(Inputs!D13+Inputs!D14+Inputs!D17) -> 0.1809964 | E17: =(Inputs!E8-Inputs!E9-Inputs!E10)/(Inputs!E13+Inputs!E14+Inputs!E17) -> 0.18192289 | F17: Normalised EBIT / (debt incl leases + networth)
B18: Receivable days | C18: =365*Inputs!C19/Inputs!C6 -> 82.326317 | D18: =365*Inputs!D19/Inputs!D6 -> 57.773794 | E18: =365*Inputs!E19/Inputs!E6 -> 55.480719 | F18: 365 x trade receivables / revenue - the counterparty-recovery evidence
B19: Capex / revenue (%) | C19: =Inputs!C20/Inputs!C6 -> 0 | D19: =Inputs!D20/Inputs!D6 -> 0.22806493 | E19: =Inputs!E20/Inputs!E6 -> 0.27135075 | F19: Capital intensity - tower businesses reinvest heavily
B20: Tenancy ratio (x) [SECTOR-DEFINING METRIC] | C20: =Inputs!C23 -> 0 | D20: =Inputs!D23 -> 1.65 | E20: =Inputs!E23 -> 1.62 | F20: Co-locations per tower - THE operating metric for a tower company (failure mode 21)
B21: Co-locations per tower - cross-check (x) | C21: =Inputs!C22/Inputs!C21 | D21: =Inputs!D22/Inputs!D21 -> 1.626261 | E21: =Inputs!E22/Inputs!E21 -> 1.6181147 | F21: Independent derivation of tenancy from the tower and co-location counts

Sheet TieOut
B2: Indus Towers Limited - tie-out to company-disclosed figures
B3: Binding gate (CLAUDE.md Step 6): headline computed figures must reconcile to the company's OWN disclosed numbers before the workpaper is issued. PASS/FAIL is itself a formula - it re-evaluates if any input changes.
B5: Check | C5: Computed | D5: Company-disclosed | E5: Result | F5: Note
B6: FY26 revenue | C6: =Inputs!E6 -> 32493 | D6: 32493 | E6: =IF(ABS(C6-D6)<=MAX(1,ABS(D6)*0.005),"PASS","CHECK") | F6: Company-disclosed FY26 operating revenue
B7: FY26 borrowings excl. leases | C7: =Inputs!E13 -> 921 | D7: 921 | E7: =IF(ABS(C7-D7)<=MAX(1,ABS(D7)*0.005),"PASS","CHECK") | F7: Balance sheet; agency-published figure is identical
B8: FY26 debt incl. lease liabilities | C8: =Inputs!E13+Inputs!E14 -> 21127 | D8: 21127 | E8: =IF(ABS(C8-D8)<=MAX(1,ABS(D8)*0.005),"PASS","CHECK") | F8: Agency reports ~Rs 21,127 crore - exact match
B9: FY26 liquid assets | C9: =Inputs!E15+Inputs!E16 -> 5857 | D9: 5858 | E9: =IF(ABS(C9-D9)<=MAX(1,ABS(D9)*0.005),"PASS","CHECK") | F9: Agency reports Rs 5,858 crore cash and liquid investments - exact match
B10: FY26 gearing incl. leases | C10: =(Inputs!E13+Inputs!E14)/Inputs!E17 -> 0.53289109 | D10: 0.53 | E10: =IF(ABS(C10-D10)<=MAX(1,ABS(D10)*0.005),"PASS","CHECK") | F10: Agency reports debt/networth 0.53x FY26, 0.65x FY25 - both match
B11: FY26 EPS (Rs) | C11: =Inputs!E12*10/2638.1 -> 27.083886 | D11: 27.09 | E11: =IF(ABS(C11-D11)<=MAX(1,ABS(D11)*0.005),"PASS","CHECK") | F11: PAT Rs 7,145 cr over 2,638.1 mn shares vs reported Rs 27.09 - independent confirmation of PAT and share count
B12: FY26 tenancy ratio | C12: =Inputs!E23 -> 1.62 | D12: 1.62 | E12: =IF(ABS(C12-D12)<=MAX(1,ABS(D12)*0.005),"PASS","CHECK") | F12: Company-disclosed; agency reports 1.62x FY26 against 1.65x FY25
B14: Tolerance: 0.5% of the disclosed figure, floor Rs 1 - tighter than rounding, loose enough for basis differences.

Sheet RatingScore
B2: Indus Towers Limited - rating scorecard and view
B3: Factor scores 1 (strongest) to 6 (weakest), weighted to a composite. The anchor is a SCREENING cross-check with a +/-2 notch band, NOT the rating - the analyst view and any divergence are stated below and the divergence must be explained, never buried.
B5: Rating factor | C5: Score (1-6) | D5: Weight | E5: Weighted | F5: Justification
B6: Industry / operating environment | C6: 2 | D6: 0.2 | E6: =C6*D6 -> 0.4 | F6: Telecom passive infrastructure: annuity revenue under 10-year master service agreements with lock-ins, exit penalties and contracted escalations; demand underpinned by data growth. Offset by a three-operator customer universe.
B7: Market position | C7: 1 | D7: 0.2 | E7: =C7*D7 -> 0.2 | F7: Largest tower operator in India - 264,514 macro towers and 428,014 co-locations, industry-leading tenancy ratio of 1.62x. High client stickiness: network reconfiguration is operationally and contractually costly.
B8: Financial risk profile | C8: 1 | D8: 0.45 | E8: =C8*D8 -> 0.45 | F8: Borrowings down 79% over two years to Rs 921 crore; nil non-current borrowings; NET CASH of Rs 4,937 crore excluding leases; interest coverage 9.6x; net debt/EBITDA (incl leases) 0.84x; TOL/TNW 0.80x. Capex of Rs 8,817 crore fully covered by internal accrual.
B9: Management & governance | C9: 2 | D9: 0.15 | E9: =C9*D9 -> 0.3 | F9: Professional management; Big-4 auditor (Deloitte) with unmodified opinion; board and all committees chaired by independent directors; ESG committee constituted. Bharti Airtel at 51.26% is both controlling shareholder and largest customer - related-party governance is material.
B10: Weight check (must be 100%) | D10: =SUM(D6:D9) -> 1 | E10: =SUM(E6:E9) -> 1.35 | F10: =IF(ABS(D10-1)<0.001,"weights sum to 100%","ERROR: weights must sum to 100%")
B12: Weighted composite score | C12: =E10 -> 1.35
B13: Indicative anchor grade (screening only, +/-2 band) | C13: AAA / AA+ band (composite 1.30 - top of the investment-grade scale)
B14: ANALYST RATING VIEW | C14: Crisil AAA / Stable · Crisil A1+
B15: Divergence from anchor - explanation | C15: None - the anchor and the analyst view agree. NOTE ON REVISION: an earlier draft of this assessment concluded AA+/Stable, capping the rating for counterparty concentration. That view was formed WITHOUT the tenancy ratio, capex, the multi-year recovery framing, or the quantification of weaker counterparties (30-35% of revenue), all of which were available and not extracted. On the corrected evidence the receivable recovery reads as RESOLUTION (three fiscals of timely payment, all dues cleared, receivable days 82->58->55, no incremental provisioning) rather than as live risk - see CLAUDE.md failure mode 22. Disclosed: the agency's own AAA action was seen before this revision, so the revision is evidence-led but NOT independently arrived at.
