Workbook

Sheet Inputs
B2: HDFC Securities Limited - extracted line items (Standalone, Rs crore)
B3: Yellow cells are EXTRACTED INPUTS traced to the source in the final column - nothing here is computed. Every downstream ratio references this sheet, so correcting a value here reflows the entire workbook.
B5: Line item | C5: FY2025 | D5: FY2026 | E5: Q1FY2027 | F5: Source
B6: RATED: commercial paper limit | C6: 18000 | D6: 20000 | E6: 20000 | F6: CareEdge press release 20-Aug-2026 (operator-supplied) header table - enhanced from Rs 18,000.00 cr. NOT an outstanding balance
B7: RATED: LT/ST bank facilities limit | C7: 3000 | D7: 3000 | E7: 3000 | F7: CareEdge press release 20-Aug-2026 (operator-supplied) header table - CARE AAA; Stable / CARE A1+, Reaffirmed
B8: Total income | C8: 3264.86 | D8: 3110.15 | E8: 950.03 | F8: FY2026 annual report (04-08-2026) P&L L3115
B9: Total expenses | C9: 1768.71 | D9: 1873.09 | F9: FY2026 annual report (04-08-2026) P&L L3122
B10: Finance costs | C10: 785.45 | D10: 817.4 | F10: FY2026 annual report (04-08-2026) P&L L3117
B11: Profit after tax | C11: 1125 | D11: 929.9 | E11: 297.06 | F11: FY2026 annual report (04-08-2026) / Q1 results
B12: Interest income | C12: 1418.34 | D12: 1497.93 | F12: FY2026 annual report (04-08-2026) P&L L3107
B13: Fees and commission income | C13: 1744.2 | D13: 1515.83 | F13: FY2026 annual report (04-08-2026) P&L
B14: Brokerage income | C14: 1259.55 | D14: 1012.19 | F14: FY2026 annual report (04-08-2026) note L5090
B15: Dividend (interim + final) | C15: 898.3 | D15: 740.1 | F15: FY2026 annual report (04-08-2026) appropriation
B16: Total equity | C16: 3348.59 | D16: 3595.92 | F16: FY2026 annual report (04-08-2026) L6633
B17: less: deferred tax assets | C17: 0.52 | D17: 15.57 | F17: FY2026 annual report (04-08-2026) BS L3033
B18: less: other intangible assets | C18: 84.24 | D18: 78.23 | F18: FY2026 annual report (04-08-2026) BS L3038
B19: less: intangibles under development | C19: 7.32 | D19: 5.63 | F19: FY2026 annual report (04-08-2026) BS L3037
B20: TANGIBLE NET WORTH (published) | C20: 3257 | D20: 3496 | E20: 3647 | F20: CareEdge press release 20-Aug-2026 (operator-supplied) Brief Financials - reproduced exactly by the build-up above
B21: Debt securities (commercial paper) | C21: 7741.52 | D21: 12931.33 | E21: 15765 | F21: FY2026 annual report (04-08-2026) BS / CareEdge press release 20-Aug-2026 (operator-supplied)
B22: Borrowings other than debt secs (TREPS) | C22: 202.25 | D22: 2182.55 | E22: 2183 | F22: FY2026 annual report (04-08-2026) BS / CareEdge press release 20-Aug-2026 (operator-supplied)
B23: Loan against deposits | E23: 338 | F23: CareEdge press release 20-Aug-2026 (operator-supplied) liquidity para
B24: TOTAL FUND-BASED DEBT | C24: 7943.77 | D24: 15113.88 | E24: 18286 | F24: FY2026 annual report (04-08-2026) / CareEdge press release 20-Aug-2026 (operator-supplied)
B25: Bank guarantees outstanding | C25: 700 | D25: 1100 | F25: FY2026 annual report (04-08-2026) CONTINGENT LIABILITIES note L5421 - off balance sheet, and CareEdge counts it in gearing. v1 never extracted this, hence 4.20x against a published 4.64x
B26: Total assets | C26: 14031.11 | D26: 21784.33 | F26: FY2026 annual report (04-08-2026) BS
B27: MTF loan book | C27: 5511.87 | D27: 7132.66 | E27: 10081 | F27: FY2026 annual report (04-08-2026) BS Loans / CareEdge press release 20-Aug-2026 (operator-supplied) - Rs 10,081 cr as on 30-Jun-2026
B28: UNENCUMBERED cash and equivalents | E28: 422 | F28: CareEdge press release 20-Aug-2026 (operator-supplied) liquidity para. NOT the balance-sheet 'bank balance' line of Rs 7,838.73 cr, which is overwhelmingly CLIENT funds and exchange margin
B29: Unutilised sanctioned lines | E29: 2698 | F29: CareEdge press release 20-Aug-2026 (operator-supplied) liquidity para
B30: Active clients (lakh) | E30: 10.05 | F30: CareEdge press release 20-Aug-2026 (operator-supplied) - ~10.05 lakh as on 31-Jul-2026; SIXTH-largest retail stockbroker
B31: Branches (no.) | C31: 134 | D31: 128 | E31: 127 | F31: FY2025 AR / FY2026 AR / CareEdge press release 20-Aug-2026 (operator-supplied). 184 at 31-Mar-2024 - consolidating toward digital

Sheet RatioSuite
B2: HDFC Securities Limited - ratio suite (Standalone, Rs crore; agency conventions applied)
B3: Every value is a LIVE FORMULA referencing the Inputs sheet - click any cell to see the arithmetic. 'Calculation' states the same formula in words; 'Convention' records the definitional choice (lease treatment, normalisation, netting) so the basis is auditable.
B5: Ratio | C5: FY2025 | D5: FY2026 | E5: Q1FY2027 | F5: Calculation | G5: Convention / note
B6: TANGIBLE NET WORTH (computed) | C6: =IF(N(Inputs!C16)=0,"",Inputs!C16-Inputs!C17-Inputs!C18-Inputs!C19) -> 3256.51 | D6: =IF(N(Inputs!D16)=0,"",Inputs!D16-Inputs!D17-Inputs!D18-Inputs!D19) -> 3496.49 | E6: =IF(N(Inputs!E16)=0,"",Inputs!E16-Inputs!E17-Inputs!E18-Inputs!E19) | F6: Total equity less deferred tax assets and all intangibles — CareEdge's net-worth definition for financial-sector entities. Reproduces the published Rs 3,257 cr / Rs 3,496 cr EXACTLY. v1 used total equity and was wrong by ~Rs 100 cr
B7: Overall gearing (x) [KEY] | C7: =IF(N(Inputs!C25)=0,"",(Inputs!C24+Inputs!C25)/Inputs!C20) -> 2.6539054 | D7: =IF(N(Inputs!D25)=0,"",(Inputs!D24+Inputs!D25)/Inputs!D20) -> 4.6378375 | E7: =IF(N(Inputs!E25)=0,"",(Inputs!E24+Inputs!E25)/Inputs!E20) | F7: (Total fund-based debt + bank guarantees outstanding) / tangible net worth — INCLUDES non-fund-based limits utilised - CareEdge's own footnote. Reproduces published 2.65x and 4.64x exactly; 5.28x as on 30-Jun-2026. v1 published 4.20x on plain debt/equity
B8: Fund-based gearing (x) | C8: =Inputs!C24/Inputs!C20 -> 2.4389837 | D8: =Inputs!D24/Inputs!D20 -> 4.3231922 | E8: =Inputs!E24/Inputs!E20 -> 5.0139841 | F8: Total fund-based debt / tangible net worth — Borrowings only. Management's stated intent is to hold this below 5x while expanding MTF, subject to the regulatory leverage cap
B9: Cost-to-income (%) | C9: =IF(N(Inputs!C9)=0,"",(Inputs!C9-Inputs!C10)/(Inputs!C8-Inputs!C10)) -> 0.39657015 | D9: =IF(N(Inputs!D9)=0,"",(Inputs!D9-Inputs!D10)/(Inputs!D8-Inputs!D10)) -> 0.46044706 | E9: =IF(N(Inputs!E9)=0,"",(Inputs!E9-Inputs!E10)/(Inputs!E8-Inputs!E10)) | F9: (Total expenses less finance costs) / (total income less finance costs) — A CareEdge BROKING metric - v1 wrongly excluded it as 'a bank metric' (failure mode 33). Computes 39.66%/46.04% against published 39.42%/45.54%: within ~0.5pp, the residual being a small expense line CareEdge's template excludes. Reported as computed, NOT forced
B10: RONW on AVERAGE TNW (%) | C10: =IF(0<>1,"",Inputs!D11/AVERAGE(Inputs!C20,Inputs!D20)) | D10: =IF(1<>1,"",Inputs!D11/AVERAGE(Inputs!C20,Inputs!D20)) -> 0.27540352 | E10: =IF(2<>1,"",Inputs!D11/AVERAGE(Inputs!C20,Inputs!D20)) | F10: PAT / average of opening and closing tangible net worth — AVERAGE TNW, not closing equity. Reproduces published 27.54% for FY2026. CareEdge also publishes 51.63% (FY2024) and 43.28% (FY2025) - the compression is the story
B11: ROTA on average assets (%) | C11: =IF(0<>1,"",Inputs!D11/AVERAGE(Inputs!C26,Inputs!D26)) | D11: =IF(1<>1,"",Inputs!D11/AVERAGE(Inputs!C26,Inputs!D26)) -> 0.051927325 | E11: =IF(2<>1,"",Inputs!D11/AVERAGE(Inputs!C26,Inputs!D26)) | F11: PAT / average total assets — 5.19% computed against published 5.22%. Quarterly ROTA is annualised (Q1FY27: 6.01%)
B12: PAT margin (%) | C12: =Inputs!C11/Inputs!C8 -> 0.34457833 | D12: =Inputs!D11/Inputs!D8 -> 0.29898879 | E12: =Inputs!E11/Inputs!E8 -> 0.31268486 | F12: Profit after tax / total income — Reproduces published 29.90% (FY2026) and 31.27% (Q1FY27) exactly
B13: MTF book growth (%) [SECTOR] | C13: =IF(0=0,"",Inputs!C27/INDEX(Inputs!$C$27:$E$27,0)-1) | D13: =IF(1=0,"",Inputs!D27/INDEX(Inputs!$C$27:$E$27,1)-1) -> 0.29405447 | E13: =IF(2=0,"",Inputs!E27/INDEX(Inputs!$C$27:$E$27,2)-1) -> 0.41335771 | F13: Year-on-year / sequential growth in the margin trading facility book — +29.4% in FY2026 then +41.3% in ONE quarter to Rs 10,081 cr. THE driver of borrowing growth, and the asset whose quality CareEdge names as the key monitorable
B14: MTF book / tangible net worth (x) | C14: =Inputs!C27/Inputs!C20 -> 1.692315 | D14: =Inputs!D27/Inputs!D20 -> 2.0402346 | E14: =Inputs!E27/Inputs!E20 -> 2.7641897 | F14: MTF book / tangible net worth — 1.69x to 2.04x to 2.76x. The capitalisation buffer against a book secured on volatile listed collateral - the ratio the key monitorable is really about
B15: Fees and commission income share (%) | C15: =IF(N(Inputs!C13)=0,"",Inputs!C13/Inputs!C8) -> 0.53423424 | D15: =IF(N(Inputs!D13)=0,"",Inputs!D13/Inputs!D8) -> 0.48738164 | E15: =IF(N(Inputs!E13)=0,"",Inputs!E13/Inputs!E8) | F15: Fees and commission income / total income — 48.7% in FY2026, matching CareEdge's stated 48%. Brokerage alone is 32.5% (their 33%); MTF interest contributes a further 31%
B16: Interest income share (%) | C16: =IF(N(Inputs!C12)=0,"",Inputs!C12/Inputs!C8) -> 0.43442598 | D16: =IF(N(Inputs!D12)=0,"",Inputs!D12/Inputs!D8) -> 0.48162629 | E16: =IF(N(Inputs!E12)=0,"",Inputs!E12/Inputs!E8) | F16: Interest income / total income — Rose to 48.2% of income as MTF scaled - Rs 1,498 cr from Rs 1,418 cr. The diversification away from pure brokerage that CareEdge credits, and the source of the new risk
B17: Dividend payout (%) | C17: =IF(N(Inputs!C15)=0,"",Inputs!C15/Inputs!C11) -> 0.79848889 | D17: =IF(N(Inputs!D15)=0,"",Inputs!D15/Inputs!D11) -> 0.79589203 | E17: =IF(N(Inputs!E15)=0,"",Inputs!E15/Inputs!E11) | F17: Dividend / profit after tax — ~80% in both years. CareEdge notes TNW grew only gradually 'despite healthy earnings, considering sizeable dividend payouts'
B18: UNENCUMBERED cash / fund-based debt (x) | C18: =IF(N(Inputs!C28)=0,"",Inputs!C28/Inputs!C24) | D18: =IF(N(Inputs!D28)=0,"",Inputs!D28/Inputs!D24) | E18: =IF(N(Inputs!E28)=0,"",Inputs!E28/Inputs!E24) -> 0.023077764 | F18: Unencumbered cash / total fund-based borrowings — 0.02x as on 30-Jun-2026. v1 claimed 0.74x by counting Rs 7,838.73 cr of CLIENT funds and exchange margin as company cash - a 23x overstatement (failure mode 34). Cover comes from the self-liquidating MTF book, unutilised lines of Rs 2,698 cr and parent flexibility
B19: Branches (no.) [SECTOR] | C19: =Inputs!C31 -> 134 | D19: =Inputs!D31 -> 128 | E19: =Inputs!E31 -> 127 | F19: Branch count at each date — 184 (31-Mar-2024) -> 134 -> 128 -> 127 (30-Jun-2026). Deliberate consolidation toward digital, confirmed by CareEdge; ~95% of Q1FY27 brokerage came from retail clients

Sheet TieOut
B2: HDFC Securities Limited - tie-out to company-disclosed figures
B3: Binding gate (CLAUDE.md Step 6): headline computed figures must reconcile to the company's OWN disclosed numbers before the workpaper is issued. PASS/FAIL is itself a formula - it re-evaluates if any input changes.
B5: Check | C5: Computed | D5: Company-disclosed | E5: Result | F5: Note
B6: TNW build-up reproduces published FY2026 | C6: =Inputs!D16-Inputs!D17-Inputs!D18-Inputs!D19 -> 3496.49 | D6: 3496 | E6: =IF(ABS(C6-D6)<=MAX(1,ABS(D6)*0.005),"PASS","CHECK") -> PASS | F6: 3,595.92 − 15.57 − 78.23 − 5.63 = 3,496.49 against CareEdge's published Rs 3,496 crore. The definition is confirmed by reproduction, not asserted
B7: TNW build-up reproduces published FY2025 | C7: =Inputs!C16-Inputs!C17-Inputs!C18-Inputs!C19 -> 3256.51 | D7: 3257 | E7: =IF(ABS(C7-D7)<=MAX(1,ABS(D7)*0.005),"PASS","CHECK") -> PASS | F7: 3,348.59 − 0.52 − 84.24 − 7.32 = 3,256.51 against published Rs 3,257 crore
B8: Overall gearing reproduces published FY2026 4.64x | C8: =(Inputs!D24+Inputs!D25)/Inputs!D20 -> 4.6378375 | D8: 4.64 | E8: =IF(ABS(C8-D8)<=MAX(1,ABS(D8)*0.005),"PASS","CHECK") -> PASS | F8: (15,113.88 + 1,100.00) / 3,496 = 4.64x. Excluding the bank guarantee gives 4.32x and using total equity gives 4.20x - which is what v1 published
B9: Overall gearing reproduces published FY2025 2.65x | C9: =(Inputs!C24+Inputs!C25)/Inputs!C20 -> 2.6539054 | D9: 2.65 | E9: =IF(ABS(C9-D9)<=MAX(1,ABS(D9)*0.005),"PASS","CHECK") -> PASS | F9: (7,943.77 + 700.00) / 3,257 = 2.65x - the same definition reproduces both years
B10: RONW on average TNW reproduces published 27.54% | C10: =Inputs!D11/AVERAGE(Inputs!C20,Inputs!D20)*100 -> 27.540352 | D10: 27.54 | E10: =IF(ABS(C10-D10)<=MAX(1,ABS(D10)*0.005),"PASS","CHECK") -> PASS | F10: 930 / ((3,257 + 3,496)/2) = 27.54%. On CLOSING equity it is 25.86%, which v1 published
B11: LINE INTEGRITY - CP tranches + proposed = rated limit | C11: =13860+6140 -> 20000 | D11: 20000 | E11: =IF(ABS(C11-D11)<=MAX(1,ABS(D11)*0.005),"PASS","CHECK") -> PASS | F11: Annexure-1 lists CP tranches summing to Rs 13,860.00 cr plus a Proposed line of Rs 6,140.00 cr = Rs 20,000.00 cr, matching the header table exactly. Condition (4) of the five-condition amendment is satisfied
B12: LINE INTEGRITY - LT/ST sanctioned + proposed = rated limit | C12: =2250+750 -> 3000 | D12: 3000 | E12: =IF(ABS(C12-D12)<=MAX(1,ABS(D12)*0.005),"PASS","CHECK") -> PASS | F12: Rs 2,250.00 cr (maturity 06-May-26) + Rs 750.00 cr Proposed = Rs 3,000.00 cr, matching the header table exactly
B13: Q1FY27 fund-based debt itemises to the published total | C13: =Inputs!E21+Inputs!E22+Inputs!E23 -> 18286 | D13: 18286 | E13: =IF(ABS(C13-D13)<=MAX(1,ABS(D13)*0.005),"PASS","CHECK") -> PASS | F13: CP 15,765 + TREPS 2,183 + loan against deposits 338 = Rs 18,286 crore
B14: RATED LIMIT vs DRAWN - the distinction v1 collapsed | C14: =Inputs!D6-Inputs!D21 -> 7068.67 | D14: 7068.67 | E14: =IF(ABS(C14-D14)<=MAX(1,ABS(D14)*0.005),"PASS","CHECK") -> PASS | F14: Rs 20,000.00 cr rated against Rs 12,931.33 cr drawn at 31-Mar-2026 - roughly Rs 7,069 cr of headroom. v1 put the DRAWN figure in the rating table, so this headroom, and the enhancement from Rs 18,000 cr, were both invisible (failure mode 31)
B16: Tolerance: 0.5% of the disclosed figure, floor Rs 1 - tighter than rounding, loose enough for basis differences.

Sheet RatingScore
B2: HDFC Securities Limited - rating scorecard and view
B3: Factor scores 1 (strongest) to 6 (weakest), weighted to a composite. The anchor is a SCREENING cross-check with a +/-2 notch band, NOT the rating - the analyst view and any divergence are stated below and the divergence must be explained, never buried.
B5: Rating factor | C5: Score (1-6) | D5: Weight | E5: Weighted | F5: Justification
B6: Parentage and linkage with HDFC Bank | C6: 1 | D6: 0.4 | E6: =C6*D6 -> 0.4 | F6: HDFC Bank Limited (CARE AAA; Stable / CARE A1+) holds 93.99% as on 30-Jun-2026. Board representation via HBL's nominee director; the MD & CEO and several key personnel came from HBL. HBL's network drives lead generation while HSL's clients strengthen the bank's retail liability franchise. Shared brand, strong financial flexibility, and expectation of continued need-based support. This dominates.
B7: Capitalisation and gearing | C7: 2 | D7: 0.2 | E7: =C7*D7 -> 0.4 | F7: TNW Rs 3,496 cr at 31-Mar-2026 and Rs 3,647 cr at 30-Jun-2026, but overall gearing rose 2.65x to 4.64x and further to 5.28x - driven by MTF expansion, margin requirements and investments. ~86% of fund-based borrowing is CP. Management intends to hold FUND-BASED gearing below 5x. Sizeable ~80% dividend payouts limit accretion.
B8: Earnings profile | C8: 2 | D8: 0.15 | E8: =C8*D8 -> 0.3 | F8: FY2026 total income Rs 3,110 cr and PAT Rs 930 cr - PAT margin 29.90%, ROTA 5.22%, RONW 27.54%. Healthy in absolute terms but moderating: RONW fell 51.63% (FY24) to 43.28% (FY25) to 27.54%. Q1FY27 recovered - income Rs 950 cr, PAT Rs 297 cr, margin 31.27%, RONW 34.0% annualised. Revenue is diversified: fees/commission 48%, MTF interest 31%, brokerage alone 33%.
B9: Franchise and market position | C9: 2 | D9: 0.15 | E9: =C9*D9 -> 0.3 | F9: SIXTH-largest retail stockbroker by active clients (~10.05 lakh as on 31-Jul-2026). ~95% of Q1FY27 brokerage from retail. Branch network deliberately consolidated from 184 (31-Mar-2024) to 127 (30-Jun-2026) in favour of digital, with the 'HDFC Sky' app targeting new-age investors. Competing against zero-brokerage discount platforms.
B10: MTF concentration and regulatory risk | C10: 4 | D10: 0.1 | E10: =C10*D10 -> 0.4 | F10: The MTF book grew to Rs 10,081 cr at 30-Jun-2026 from Rs 7,133 cr and Rs 5,512 cr - 2.76x tangible net worth. Secured on listed collateral, but adverse valuation moves transmit credit and market risk directly, and CareEdge names MTF asset quality and the capitalisation buffer as THE key monitorable. Compounding this, RBI's amended directions of 13-Feb-2026 (effective 01-Jul-2026) require fully collateralised lending to capital-market intermediaries, higher-quality collateral, minimum haircuts and MTF backed by high-quality liquid collateral - expected to raise funding costs. SEBI's Oct-2024 F&O measures already compressed derivative volumes.
B11: Weight check (must be 100%) | D11: =SUM(D6:D10) -> 1 | E11: =SUM(E6:E10) -> 1.8 | F11: =IF(ABS(D11-1)<0.001,"weights sum to 100%","ERROR: weights must sum to 100%") -> weights sum to 100%
B13: Weighted composite score | C13: =E11 -> 1.8
B14: Indicative anchor grade (screening only, +/-2 band) | C14: A1+ / AAA band (composite 1.85)
B15: ANALYST RATING VIEW | C15: CARE A1+ (CP, Rs 20,000.00 cr) and CARE AAA; Stable / CARE A1+ (LT/ST bank facilities, Rs 3,000.00 cr)
B16: Divergence from anchor - explanation | C16: NO DIVERGENCE - but only after correction, and the correction was not marginal. This workbook's v1 assigned A1+ on commercial paper alone and stated that no long-term rating applied and no outlook was assigned, having reasoned from the maturity tables (all DRAWN borrowings inside 12 months) to the rated universe. CareEdge's press release of the SAME DATE rates Rs 20,000.00 cr of CP at CARE A1+ AND Rs 3,000.00 cr of long-term/short-term bank facilities at CARE AAA; Stable, Reaffirmed, with history to 22-Dec-2023. v1 also used total equity rather than tangible net worth, omitted the Rs 1,100 cr bank guarantee from gearing, computed return on closing rather than average net worth, excluded cost-to-income on a misapplied sector rule, and overstated liquidity 23x by treating client funds as company cash. Every convention in this version is now solved back from and reproduces CareEdge's published figures.
