Workbook

Sheet Assumptions
B2: Repco Home Finance Limited - forecast drivers (Rs crore; standalone)
B3: Yellow cells are the DRIVERS. Every one is derived from the company's own documents and the arithmetic of the derivation is written beside it, so a reviewer can disagree with a number rather than with an assertion. FY2027E rolls forward from the 30-Jun-2026 balance sheet because no 31-Mar-2026 balance sheet exists in the document set; that carries about one quarter of growth twice - roughly Rs 250 crore, 1.6% of the book - and is stated here rather than smoothed away.
B5: Line | C5: FY2027E | D5: FY2028E | E5: FY2029E | F5: FY2030E | G5: FY2031E | H5: Derivation / source
B6: GROWTH
B7: Disbursements (Rs cr) | C7: 3600 | D7: 3924 | E7: 4277 | F7: 4662 | G7: 5081 | H7: Actuals 2,919 (FY2023) / 3,135 (FY2024) / 3,284 (FY2025) per the FY2025 AR six-year table: growth of 7.4% then 4.8%. Base case takes 9.6% for FY2027E and 9.0% thereafter - faster than the FY2025 actual because the network grew from 159 to 189 branches and from 192 to 233 touchpoints over FY2023-FY2025 and that added capacity has not yet been worked through.
B8: Run-off rate (% of opening AUM) | C8: 17 | D8: 17 | E8: 17 | F8: 17 | G8: 17 | H8: Derived from the AUM roll-forward: FY2023 opening 11,759 + disbursements 2,919 less closing 12,449 implies run-off of 2,229 = 19.0% of opening; FY2024 implies 2,071 = 15.3%; FY2025 implies 2,305 = 17.1%. Held at the three-year mean, rounded to 17.0%.
B9: SPREAD
B10: Yield on average AUM (%) | C10: 11.8 | D10: 11.75 | E10: 11.7 | F10: 11.7 | G10: 11.7 | H10: Interest income over average reported AUM: FY2023 1,257.01/12,104 = 10.38%; FY2024 1,495.98/12,981 = 11.52%; FY2025 1,648.19/14,002.5 = 11.77%. Held at 11.80% then eased 10bps as the salaried mix rises - the FY2025 AR states an intention to keep 'a slight tilt towards salaried professionals'.
B11: Cost of funds on average debt (%) | C11: 8.55 | D11: 8.5 | E11: 8.5 | F11: 8.5 | G11: 8.5 | H11: Finance costs over average total debt: FY2023 701.07/9,808.04 = 7.15%; FY2024 845.57/10,312.56 = 8.20%; FY2025 965.86/10,920.07 = 8.85%. Eased modestly on the RBI's projected disinflation (FY2025 AR MD&A: CPI 4.0% for 2025-26) and on the first NCD issuance broadening the base, but NOT below the FY2024 level - a lender funded almost entirely by banks has little pricing power over its liabilities.
B12: COSTS AND DISTRIBUTION
B13: Operating expenses / average total assets (%) | C13: 1.52 | D13: 1.53 | E13: 1.54 | F13: 1.55 | G13: 1.55 | H13: Actuals 1.19% (FY2023), 1.30% (FY2024), 1.47% (FY2025), 1.51% annualised in Q1FY2027 - a steady rise as branches were added. Continued to drift up: the FY2025 AR records 15 new branches and 9 new satellite centres in a single year, and employee cost rose 17.3% in FY2025 and 23.8% in FY2026 against book growth of 7.2%.
B14: Credit cost (% of average AUM) | C14: 0.3 | D14: 0.33 | E14: 0.35 | F14: 0.38 | G14: 0.4 | H14: The impairment line was a CHARGE of 233.06 (FY2022) and 51.55 (FY2023), then a WRITE-BACK of 0.51 (FY2024), 37.57 (FY2025) and 31.07 (FY2026), and turned back to a charge of 9.69 in Q1FY2027 - 0.25% of average managed assets annualised. A write-back is a one-way release from an existing stock of provisions and cannot be forecast, so the base case normalises to a small charge and lets it drift up as the book seasons and the non-housing share rises.
B15: Effective tax rate (%) | C15: 25.2 | D15: 25.2 | E15: 25.2 | F15: 25.2 | G15: 25.2 | H15: FY2025 148.05/587.49 = 25.20%. FY2026's 22.74% is distorted by the Rs 14.40 crore reversal of the deferred tax liability on the Section 36(1)(viii) special reserve (Note 7 to the Q1FY2027 results; an Emphasis of Matter in the auditor's limited review report) and is not repeatable.
B16: Dividend payout (% of PAT) | C16: 8 | D16: 8 | E16: 8 | F16: 8 | G16: 8 | H16: FY2025 Rs 4.00 per share, Rs 25.02 crore on PAT of Rs 439.44 crore = 5.7%; FY2024 Rs 3.00 per share, Rs 18.77 crore = 4.8% (AR Note 41). Raised modestly to 8%: a company carrying 37% CRAR against a 15% minimum has no capital reason to retain 95% of earnings, and the very low payout is itself part of why return on equity is drifting down.
B17: BALANCE SHEET STRUCTURE
B18: Cash and liquid investments (% of total assets) | C18: 1.5 | D18: 1.5 | E18: 1.5 | F18: 1.5 | G18: 1.5 | H18: 30-Jun-2026 actual: cash 136.83 + other bank balances 5.29 + investments 138.10 = 280.22 on total assets of 16,245.83 = 1.72%. FY2025: 347.52 on 14,602.24 = 2.38%. The series is falling; held at 1.50%, thin but consistent with the company's own practice and with an LCR of 202.13%.
B19: Non-debt liabilities (% of total assets) | C19: 0.9 | D19: 0.9 | E19: 0.9 | F19: 0.9 | G19: 0.9 | H19: 30-Jun-2026 actual: total liabilities 12,227.18 less total debt 12,087.01 = 140.17 on 16,245.83 = 0.86%. Comprises trade payables, lease liabilities, provisions and deferred tax.
B20: Non-earning assets (Rs cr) | C20: 270 | D20: 284 | E20: 298 | F20: 313 | G20: 329 | H20: 30-Jun-2026: PP&E 25.44 + right-of-use 47.30 + intangibles 17.69 + intangibles under development 5.21 + others 161.74 = 257.38. Grown 5% a year with the branch network.
B21: Risk weight density (RWA / AUM, %) | C21: 62.4 | D21: 62.4 | E21: 62.4 | F21: 62.4 | G21: 62.4 | H21: FY2025: risk-weighted assets 9,048.38 (AR Note 32.1) on reported AUM of 14,492 = 62.44%. Individual housing loans below Rs 30 lakh at LTV under 80% attract a 35% risk weight and loans against property 75%, so density moves with the housing / non-housing mix. Held flat, which is mildly conservative given the mix shift towards non-housing.

Sheet Book_Build
B2: Loan book roll-forward (Rs crore)
B3: Opening AUM plus disbursements less run-off equals closing AUM. FY2027E opens on the 30-Jun-2026 loan carrying value of 15,708.23 from the Reg 54(3) security-cover certificate - the newest balance sheet in the document set (139.05 exclusive charge + 13,299.24 pari passu + 2,269.94 unencumbered).
B5: Line | C5: FY2027E | D5: FY2028E | E5: FY2029E | F5: FY2030E | G5: FY2031E | H5: Derivation / source
B6: Opening AUM | C6: 15708.23 | D6: =C9 -> 16637.831 | E6: =D9 -> 17733.4 | F6: =E9 -> 18995.722 | G6: =F9 -> 20428.449 | H6: FY2027E opening is the 30-Jun-2026 actual; each later year opens on the prior year's close.
B7: Disbursements | C7: =Assumptions!C7 -> 3600 | D7: =Assumptions!D7 -> 3924 | E7: =Assumptions!E7 -> 4277 | F7: =Assumptions!F7 -> 4662 | G7: =Assumptions!G7 -> 5081 | H7: from Assumptions
B8: Less: run-off (repayments, prepayments, write-offs) | C8: =-C6*Assumptions!C8/100 -> -2670.3991 | D8: =-D6*Assumptions!D8/100 -> -2828.4313 | E8: =-E6*Assumptions!E8/100 -> -3014.6779 | F8: =-F6*Assumptions!F8/100 -> -3229.2727 | G8: =-G6*Assumptions!G8/100 -> -3472.8363 | H8: opening AUM times the run-off rate
B9: Closing AUM | C9: =SUM(C6:C8) -> 16637.831 | D9: =SUM(D6:D8) -> 17733.4 | E9: =SUM(E6:E8) -> 18995.722 | F9: =SUM(F6:F8) -> 20428.449 | G9: =SUM(G6:G8) -> 22036.613 | H9: opening + disbursements - run-off
B10: Average AUM | C10: =(C6+C9)/2 -> 16173.03 | D10: =(D6+D9)/2 -> 17185.615 | E10: =(E6+E9)/2 -> 18364.561 | F10: =(F6+F9)/2 -> 19712.085 | G10: =(G6+G9)/2 -> 21232.531
B11: AUM growth (%) | C11: =100*C9/C6-100 -> 5.9179226 | D11: =100*D9/D6-100 -> 6.5848052 | E11: =100*E9/E6-100 -> 7.1183309 | F11: =100*F9/F6-100 -> 7.5423684 | G11: =100*G9/G6-100 -> 7.872177 | H11: Actual growth was 5.9% (FY2023), 8.5% (FY2024), 7.2% (FY2025) on the reported loan book.

Sheet P_and_L
B2: Projected profit and loss (Rs crore)
B3: A lender's P&L: interest earned on the book, less interest paid on the funding, less operating costs, less credit cost. Every line is a live formula off Book_Build, Balance_Sheet and Assumptions.
B5: Line | C5: FY2027E | D5: FY2028E | E5: FY2029E | F5: FY2030E | G5: FY2031E | H5: Derivation / source
B6: Interest income | C6: =Book_Build!C10*Assumptions!C10/100 -> 1908.4176 | D6: =Book_Build!D10*Assumptions!D10/100 -> 2019.3098 | E6: =Book_Build!E10*Assumptions!E10/100 -> 2148.6536 | F6: =Book_Build!F10*Assumptions!F10/100 -> 2306.314 | G6: =Book_Build!G10*Assumptions!G10/100 -> 2484.2061 | H6: average AUM times yield
B7: Fee, commission and other operating income | C7: =Book_Build!C10*0.0026 -> 42.049879 | D7: =Book_Build!D10*0.0026 -> 44.6826 | E7: =Book_Build!E10*0.0026 -> 47.747858 | F7: =Book_Build!F10*0.0026 -> 51.251422 | G7: =Book_Build!G10*0.0026 -> 55.20458 | H7: FY2025 fees 21.49 + other operating revenue 15.48 = 36.97 on average AUM of 14,002.5 = 0.264%. Held at 0.26% of average AUM.
B8: Revenue from operations | C8: =SUM(C6:C7) -> 1950.4675 | D8: =SUM(D6:D7) -> 2063.9924 | E8: =SUM(E6:E7) -> 2196.4015 | F8: =SUM(F6:F7) -> 2357.5654 | G8: =SUM(G6:G7) -> 2539.4107
B9: Finance costs | C9: =-Balance_Sheet!C18*Assumptions!C11/100 -> -1033.4394 | D9: =-Balance_Sheet!D18*Assumptions!D11/100 -> -1068.3854 | E9: =-Balance_Sheet!E18*Assumptions!E11/100 -> -1124.2202 | F9: =-Balance_Sheet!F18*Assumptions!F11/100 -> -1191.4732 | G9: =-Balance_Sheet!G18*Assumptions!G11/100 -> -1269.8776 | H9: OPENING total debt (not average) times cost of funds - priced on the opening balance to avoid a circular reference through closing debt / retained earnings / PAT / finance costs; see the note on Balance_Sheet!S_AVGD
B10: Net interest income | C10: =C8+C9 -> 917.02812 | D10: =D8+D9 -> 995.60696 | E10: =E8+E9 -> 1072.1813 | F10: =F8+F9 -> 1166.0922 | G10: =G8+G9 -> 1269.5331 | H10: revenue from operations less finance costs - the company's OWN NII convention, which reproduces its published NII in every year it states one (FY2022 600.26 vs 600; FY2023 582.67 vs 583; FY2024 678.95 vs 679; FY2025 719.30 vs 719).
B11: Operating expenses | C11: =-Balance_Sheet!C11*Assumptions!C13/100 -> -253.92467 | D11: =-Balance_Sheet!D11*Assumptions!D13/100 -> -271.24671 | E11: =-Balance_Sheet!E11*Assumptions!E13/100 -> -291.67069 | F11: =-Balance_Sheet!F11*Assumptions!F13/100 -> -314.99754 | G11: =-Balance_Sheet!G11*Assumptions!G13/100 -> -339.16724 | H11: average total assets times the opex ratio
B12: Pre-provision operating profit | C12: =C10+C11 -> 663.10345 | D12: =D10+D11 -> 724.36025 | E12: =E10+E11 -> 780.51061 | F12: =F10+F11 -> 851.09465 | G12: =G10+G11 -> 930.36589 | H12: Actuals: 452.31 (FY2023), 524.21 (FY2024), 549.92 (FY2025), 554.97 (FY2026) - core earnings power once the provision swing is stripped out. Growth of 4.9% then 0.9% over the last two actual years.
B13: Credit cost | C13: =-Book_Build!C10*Assumptions!C14/100 -> -48.519091 | D13: =-Book_Build!D10*Assumptions!D14/100 -> -56.71253 | E13: =-Book_Build!E10*Assumptions!E14/100 -> -64.275962 | F13: =-Book_Build!F10*Assumptions!F14/100 -> -74.905924 | G13: =-Book_Build!G10*Assumptions!G14/100 -> -84.930123 | H13: average AUM times the credit-cost rate
B14: Profit before tax | C14: =C12+C13 -> 614.58436 | D14: =D12+D13 -> 667.64772 | E14: =E12+E13 -> 716.23464 | F14: =F12+F13 -> 776.18872 | G14: =G12+G13 -> 845.43577 | H14: Actuals: 400.76 (FY2023), 524.72 (FY2024), 587.49 (FY2025), 586.04 (FY2026) - FY2026 was FLAT on FY2025.
B15: Tax | C15: =-C14*Assumptions!C15/100 -> -154.87526 | D15: =-D14*Assumptions!D15/100 -> -168.24722 | E15: =-E14*Assumptions!E15/100 -> -180.49113 | F15: =-F14*Assumptions!F15/100 -> -195.59956 | G15: =-G14*Assumptions!G15/100 -> -213.04981
B16: Profit after tax | C16: =C14+C15 -> 459.7091 | D16: =D14+D15 -> 499.40049 | E16: =E14+E15 -> 535.74351 | F16: =F14+F15 -> 580.58917 | G16: =G14+G15 -> 632.38596 | H16: Actuals: 296.08 (FY2023), 394.70 (FY2024), 439.44 (FY2025), 452.77 (FY2026).
B17: Dividend | C17: =-C16*Assumptions!C16/100 -> -36.776728 | D17: =-D16*Assumptions!D16/100 -> -39.952039 | E17: =-E16*Assumptions!E16/100 -> -42.859481 | F17: =-F16*Assumptions!F16/100 -> -46.447133 | G17: =-G16*Assumptions!G16/100 -> -50.590877
B18: Retained earnings | C18: =C16+C17 -> 422.93237 | D18: =D16+D17 -> 459.44845 | E18: =E16+E17 -> 492.88403 | F18: =F16+F17 -> 534.14203 | G18: =G16+G17 -> 581.79508

Sheet Balance_Sheet
B2: Projected balance sheet (Rs crore) - debt is the FUNDING GAP, not a trend
B3: Failure mode 18: projected debt is DERIVED, never carried forward from the historical pattern. Assets follow the book the company chooses to write; equity follows retained earnings; debt is whatever is left over. The arithmetic is visible on the debt row itself.
B5: Line | C5: FY2027E | D5: FY2028E | E5: FY2029E | F5: FY2030E | G5: FY2031E | H5: Derivation / source
B6: Loans (closing AUM) | C6: =Book_Build!C9 -> 16637.831 | D6: =Book_Build!D9 -> 17733.4 | E6: =Book_Build!E9 -> 18995.722 | F6: =Book_Build!F9 -> 20428.449 | G6: =Book_Build!G9 -> 22036.613 | H6: from Book_Build
B7: Non-earning assets | C7: =Assumptions!C20 -> 270 | D7: =Assumptions!D20 -> 284 | E7: =Assumptions!E20 -> 298 | F7: =Assumptions!F20 -> 313 | G7: =Assumptions!G20 -> 329 | H7: from Assumptions
B8: Total assets | C8: =(C6+C7)/(1-Assumptions!C18/100) -> 17165.311 | D8: =(D6+D7)/(1-Assumptions!D18/100) -> 18291.776 | E8: =(E6+E7)/(1-Assumptions!E18/100) -> 19587.535 | F8: =(F6+F7)/(1-Assumptions!F18/100) -> 21057.309 | G8: =(G6+G7)/(1-Assumptions!G18/100) -> 22706.206 | H8: solved so that cash is the stated percentage OF the total: total assets = (loans + non-earning assets) / (1 - cash%)
B9: Cash and liquid investments | C9: =C8*Assumptions!C18/100 -> 257.47966 | D9: =D8*Assumptions!D18/100 -> 274.37664 | E9: =E8*Assumptions!E18/100 -> 293.81302 | F9: =F8*Assumptions!F18/100 -> 315.85963 | G9: =G8*Assumptions!G18/100 -> 340.59309 | H9: the balancing asset
B10: Opening total assets | C10: 16245.83 | D10: =C8 -> 17165.311 | E10: =D8 -> 18291.776 | F10: =E8 -> 19587.535 | G10: =F8 -> 21057.309 | H10: FY2027E opens on the 30-Jun-2026 total of 16,245.83 (Reg 54(3) certificate).
B11: Average total assets | C11: =(C8+C10)/2 -> 16705.57 | D11: =(D8+D10)/2 -> 17728.543 | E11: =(E8+E10)/2 -> 18939.656 | F11: =(F8+F10)/2 -> 20322.422 | G11: =(G8+G10)/2 -> 21881.757 | H11: denominator for the opex and return ratios
B12: FUNDING
B13: Opening net worth | C13: 4018.65 | D13: =C15 -> 4441.5824 | E13: =D15 -> 4901.0308 | F13: =E15 -> 5393.9149 | G13: =F15 -> 5928.0569 | H13: FY2027E opens on the Reg 52(4) net worth of 4,018.65 at 30-Jun-2026 - the company's own published figure, not a derived one.
B14: Add: retained earnings | C14: =P_and_L!C18 -> 422.93237 | D14: =P_and_L!D18 -> 459.44845 | E14: =P_and_L!E18 -> 492.88403 | F14: =P_and_L!F18 -> 534.14203 | G14: =P_and_L!G18 -> 581.79508 | H14: from P_and_L
B15: Closing net worth | C15: =C13+C14 -> 4441.5824 | D15: =D13+D14 -> 4901.0308 | E15: =E13+E14 -> 5393.9149 | F15: =F13+F14 -> 5928.0569 | G15: =G13+G14 -> 6509.852
B16: Non-debt liabilities | C16: =C8*Assumptions!C19/100 -> 154.4878 | D16: =D8*Assumptions!D19/100 -> 164.62599 | E16: =E8*Assumptions!E19/100 -> 176.28781 | F16: =F8*Assumptions!F19/100 -> 189.51578 | G16: =G8*Assumptions!G19/100 -> 204.35585 | H16: from Assumptions
B17: Total debt (FUNDING GAP) | C17: =C8-C15-C16 -> 12569.24 | D17: =D8-D15-D16 -> 13226.119 | E17: =E8-E15-E16 -> 14017.332 | F17: =F8-F15-F16 -> 14939.736 | G17: =G8-G15-G16 -> 15991.998 | H17: total assets less net worth less non-debt liabilities. This is the borrowing the company must have outstanding to fund the book it writes - derived from the funding requirement, not extrapolated from the historical debt trend.
B18: Opening total debt | C18: 12087.01 | D18: =C17 -> 12569.24 | E18: =D17 -> 13226.119 | F18: =E17 -> 14017.332 | G18: =F17 -> 14939.736 | H18: FY2027E opens on the 30-Jun-2026 total of 12,087.01 (bank 10,992.79 + other borrowings 895.03 + listed secured NCD 125.49 + other debt securities 73.70).
B19: Average total debt (memo only - not used upstream) | C19: =(C17+C18)/2 -> 12328.125 | D19: =(D17+D18)/2 -> 12897.68 | E19: =(E17+E18)/2 -> 13621.726 | F19: =(F17+F18)/2 -> 14478.534 | G19: =(G17+G18)/2 -> 15465.867 | H19: display only. Finance costs is priced on OPENING debt, not this average, to avoid a circular reference (closing debt needs closing net worth needs retained earnings needs PAT needs finance costs needs... closing debt).
B20: Incremental borrowing required in the year | C20: =C17-C18 -> 482.23039 | D20: =D17-D18 -> 656.87909 | E20: =E17-E18 -> 791.21258 | F20: =F17-F18 -> 922.40392 | G20: =G17-G18 -> 1052.262 | H20: the quantum that has to be raised each year from a funding base that was 100% bank and NHB at 31-Mar-2025 - the central refinancing question in this rating.

Sheet Credit_Ratios
B2: Credit ratios on ICRA HFC conventions, every projected year
B3: The same convention set as the historical workbook, so projected years sit on identical definitions. Total managed assets = total assets + impairment allowance, VERBATIM from ICRA's own footnote in the GIC Housing Finance rationale of 10-Oct-2025.
B5: Line | C5: FY2027E | D5: FY2028E | E5: FY2029E | F5: FY2030E | G5: FY2031E | H5: Derivation / source
B6: Impairment allowance (closing) | C6: =Book_Build!C9*0.0276 -> 459.20413 | D6: =Book_Build!D9*0.0276 -> 489.44183 | E6: =Book_Build!E9*0.0276 -> 524.28192 | F6: =Book_Build!F9*0.0276 -> 563.82519 | G6: =Book_Build!G9*0.0276 -> 608.21051 | H6: FY2025 actual 433.39 on gross exposure of 14,542.57 = 2.98%; FY2024 517.86 on 13,560.22 = 3.82%. Held at 2.76%, the level implied by 30-Jun-2026 provision coverage of 43.48% on gross NPA of 3.33% plus standard-asset provisioning.
B7: Total managed assets | C7: =Balance_Sheet!C8+C6 -> 17624.515 | D7: =Balance_Sheet!D8+D6 -> 18781.218 | E7: =Balance_Sheet!E8+E6 -> 20111.817 | F7: =Balance_Sheet!F8+F6 -> 21621.134 | G7: =Balance_Sheet!G8+G6 -> 23314.416 | H7: ICRA definition
B8: Opening total managed assets | C8: 16679.22 | D8: =C7 -> 17624.515 | E8: =D7 -> 18781.218 | F8: =E7 -> 20111.817 | G8: =F7 -> 21621.134 | H8: FY2027E opening approximates the 30-Jun-2026 allowance with the FY2025 actual of 433.39, the latest disclosed - the allowance is not disclosed after FY2025.
B9: Net interest margin (% of average total assets) | C9: =100*P_and_L!C10/Balance_Sheet!C11 -> 5.4893554 | D9: =100*P_and_L!D10/Balance_Sheet!D11 -> 5.6158418 | E9: =100*P_and_L!E10/Balance_Sheet!E11 -> 5.6610391 | F9: =100*P_and_L!F10/Balance_Sheet!F11 -> 5.7379588 | G9: =100*P_and_L!G10/Balance_Sheet!G11 -> 5.8017879 | H9: Actuals 4.75 / 5.18 / 5.08; 5.51 annualised in Q1FY2027
B10: Operating expenses / average total assets (%) | C10: =-100*P_and_L!C11/Balance_Sheet!C11 -> 1.52 | D10: =-100*P_and_L!D11/Balance_Sheet!D11 -> 1.53 | E10: =-100*P_and_L!E11/Balance_Sheet!E11 -> 1.54 | F10: =-100*P_and_L!F11/Balance_Sheet!F11 -> 1.55 | G10: =-100*P_and_L!G11/Balance_Sheet!G11 -> 1.55 | H10: Actuals 1.19 / 1.30 / 1.47
B11: Credit cost (% of average AUM) | C11: =-100*P_and_L!C13/Book_Build!C10 -> 0.3 | D11: =-100*P_and_L!D13/Book_Build!D10 -> 0.33 | E11: =-100*P_and_L!E13/Book_Build!E10 -> 0.35 | F11: =-100*P_and_L!F13/Book_Build!F10 -> 0.38 | G11: =-100*P_and_L!G13/Book_Build!G10 -> 0.4 | H11: Actuals 0.40 / -0.00 / -0.26 on average managed assets; the negative years were write-backs
B12: Return on average managed assets (%) | C12: =100*P_and_L!C16/((C7+C8)/2) -> 2.6802277 | D12: =100*P_and_L!D16/((D7+D8)/2) -> 2.7435267 | E12: =100*P_and_L!E16/((E7+E8)/2) -> 2.7549587 | F12: =100*P_and_L!F16/((F7+F8)/2) -> 2.7824017 | G12: =100*P_and_L!G16/((G7+G8)/2) -> 2.8146354 | H12: Actuals 2.32 / 2.90 / 3.00. CareEdge's stated downgrade trigger is a sustained return on average total assets below 2.00%.
B13: Return on average net worth (%) | C13: =100*P_and_L!C16/((Balance_Sheet!C15+Balance_Sheet!C13)/2) -> 10.867529 | D13: =100*P_and_L!D16/((Balance_Sheet!D15+Balance_Sheet!D13)/2) -> 10.69081 | E13: =100*P_and_L!E16/((Balance_Sheet!E15+Balance_Sheet!E13)/2) -> 10.407894 | F13: =100*P_and_L!F16/((Balance_Sheet!F15+Balance_Sheet!F13)/2) -> 10.255973 | G13: =100*P_and_L!G16/((Balance_Sheet!G15+Balance_Sheet!G13)/2) -> 10.168686 | H13: Actuals 12.46 / 14.59 / 14.16
B14: Gearing (times) | C14: =Balance_Sheet!C17/Balance_Sheet!C15 -> 2.8299014 | D14: =Balance_Sheet!D17/Balance_Sheet!D15 -> 2.6986403 | E14: =Balance_Sheet!E17/Balance_Sheet!E15 -> 2.5987307 | F14: =Balance_Sheet!F17/Balance_Sheet!F15 -> 2.5201742 | G14: =Balance_Sheet!G17/Balance_Sheet!G15 -> 2.456584 | H14: Actuals 3.94 / 3.70 / 3.36; 3.01 at 30-Jun-2026. CareEdge's downgrade trigger is gearing sustained above 5x; the regulatory ceiling for an HFC is 12x net owned funds.
B15: CRAR (%) - indicative | C15: =100*(Balance_Sheet!C15-Assumptions!C20)/(Book_Build!C9*Assumptions!C21/100) -> 40.180888 | D15: =100*(Balance_Sheet!D15-Assumptions!D20)/(Book_Build!D9*Assumptions!D21/100) -> 41.724024 | E15: =100*(Balance_Sheet!E15-Assumptions!E20)/(Book_Build!E9*Assumptions!E21/100) -> 42.991419 | F15: =100*(Balance_Sheet!F15-Assumptions!F20)/(Book_Build!F9*Assumptions!F21/100) -> 44.04881 | G15: =100*(Balance_Sheet!G15-Assumptions!G20)/(Book_Build!G9*Assumptions!G21/100) -> 44.948884 | H15: Net owned funds approximated as net worth less non-earning assets, over risk-weighted assets at the stated density. INDICATIVE ONLY - the regulatory computation deducts specific items this model cannot see. Reported CRAR was 35.79 / 33.97 / 37.09 for FY2023-FY2025 against a 15% minimum.
B16: Equity / total assets (%) | C16: =100*Balance_Sheet!C15/Balance_Sheet!C8 -> 25.875339 | D16: =100*Balance_Sheet!D15/Balance_Sheet!D8 -> 26.79363 | E16: =100*Balance_Sheet!E15/Balance_Sheet!E8 -> 27.537487 | F16: =100*Balance_Sheet!F15/Balance_Sheet!F8 -> 28.152016 | G16: =100*Balance_Sheet!G15/Balance_Sheet!G8 -> 28.669924 | H16: Actuals 20.09 / 21.11 / 22.69; 24.74 at 30-Jun-2026
B17: Pre-provision profit / credit cost (times) | C17: =-P_and_L!C12/P_and_L!C13 -> 13.666856 | D17: =-P_and_L!D12/P_and_L!D13 -> 12.77249 | E17: =-P_and_L!E12/P_and_L!E13 -> 12.143118 | F17: =-P_and_L!F12/P_and_L!F13 -> 11.362181 | G17: =-P_and_L!G12/P_and_L!G13 -> 10.954487 | H17: ICRA's NBFC methodology: 'pre-credit-cost profits in relation to credit costs provides insights into the buffer created by business profits on the incurred credit cost'. This row is that buffer, in multiples.

Sheet Debt_Breakup
B2: Debt structure - actuals at 30-Jun-2026 and the projected requirement
B3: Statutory decomposition tied to the Reg 54(3) security-cover certificate of 30-Jun-2026 and the funding-concentration disclosure of 31-Mar-2025, plus the rated-limits-versus-drawn-debt distinction (failure modes 13 and 31). Actual figures appear in the FY2027E column only because that is the column adjacent to the labels; they are dated in the note.
B5: Line | C5: FY2027E | D5: FY2028E | E5: FY2029E | F5: FY2030E | G5: FY2031E | H5: Derivation / source
B6: ACTUAL DRAWN DEBT AT 30-JUN-2026 (Reg 54(3) certificate)
B7: Bank borrowings (pari passu charge) | C7: 10992.79 | H7: security-cover certificate
B8: Other borrowings | C8: 895.03 | H8: security-cover certificate
B9: Listed secured non-convertible debentures | C9: 125.49 | H9: 8.40% Repco Home Finance Limited 2029, ISIN INE612J07160, Debenture Trust Deed dated 13-03-2026, face value Rs 100,000. The auditor certifies compliance with the financial covenants of the Trust Deed for the quarter ended 30-Jun-2026.
B10: Other debt securities | C10: 73.7 | H10: security-cover certificate
B11: TOTAL DRAWN DEBT | C11: 12087.01 | H11: reproduces the company's own Reg 52(4) disclosure: 12,087.01 / 16,245.83 = 0.744, published as 0.74. This is the check that PROVES the assembled debt figure.
B12: Lease liabilities (excluded from gearing) | C12: 51.03 | H12: separately disclosed only at this date; sits inside other financial liabilities in every earlier period, so gearing is computed excluding leases in ALL periods rather than on a basis that changes midway through the series.
B13: FUNDING CONCENTRATION AT 31-MAR-2025 (AR Note 34)
B14: Long-term loan facility | C14: 9762.33 | H14: 86.48% of total liabilities
B15: Refinance from National Housing Bank | C15: 875.54 | H15: 7.76% of total liabilities
B16: Working capital loans including cash credit | C16: 501.22 | H16: 4.44% of total liabilities
B17: Commercial paper | C17: 0 | H17: NIL at every quarter-end from 31-Mar-2024 to 31-Mar-2025
B18: External commercial borrowing | C18: 0 | H18: NIL
B19: Secured non-convertible debentures | C19: 0 | H19: NIL at 31-Mar-2025
B20: Subordinated Tier-II NCDs | C20: 0 | H20: NIL
B21: Public deposits | C21: 0 | H21: the company does not accept public deposits
B22: Top 10 borrowings | C22: 10397.24 | H22: 93.34% of total borrowings
B23: Twelve significant counterparties | C23: 10914.96 | H23: 96.69% of total liabilities
B24: PROJECTED INCREMENTAL BORROWING
B25: Incremental borrowing required | C25: =Balance_Sheet!C20 -> 482.23039 | D25: =Balance_Sheet!D20 -> 656.87909 | E25: =Balance_Sheet!E20 -> 791.21258 | F25: =Balance_Sheet!F20 -> 922.40392 | G25: =Balance_Sheet!G20 -> 1052.262 | H25: the annual quantum that has to be raised, refinanced or replaced
B26: as a multiple of the FY2026 NCD issuance | C26: =Balance_Sheet!C20/199.19 -> 2.4209568 | D26: =Balance_Sheet!D20/199.19 -> 3.2977513 | E26: =Balance_Sheet!E20/199.19 -> 3.9721501 | F26: =Balance_Sheet!F20/199.19 -> 4.6307742 | G26: =Balance_Sheet!G20/199.19 -> 5.2827048 | H26: debt securities stood at 199.19 at 30-Jun-2026, 1.6% of drawn debt; this row states how far that new channel would have to scale to carry the requirement
B27: RATED LIMITS versus DRAWN DEBT
B28: ICRA rated limits | H28: TO BE CONFIRMED BY ISSUER. ICRA rates long-term fund-based term loans, non-convertible debentures and commercial paper (FY2025 AR Note 32.17 and corporate governance report item 18), but no ICRA rated AMOUNT is disclosed in any company document, and no ICRA CORPORATE rationale for this issuer exists in the reference library - the only ICRA file is a SECURITISATION rationale on the PRATHAM 12 2025 trust. A rated limit is a sanctioned facility, never an outstanding balance, and an outstanding must not be substituted for one.
B29: Memo - CareEdge published limits, 30-Sep-2025 | H29: CARE-published, NOT issuer-confirmed, and NOT ICRA's rated universe: long-term bank facilities Rs 11,145.00 crore (CARE AA-; Stable) and commercial paper Rs 800.00 crore (CARE A1+), both reaffirmed. Carried as a peer-agency cross-reference for Step 14 only. Note that CareEdge's Rs 11,145.00 crore of long-term bank facilities sits against drawn bank borrowings of Rs 10,992.79 crore at 30-Jun-2026 - limits and drawings are different measures and the gap between them is the undrawn headroom.

Sheet Stress_Case
B2: Stress case - the three variables ICRA's NBFC methodology names
B3: Asset quality, spread and growth are flexed together; capital and gearing are read off the result. The stress is calibrated to the company's OWN history rather than to an abstract percentage: in FY2022 the impairment charge was 233.06 on an average book of about 11,525, i.e. 2.02%, with gross NPA at 7.0% and disbursements falling from 2,627 to 1,769 over two years.
B5: Line | C5: FY2027E | D5: FY2028E | E5: FY2029E | F5: FY2030E | G5: FY2031E | H5: Derivation / source
B6: Stress credit cost (% of average AUM) | C6: 1 | D6: 1 | E6: 1 | F6: 1 | G6: 1 | H6: half the FY2022 peak of 2.02%, but sustained for five years rather than one - a prolonged moderate stress is harder for a lender to absorb than a single sharp one, because provisions cannot be released to offset it
B7: Spread compression (bps off net interest income) | C7: 75 | D7: 75 | E7: 75 | F7: 75 | G7: 75 | H7: 75bps: the cost of funds rose 170bps between FY2023 and FY2025 (7.15% to 8.85%) while the yield rose 139bps, so the spread compressed 31bps in two years with no market stress at all. A lender funded almost entirely by banks cannot reprice its liabilities away from a rate shock.
B8: Disbursements held flat at the FY2025 actual (Rs cr) | C8: 3284 | D8: 3284 | E8: 3284 | F8: 3284 | G8: 3284 | H8: zero growth for five years, against the FY2021-FY2022 experience when disbursements fell from 2,627 to 1,841 to 1,769 - a 33% cumulative decline
B10: Opening AUM | C10: 15708.23 | D10: =C13 -> 16321.831 | E10: =D13 -> 16831.12 | F10: =E13 -> 17253.829 | G10: =F13 -> 17604.678
B11: Disbursements | C11: =C8 -> 3284 | D11: =D8 -> 3284 | E11: =E8 -> 3284 | F11: =F8 -> 3284 | G11: =G8 -> 3284 | H11: held flat
B12: Less: run-off | C12: =-C10*Assumptions!C8/100 -> -2670.3991 | D12: =-D10*Assumptions!D8/100 -> -2774.7113 | E12: =-E10*Assumptions!E8/100 -> -2861.2903 | F12: =-F10*Assumptions!F8/100 -> -2933.151 | G12: =-G10*Assumptions!G8/100 -> -2992.7953 | H12: same run-off rate as the base case
B13: Closing AUM | C13: =SUM(C10:C12) -> 16321.831 | D13: =SUM(D10:D12) -> 16831.12 | E13: =SUM(E10:E12) -> 17253.829 | F13: =SUM(F10:F12) -> 17604.678 | G13: =SUM(G10:G12) -> 17895.883
B14: Average AUM | C14: =(C10+C13)/2 -> 16015.03 | D14: =(D10+D13)/2 -> 16576.475 | E14: =(E10+E13)/2 -> 17042.474 | F14: =(F10+F13)/2 -> 17429.254 | G14: =(G10+G13)/2 -> 17750.281
B15: Net interest income | C15: =P_and_L!C10*C14/Book_Build!C10-C14*C7/10000 -> 787.95662 | D15: =P_and_L!D10*D14/Book_Build!D10-D14*D7/10000 -> 835.99435 | E15: =P_and_L!E10*E14/Book_Build!E10-E14*E7/10000 -> 867.17516 | F15: =P_and_L!F10*F14/Book_Build!F10-F14*F7/10000 -> 900.32913 | G15: =P_and_L!G10*G14/Book_Build!G10-G14*G7/10000 -> 928.19571 | H15: base-case NII scaled to the smaller stress book, then the spread compression applied to that book
B16: Operating expenses | C16: =P_and_L!C11 -> -253.92467 | D16: =P_and_L!D11 -> -271.24671 | E16: =P_and_L!E11 -> -291.67069 | F16: =P_and_L!F11 -> -314.99754 | G16: =P_and_L!G11 -> -339.16724 | H16: held at the base case - a lender cannot shrink its branch network in step with a demand shock, which is exactly what makes operating leverage cut both ways
B17: Pre-provision operating profit | C17: =C15+C16 -> 534.03195 | D17: =D15+D16 -> 564.74763 | E17: =E15+E16 -> 575.50446 | F17: =F15+F16 -> 585.33159 | G17: =G15+G16 -> 589.02847
B18: Credit cost | C18: =-C14*C6/100 -> -160.1503 | D18: =-D14*D6/100 -> -165.76475 | E18: =-E14*E6/100 -> -170.42474 | F18: =-F14*F6/100 -> -174.29254 | G18: =-G14*G6/100 -> -177.50281
B19: Profit before tax | C19: =C17+C18 -> 373.88165 | D19: =D17+D18 -> 398.98288 | E19: =E17+E18 -> 405.07972 | F19: =F17+F18 -> 411.03905 | G19: =G17+G18 -> 411.52567
B20: Profit after tax | C20: =IF(C19>0,C19*(1-Assumptions!C15/100),C19) -> 279.66347 | D20: =IF(D19>0,D19*(1-Assumptions!D15/100),D19) -> 298.43919 | E20: =IF(E19>0,E19*(1-Assumptions!E15/100),E19) -> 302.99963 | F20: =IF(F19>0,F19*(1-Assumptions!F15/100),F19) -> 307.45721 | G20: =IF(G19>0,G19*(1-Assumptions!G15/100),G19) -> 307.8212 | H20: no tax shield assumed on a loss
B21: Opening net worth | C21: 4018.65 | D21: =C23 -> 4275.9404 | E21: =D23 -> 4550.5045 | F21: =E23 -> 4829.2641 | G21: =F23 -> 5112.1247
B22: Retained earnings | C22: =C20*(1-Assumptions!C16/100) -> 257.29039 | D22: =D20*(1-Assumptions!D16/100) -> 274.56406 | E22: =E20*(1-Assumptions!E16/100) -> 278.75966 | F22: =F20*(1-Assumptions!F16/100) -> 282.86063 | G22: =G20*(1-Assumptions!G16/100) -> 283.1955
B23: Closing net worth | C23: =C21+C22 -> 4275.9404 | D23: =D21+D22 -> 4550.5045 | E23: =E21+E22 -> 4829.2641 | F23: =F21+F22 -> 5112.1247 | G23: =G21+G22 -> 5395.3202
B24: Total assets implied | C24: =(C13+Assumptions!C20)/(1-Assumptions!C18/100) -> 16844.498 | D24: =(D13+Assumptions!D20)/(1-Assumptions!D18/100) -> 17375.756 | E24: =(E13+Assumptions!E20)/(1-Assumptions!E18/100) -> 17819.116 | F24: =(F13+Assumptions!F20)/(1-Assumptions!F18/100) -> 18190.536 | G24: =(G13+Assumptions!G20)/(1-Assumptions!G18/100) -> 18502.419
B25: Total debt implied | C25: =C24-C23-C24*Assumptions!C19/100 -> 12416.957 | D25: =D24-D23-D24*Assumptions!D19/100 -> 12668.87 | E25: =E24-E23-E24*Assumptions!E19/100 -> 12829.48 | F25: =F24-F23-F24*Assumptions!F19/100 -> 12914.697 | G25: =G24-G23-G24*Assumptions!G19/100 -> 12940.577
B26: Gearing in stress (times) | C26: =C25/C23 -> 2.9039127 | D26: =D25/D23 -> 2.7840583 | E26: =E25/E23 -> 2.6566118 | F26: =F25/F23 -> 2.5262875 | G26: =G25/G23 -> 2.3984818 | H26: against CareEdge's downgrade trigger of 5x sustained and the regulatory ceiling of 12x net owned funds
B27: CRAR in stress (%) - indicative | C27: =100*(C23-Assumptions!C20)/(C13*Assumptions!C21/100) -> 39.332452 | D27: =100*(D23-Assumptions!D20)/(D13*Assumptions!D21/100) -> 40.623244 | E27: =100*(E23-Assumptions!E20)/(E13*Assumptions!E21/100) -> 42.087128 | F27: =100*(F23-Assumptions!F20)/(F13*Assumptions!F21/100) -> 43.686712 | G27: =100*(G23-Assumptions!G20)/(G13*Assumptions!G21/100) -> 45.368552 | H27: against the 15% regulatory minimum
B28: Return on average assets in stress (%) | C28: =100*C20/C24 -> 1.660266 | D28: =100*D20/D24 -> 1.7175609 | E28: =100*E20/E24 -> 1.700419 | F28: =100*F20/F24 -> 1.6902042 | G28: =100*G20/G24 -> 1.6636808 | H28: against CareEdge's downgrade trigger of a sustained 2.00%
