Workbook

Sheet Inputs
B2: Riba Textiles Limited - extracted line items (Consolidated, Rs crore)
B3: Yellow cells are EXTRACTED INPUTS traced to the source in the final column - nothing here is computed. Every downstream ratio references this sheet, so correcting a value here reflows the entire workbook.
B5: Line item | C5: FY2023 | D5: FY2024 | E5: FY2025 | F5: Source
B6: Revenue from operations | D6: 246.89 | E6: 295.86 | F6: AR FY2024-25 (998.md) P&L L~3095
B7: Other income | D7: 0.31 | E7: 0.27 | F7: AR FY2024-25 (998.md) P&L L~3096
B8: Total income | C8: 242.83 | D8: 247.21 | E8: 296.13 | F8: AR FY2023-24 (973.md) comparative L3164; AR FY2024-25 (998.md) L~3097
B9: Depreciation | C9: 4.47 | D9: 4.79 | E9: 5.47 | F9: AR FY2023-24 (973.md) comparative L3170; AR FY2024-25 (998.md) L~3109
B10: Finance cost | C10: 4.49 | D10: 4.65 | E10: 5.89 | F10: AR FY2023-24 (973.md) comparative L3171; AR FY2024-25 (998.md) L~3110
B11: Profit before tax | C11: 9.74 | D11: 10.6 | E11: 11.16 | F11: AR FY2023-24 (973.md) comparative L3177; AR FY2024-25 (998.md) L~3120
B12: Profit after tax | C12: 7.4 | D12: 7.92 | E12: 8.5 | F12: AR FY2023-24 (973.md) comparative L3182; AR FY2024-25 (998.md) L3121
B13: Borrowings - non-current | C13: 26.12 | D13: 25.38 | E13: 25.74 | F13: AR FY2023-24 (973.md) comparative L3120; AR FY2024-25 (998.md) L3060
B14: Borrowings - current | C14: 34.68 | D14: 42.3 | E14: 35.65 | F14: AR FY2023-24 (973.md) comparative L3124; AR FY2024-25 (998.md) L3064
B15: Cash + other bank balances | D15: 4.77 | E15: 2.54 | F15: AR FY2024-25 (998.md) L~3046-3047
B16: Tangible net worth | C16: 81.48 | D16: 89.4 | E16: 97.9 | F16: Equity share capital + reserves
B17: Total assets | C17: 164.21 | D17: 179.08 | E17: 181.45 | F17: AR FY2023-24 (973.md) comparative L3110; AR FY2024-25 (998.md) L3067
B18: Inventories | D18: 25.68 | E18: 25.16 | F18: AR FY2024-25 (998.md) L3042
B19: Trade receivables | D19: 41.59 | E19: 36.22 | F19: AR FY2024-25 (998.md) L3044
B20: Current assets | D20: 82.63 | E20: 75.89 | F20: AR FY2024-25 (998.md) L~3050
B21: Current liabilities | D21: 61.99 | E21: 54.91 | F21: AR FY2024-25 (998.md) L3068

Sheet RatioSuite
B2: Riba Textiles Limited - ratio suite (Consolidated, Rs crore; agency conventions applied)
B3: Every value is a LIVE FORMULA referencing the Inputs sheet - click any cell to see the arithmetic. 'Calculation' states the same formula in words; 'Convention' records the definitional choice (lease treatment, normalisation, netting) so the basis is auditable.
B5: Ratio | C5: FY2023 | D5: FY2024 | E5: FY2025 | F5: Calculation | G5: Convention / note
B6: PBILDT | C6: =Inputs!C11+Inputs!C10+Inputs!C9-Inputs!C7 -> 18.7 | D6: =Inputs!D11+Inputs!D10+Inputs!D9-Inputs!D7 -> 19.73 | E6: =Inputs!E11+Inputs!E10+Inputs!E9-Inputs!E7 -> 22.25 | F6: CareEdge earnings measure. No lease liabilities on the balance sheet in any year, so PBILDT equals PBDIT here - absence recorded, not assumed
B7: PBILDT margin (%) | C7: =(Inputs!C11+Inputs!C10+Inputs!C9-Inputs!C7)/Inputs!C8 -> 0.077008607 | D7: =(Inputs!D11+Inputs!D10+Inputs!D9-Inputs!D7)/Inputs!D8 -> 0.079810687 | E7: =(Inputs!E11+Inputs!E10+Inputs!E9-Inputs!E7)/Inputs!E8 -> 0.07513592 | F7: THE CORE WEAKNESS: thin and slipping
B8: PAT margin (%) | C8: =Inputs!C12/Inputs!C8 -> 0.030473994 | D8: =Inputs!D12/Inputs!D8 -> 0.032037539 | E8: =Inputs!E12/Inputs!E8 -> 0.02870361 | F8: Profit after tax over income
B9: Total debt | C9: =Inputs!C13+Inputs!C14 -> 60.8 | D9: =Inputs!D13+Inputs!D14 -> 67.68 | E9: =Inputs!E13+Inputs!E14 -> 61.39 | F9: Non-current plus current borrowings
B10: Net debt | C10: =Inputs!C13+Inputs!C14-Inputs!C15 -> 60.8 | D10: =Inputs!D13+Inputs!D14-Inputs!D15 -> 62.91 | E10: =Inputs!E13+Inputs!E14-Inputs!E15 -> 58.85 | F10: Debt less cash
B11: Overall gearing (x) [SECTOR-DEFINING] | C11: =(Inputs!C13+Inputs!C14)/Inputs!C16 -> 0.74619539 | D11: =(Inputs!D13+Inputs!D14)/Inputs!D16 -> 0.75704698 | E11: =(Inputs!E13+Inputs!E14)/Inputs!E16 -> 0.62706844 | F11: Total debt to tangible net worth - CareEdge reports this AND the net measure
B12: Net overall gearing (x) | C12: =(Inputs!C13+Inputs!C14-Inputs!C15)/Inputs!C16 -> 0.74619539 | D12: =(Inputs!D13+Inputs!D14-Inputs!D15)/Inputs!D16 -> 0.70369128 | E12: =(Inputs!E13+Inputs!E14-Inputs!E15)/Inputs!E16 -> 0.6011236 | F12: Net of cash
B13: TOL / TNW (x) | C13: =(Inputs!C17-Inputs!C16)/Inputs!C16 -> 1.0153412 | D13: =(Inputs!D17-Inputs!D16)/Inputs!D16 -> 1.003132 | E13: =(Inputs!E17-Inputs!E16)/Inputs!E16 -> 0.85342186 | F13: Total outside liabilities to tangible net worth
B14: Interest coverage (x) [SECTOR-DEFINING] | C14: =(Inputs!C11+Inputs!C10+Inputs!C9-Inputs!C7)/Inputs!C10 -> 4.1648107 | D14: =(Inputs!D11+Inputs!D10+Inputs!D9-Inputs!D7)/Inputs!D10 -> 4.2430108 | E14: =(Inputs!E11+Inputs!E10+Inputs!E9-Inputs!E7)/Inputs!E10 -> 3.7775891 | F14: PBILDT to finance cost. DECLINING - the key monitorable
B15: Total debt / PBILDT (x) | C15: =(Inputs!C13+Inputs!C14)/(Inputs!C11+Inputs!C10+Inputs!C9-Inputs!C7) -> 3.2513369 | D15: =(Inputs!D13+Inputs!D14)/(Inputs!D11+Inputs!D10+Inputs!D9-Inputs!D7) -> 3.4303092 | E15: =(Inputs!E13+Inputs!E14)/(Inputs!E11+Inputs!E10+Inputs!E9-Inputs!E7) -> 2.7591011 | F15: Years of earnings to clear debt
B16: Current ratio (x) | C16: =Inputs!C20/Inputs!C21 | D16: =Inputs!D20/Inputs!D21 -> 1.3329569 | E16: =Inputs!E20/Inputs!E21 -> 1.3820798 | F16: Short-term liquidity
B17: RoCE (%) | C17: =(Inputs!C11+Inputs!C10-Inputs!C7)/(Inputs!C13+Inputs!C14+Inputs!C16) -> 0.10001406 | D17: =(Inputs!D11+Inputs!D10-Inputs!D7)/(Inputs!D13+Inputs!D14+Inputs!D16) -> 0.095110772 | E17: =(Inputs!E11+Inputs!E10-Inputs!E7)/(Inputs!E13+Inputs!E14+Inputs!E16) -> 0.10534246 | F17: PBIT over capital employed
B18: Receivable days | C18: =365*Inputs!C19/Inputs!C8 -> 0 | D18: =365*Inputs!D19/Inputs!D8 -> 61.406699 | E18: =365*Inputs!E19/Inputs!E8 -> 44.643569 | F18: Collection cycle - improving sharply
B19: Inventory days | C19: =365*Inputs!C18/Inputs!C8 -> 0 | D19: =365*Inputs!D18/Inputs!D8 -> 37.915942 | E19: =365*Inputs!E18/Inputs!E8 -> 31.01138 | F19: Stock holding - improving

Sheet TieOut
B2: Riba Textiles Limited - tie-out to company-disclosed figures
B3: Binding gate (CLAUDE.md Step 6): headline computed figures must reconcile to the company's OWN disclosed numbers before the workpaper is issued. PASS/FAIL is itself a formula - it re-evaluates if any input changes.
B5: Check | C5: Computed | D5: Company-disclosed | E5: Result | F5: Note
B6: FY25 total income = revenue + other income | C6: =Inputs!E6+Inputs!E7 -> 296.13 | D6: 296.13 | E6: =IF(ABS(C6-D6)<=MAX(1,ABS(D6)*0.005),"PASS","CHECK") | F6: Reported total income Rs 296.13 crore - exact
B7: FY25 current ratio vs company-disclosed | C7: =Inputs!E20/Inputs!E21 -> 1.3820798 | D7: 1.38 | E7: =IF(ABS(C7-D7)<=MAX(1,ABS(D7)*0.005),"PASS","CHECK") | F7: The FY2025 AR's own key-ratio table reports 1.38 - exact match
B8: FY24 current ratio vs company-disclosed | C8: =Inputs!D20/Inputs!D21 -> 1.3329569 | D8: 1.33 | E8: =IF(ABS(C8-D8)<=MAX(1,ABS(D8)*0.005),"PASS","CHECK") | F8: The FY2024 AR reports 1.33 - exact match
B9: FY25 company 'debt-equity' = LT debt / TNW | C9: =Inputs!E13/Inputs!E16 -> 0.26292135 | D9: 0.26 | E9: =IF(ABS(C9-D9)<=MAX(1,ABS(D9)*0.005),"PASS","CHECK") | F9: The company's published 'Debt Equity Ratio' uses LONG-TERM debt only. Reproducing 0.26 confirms both the extraction and the convention - CareEdge gearing on TOTAL debt is 0.63x
B10: FY24 company 'debt-equity' = LT debt / TNW | C10: =Inputs!D13/Inputs!D16 -> 0.28389262 | D10: 0.28 | E10: =IF(ABS(C10-D10)<=MAX(1,ABS(D10)*0.005),"PASS","CHECK") | F10: Company reports 0.28 - exact
B12: Tolerance: 0.5% of the disclosed figure, floor Rs 1 - tighter than rounding, loose enough for basis differences.

Sheet RatingScore
B2: Riba Textiles Limited - rating scorecard and view
B3: Factor scores 1 (strongest) to 6 (weakest), weighted to a composite. The anchor is a SCREENING cross-check with a +/-2 notch band, NOT the rating - the analyst view and any divergence are stated below and the divergence must be explained, never buried.
B5: Rating factor | C5: Score (1-6) | D5: Weight | E5: Weighted | F5: Justification
B6: Industry risk - cotton textiles | C6: 4 | D6: 0.2 | E6: =C6*D6 -> 0.8 | F6: Terry towels and home textiles: fragmented, working-capital intensive, exposed to cotton price volatility and to export demand. CareEdge's cotton-textile methodology treats raw material pass-through as the central variable. Structurally a mid-band industry.
B7: Scale and market position | C7: 4 | D7: 0.15 | E7: =C7*D7 -> 0.6 | F7: Revenue of Rs 295.86 crore in FY2025 (+19.8%). Small in absolute terms; Panipat-based with a single promoter group holding. Limited pricing power against branded and export buyers.
B8: Financial risk - leverage | C8: 2 | D8: 0.25 | E8: =C8*D8 -> 0.5 | F8: Genuine deleveraging: overall gearing 0.76x to 0.63x, net gearing 0.70x to 0.60x, TOL/TNW 1.00x to 0.85x. Total debt fell to Rs 61.39 crore while net worth rose to Rs 97.90 crore through accruals. The clearest strength in the credit.
B9: Financial risk - profitability and coverage | C9: 4 | D9: 0.25 | E9: =C9*D9 -> 1 | F9: THE CONSTRAINT. PBILDT margin 7.52%, down from 7.99%; the company's own operating margin fell 16.63% to 12.56%. Interest coverage DECLINED to 3.78x from 4.24x even as debt fell, because finance cost rose 26.7% while PBILDT rose only 12.8%. Revenue grew 19.8% but earnings did not keep pace - growth is being bought with margin.
B10: Working capital and liquidity | C10: 3 | D10: 0.15 | E10: =C10*D10 -> 0.45 | F10: Marked improvement: receivable days 61 to 45, inventory days 38 to 31, current ratio 1.33x to 1.38x. Offset by thin absolute liquidity - cash and bank balances of only Rs 2.54 crore against Rs 35.65 crore of current borrowings.
B11: Weight check (must be 100%) | D11: =SUM(D6:D10) -> 1 | E11: =SUM(E6:E10) -> 3.35 | F11: =IF(ABS(D11-1)<0.001,"weights sum to 100%","ERROR: weights must sum to 100%")
B13: Weighted composite score | C13: =E11 -> 3.35
B14: Indicative anchor grade (screening only, +/-2 band) | C14: BBB band (composite 3.35)
B15: ANALYST RATING VIEW | C15: CARE BBB; Stable / CARE A3+
B16: Divergence from anchor - explanation | C16: No divergence at the issuer level. The company's own FY2024-25 annual report discloses CRISIL reaffirming BBB/Stable on Rs 94 crore of bank facilities on 04-Jul-2025, up from BBB/Negative on Rs 76.5 crore in the two prior years. This assessment reaches the same band and the same outlook independently, and the Negative-to-Stable move is corroborated by the deleveraging above. NO Riba rationale exists in any reference library - searched; the anchor is the issuer's own Step 7b disclosure.
