Workbook

Sheet Inputs
B2: State Bank of India - extracted line items (Consolidated, Rs crore)
B3: Yellow cells are EXTRACTED INPUTS traced to the source in the final column - nothing here is computed. Every downstream ratio references this sheet, so correcting a value here reflows the entire workbook.
B5: Line item | C5: FY2022 | D5: FY2023 | E5: FY2024 | F5: FY2025 | G5: FY2026 | H5: Source
B6: Operating profit | C6: 75292 | D6: 83713 | E6: 93797 | F6: 110579 | G6: 123015 | H6: FY26 AR 'Ten Years at a Glance' (L420-450) 'Operating Result'
B7: Net profit | C7: 31676 | D7: 50232 | E7: 61077 | F7: 70901 | G7: 80032 | H7: FY26 AR 'Ten Years at a Glance' (L420-450) 'Net Profit'
B8: RoAA (%) | C8: 0.67 | D8: 0.96 | E8: 1.04 | F8: 1.1 | G8: 1.12 | H8: FY26 AR 'Ten Years at a Glance' (L420-450) 'Return on Average Assets'
B9: RoE (%) | C9: 13.92 | D9: 19.43 | E9: 20.32 | F9: 19.87 | G9: 18.57 | H9: FY26 AR 'Ten Years at a Glance' (L420-450) 'Return on Equity'
B10: Cost-to-income (%) | C10: 53.31 | D10: 53.87 | E10: 55.66 | F10: 51.64 | G10: 50.11 | H10: FY26 AR 'Ten Years at a Glance' (L420-450) 'Expenses to Income'
B11: EPS (Rs) | C11: 35.49 | D11: 56.29 | E11: 68.44 | F11: 79.44 | G11: 87.59 | H11: FY26 AR 'Ten Years at a Glance' (L420-450) 'Earnings Per Share'
B12: DPS (Rs) | C12: 7.1 | D12: 11.3 | E12: 13.7 | F12: 15.9 | G12: 17.35 | H12: FY26 AR 'Ten Years at a Glance' (L420-450) 'Dividend Per Share'
B13: Tier I capital (%) | C13: 11.42 | D13: 12.06 | E13: 11.93 | F13: 12.11 | G13: 13.33 | H13: FY26 AR 'Ten Years at a Glance' (L420-450) 'Tier I Capital %'
B14: Tier II capital (%) | C14: 2.41 | D14: 2.62 | E14: 2.35 | F14: 2.14 | G14: 2.07 | H14: FY26 AR 'Ten Years at a Glance' (L420-450) 'Tier II Capital %'
B15: CRAR as reported (%) | C15: 13.83 | D15: 14.68 | E15: 14.28 | F15: 14.25 | G15: 15.4 | H15: FY26 AR 'Ten Years at a Glance' (L420-450) 'Basel-III Total Capital %'
B16: Gross NPA (Rs cr) | C16: 112023 | D16: 90928 | E16: 84276 | F16: 76880 | G16: 73452 | H16: FY26 AR asset-quality table (L4282-4286)
B17: Gross NPA (%) | C17: 3.97 | D17: 2.78 | E17: 2.24 | F17: 1.82 | G17: 1.49 | H17: FY26 AR asset-quality table (L4282-4286)
... B21: Domestic branches (no.) | C21: 22266 | D21: 22405 | E21: 22542 | F21: 22937 | G21: 23265 | H21: FY26 AR 'Ten Years at a Glance' (L420-450)
B22: CET-1 (%) [FY26 only] | G22: 12.29 | H22: FY26 AR Chairman's statement (L764-790) 'highest ever level'
B23: CASA ratio (%) [domestic] | G23: 39.46 | H23: FY26 AR Chairman's statement (L764-790) - DOMESTIC deposit basis
B24: Slippage ratio (%) [FY26] | G24: 0.54 | H24: FY26 AR Chairman's statement (L764-790) 'contained at'
B25: GoI shareholding (%) | F25: 56.92 | G25: 55.03 | H25: FY26 AR L11698

Sheet RatioSuite
B2: State Bank of India - ratio suite (Consolidated, Rs crore; agency conventions applied)
B3: Every value is a LIVE FORMULA referencing the Inputs sheet - click any cell to see the arithmetic. 'Calculation' states the same formula in words; 'Convention' records the definitional choice (lease treatment, normalisation, netting) so the basis is auditable.
B5: Ratio | C5: FY2022 | D5: FY2023 | E5: FY2024 | F5: FY2025 | G5: FY2026 | H5: Calculation | I5: Convention / note
B6: CRAR cross-check (Tier I + Tier II) | C6: =Inputs!C13+Inputs!C14 -> 13.83 | D6: =Inputs!D13+Inputs!D14 -> 14.68 | E6: =Inputs!E13+Inputs!E14 -> 14.28 | F6: =Inputs!F13+Inputs!F14 -> 14.25 | G6: =Inputs!G13+Inputs!G14 -> 15.4 | H6: Must equal reported CRAR - independent reconstruction of the capital stack
B7: Capital buffer over D-SIB minimum (pp) | C7: =Inputs!C15-12.3 -> 1.53 | D7: =Inputs!D15-12.3 -> 2.38 | E7: =Inputs!E15-12.3 -> 1.98 | F7: =Inputs!F15-12.3 -> 1.95 | G7: =Inputs!G15-12.3 -> 3.1 | H7: Reported CRAR less the 12.3% D-SIB requirement (11.5% + 0.80% surcharge)
B8: Implied PCR excl. AUCA (%) | C8: =(Inputs!C16-Inputs!C18)/Inputs!C16 -> 0.75035484 | D8: =(Inputs!D16-Inputs!D18)/Inputs!D16 -> 0.76391211 | E8: =(Inputs!E16-Inputs!E18)/Inputs!E16 -> 0.75021358 | F8: =(Inputs!F16-Inputs!F18)/Inputs!F16 -> 0.74418574 | G8: =(Inputs!G16-Inputs!G18)/Inputs!G16 -> 0.74364211 | H8: Provision coverage derived from the GNPA/NNPA stock - FY26 ties to reported 74.36%
B9: Net NPA / Gross NPA (%) | C9: =Inputs!C18/Inputs!C16 -> 0.24964516 | D9: =Inputs!D18/Inputs!D16 -> 0.23608789 | E9: =Inputs!E18/Inputs!E16 -> 0.24978642 | F9: =Inputs!F18/Inputs!F16 -> 0.25581426 | G9: =Inputs!G18/Inputs!G16 -> 0.25635789 | H9: Residual uncovered share of the bad-loan book
B10: Net profit growth (%) | C10: =Inputs!C7/OFFSET(Inputs!C7,0,-1)-1 | D10: =Inputs!D7/OFFSET(Inputs!D7,0,-1)-1 | E10: =Inputs!E7/OFFSET(Inputs!E7,0,-1)-1 | F10: =Inputs!F7/OFFSET(Inputs!F7,0,-1)-1 | G10: =Inputs!G7/OFFSET(Inputs!G7,0,-1)-1 | H10: YoY growth in net profit
B11: Operating profit growth (%) | C11: =Inputs!C6/OFFSET(Inputs!C6,0,-1)-1 | D11: =Inputs!D6/OFFSET(Inputs!D6,0,-1)-1 | E11: =Inputs!E6/OFFSET(Inputs!E6,0,-1)-1 | F11: =Inputs!F6/OFFSET(Inputs!F6,0,-1)-1 | G11: =Inputs!G6/OFFSET(Inputs!G6,0,-1)-1 | H11: YoY growth in pre-provision operating profit
B12: Dividend payout (%) | C12: =Inputs!C12/Inputs!C11 -> 0.20005635 | D12: =Inputs!D12/Inputs!D11 -> 0.20074614 | E12: =Inputs!E12/Inputs!E11 -> 0.20017534 | F12: =Inputs!F12/Inputs!F11 -> 0.20015106 | G12: =Inputs!G12/Inputs!G11 -> 0.19808197 | H12: DPS / EPS - tests the ~20% payout policy
B13: Slippages / opening Gross NPA (%) | C13: =Inputs!C20/OFFSET(Inputs!C16,0,-1) | D13: =Inputs!D20/OFFSET(Inputs!D16,0,-1) | E13: =Inputs!E20/OFFSET(Inputs!E16,0,-1) | F13: =Inputs!F20/OFFSET(Inputs!F16,0,-1) | G13: =Inputs!G20/OFFSET(Inputs!G16,0,-1) | H13: Fresh slippage relative to the opening stressed stock
B14: RoAA (%) [SECTOR-DEFINING] | C14: =Inputs!C8 -> 0.67 | D14: =Inputs!D8 -> 0.96 | E14: =Inputs!E8 -> 1.04 | F14: =Inputs!F8 -> 1.1 | G14: =Inputs!G8 -> 1.12 | H14: Return on average assets - the core bank profitability metric
B15: RoE (%) | C15: =Inputs!C9 -> 13.92 | D15: =Inputs!D9 -> 19.43 | E15: =Inputs!E9 -> 20.32 | F15: =Inputs!F9 -> 19.87 | G15: =Inputs!G9 -> 18.57 | H15: Return on equity
B16: Cost-to-income (%) | C16: =Inputs!C10 -> 53.31 | D16: =Inputs!D10 -> 53.87 | E16: =Inputs!E10 -> 55.66 | F16: =Inputs!F10 -> 51.64 | G16: =Inputs!G10 -> 50.11 | H16: Operating expenses / net total income
B17: Gross NPA (%) [SECTOR-DEFINING] | C17: =Inputs!C17 -> 3.97 | D17: =Inputs!D17 -> 2.78 | E17: =Inputs!E17 -> 2.24 | F17: =Inputs!F17 -> 1.82 | G17: =Inputs!G17 -> 1.49 | H17: Headline asset-quality metric
B18: Net NPA (%) [SECTOR-DEFINING] | C18: =Inputs!C19 -> 1.02 | D18: =Inputs!D19 -> 0.67 | E18: =Inputs!E19 -> 0.57 | F18: =Inputs!F19 -> 0.47 | G18: =Inputs!G19 -> 0.39 | H18: Asset quality net of provisions

Sheet TieOut
B2: State Bank of India - tie-out to company-disclosed figures
B3: Binding gate (CLAUDE.md Step 6): headline computed figures must reconcile to the company's OWN disclosed numbers before the workpaper is issued. PASS/FAIL is itself a formula - it re-evaluates if any input changes.
B5: Check | C5: Computed | D5: Company-disclosed | E5: Result | F5: Note
B6: FY26 CRAR = Tier I + Tier II | C6: =Inputs!G13+Inputs!G14 -> 15.4 | D6: 15.4 | E6: =IF(ABS(C6-D6)<=MAX(1,ABS(D6)*0.005),"PASS","CHECK") | F6: 13.33 + 2.07; reported CRAR is 15.40% - exact reconstruction of the capital stack
B7: FY26 net profit | C7: =Inputs!G7 -> 80032 | D7: 80032 | E7: =IF(ABS(C7-D7)<=MAX(1,ABS(D7)*0.005),"PASS","CHECK") | F7: Chairman's statement: net profit grew 12.88% to Rs 80,032 crore
B8: FY26 net profit growth | C8: =Inputs!G7/Inputs!F7-1 -> 0.12878521 | D8: 0.1288 | E8: =IF(ABS(C8-D8)<=MAX(1,ABS(D8)*0.005),"PASS","CHECK") | F8: Independently derived 12.88% matches the stated growth exactly
B9: FY26 operating profit growth | C9: =Inputs!G6/Inputs!F6-1 -> 0.11246258 | D9: 0.1125 | E9: =IF(ABS(C9-D9)<=MAX(1,ABS(D9)*0.005),"PASS","CHECK") | F9: Independently derived 11.25% matches the stated growth exactly
B10: FY26 implied PCR excl. AUCA | C10: =(Inputs!G16-Inputs!G18)/Inputs!G16 -> 0.74364211 | D10: 0.7436 | E10: =IF(ABS(C10-D10)<=MAX(1,ABS(D10)*0.005),"PASS","CHECK") | F10: Derived from the NPA stock; the Bank reports PCR of 74.36% without AUCA - exact match
B11: FY26 GNPA improvement (pp) | C11: =Inputs!G17-Inputs!F17 -> -0.33 | D11: -0.33 | E11: =IF(ABS(C11-D11)<=MAX(1,ABS(D11)*0.005),"PASS","CHECK") | F11: Stated as 'an improvement of 33 bps YoY' - reconciles
B12: FY26 dividend payout | C12: =Inputs!G12/Inputs!G11 -> 0.19808197 | D12: 0.1981 | E12: =IF(ABS(C12-D12)<=MAX(1,ABS(D12)*0.005),"PASS","CHECK") | F12: Rs 17.35 / Rs 87.59; the ten-year table reports payout of 20.01% - reconciles to rounding
B14: Tolerance: 0.5% of the disclosed figure, floor Rs 1 - tighter than rounding, loose enough for basis differences.

Sheet RatingScore
B2: State Bank of India - rating scorecard and view
B3: Factor scores 1 (strongest) to 6 (weakest), weighted to a composite. The anchor is a SCREENING cross-check with a +/-2 notch band, NOT the rating - the analyst view and any divergence are stated below and the divergence must be explained, never buried.
B5: Rating factor | C5: Score (1-6) | D5: Weight | E5: Weighted | F5: Justification
B6: Sovereign ownership and systemic importance | C6: 1 | D6: 0.4 | E6: =C6*D6 -> 0.4 | F6: Government of India holds 55.03% (FY2026; 56.92% FY2025) and SBI is designated a Domestic Systemically Important Bank by the RBI, carrying an additional 0.80% CET-1 surcharge from 01-Apr-2025. Support expectation is the dominant rating factor: SBI is the largest bank in the country with a balance sheet above Rs 76 lakh crore and total business above Rs 109 lakh crore.
B7: Market position and deposit franchise | C7: 1 | D7: 0.2 | E7: =C7*D7 -> 0.2 | F7: Largest Indian bank by every measure: deposits Rs 59.76 lakh crore (+11.03%), advances Rs 49.33 lakh crore (+16.87%), 23,265 domestic branches and 245 foreign offices. CASA ratio of 39.46% on domestic deposits is a structural funding advantage; retail banking supplies 88.27% of deposits.
B8: Asset quality | C8: 1 | D8: 0.15 | E8: =C8*D8 -> 0.15 | F8: Gross NPA 1.49% (-33 bps YoY) and net NPA 0.39% (-8 bps), the best in the ten-year series and down from 4.98% / 1.50% in FY2021. Provision coverage 74.36% excluding AUCA and 99.01% including it; slippage ratio contained at 0.54%.
B9: Capitalisation | C9: 2 | D9: 0.15 | E9: =C9*D9 -> 0.3 | F9: CRAR 15.40% against a 12.30% D-SIB requirement, a 310 bps buffer, and CET-1 at a record 12.29%. Capital has been built through accretion - Tier I rose to 13.33% from 12.11%. Scored 2 rather than 1 because the buffer, while comfortable, is thinner than the best-capitalised private peers against 16.87% advances growth.
B10: Earnings profile | C10: 2 | D10: 0.1 | E10: =C10*D10 -> 0.2 | F10: Net profit Rs 80,032 crore (+12.88%), operating profit Rs 1.23 lakh crore (+11.25%), RoAA 1.12% and cost-to-income improved to 50.11%. RoE of 18.57% is strong but has eased from 20.32% in FY2024, and NII growth of 4.08% materially lagged advances growth of 16.87% - margin compression is the one clear negative trend in the FY2026 numbers.
B11: Weight check (must be 100%) | D11: =SUM(D6:D10) -> 1 | E11: =SUM(E6:E10) -> 1.25 | F11: =IF(ABS(D11-1)<0.001,"weights sum to 100%","ERROR: weights must sum to 100%")
B13: Weighted composite score | C13: =E11 -> 1.25
B14: Indicative anchor grade (screening only, +/-2 band) | C14: AAA band (composite 1.25 - highest investment grade)
B15: ANALYST RATING VIEW | C15: Crisil AAA / Stable - Crisil A1+
B16: Divergence from anchor - explanation | C16: TO BE COMPLETED AT STEP 14 - this view was formed from the issuer's own disclosures before opening the CRISIL rationale of 05-Mar-2026 or the CareEdge rationale of 13-Oct-2025, both of which the pre-flight confirmed exist.
