Workbook

Sheet Inputs
B2: Aptus Value Housing Finance India Limited - extracted line items (Consolidated, Rs crore)
B3: Yellow cells are EXTRACTED INPUTS traced to the source in the final column - nothing here is computed. Every downstream ratio references this sheet, so correcting a value here reflows the entire workbook.
B5: Line item | C5: FY2025 | D5: FY2026 | E5: Q1FY2027 | F5: Source
B6: RATED: long-term bank facilities | C6: 2100 | D6: 2100 | E6: 2100 | F6: CareEdge press release 02-Jul-2026 (reference library) - CARE AA; Stable, Reaffirmed. Term loan 2,058.75 + WC 30.00 + BG 11.25
B7: RATED: non-convertible debentures | C7: 1145 | D7: 1145 | E7: 1145 | F7: CareEdge press release 02-Jul-2026 (reference library) - NCD II-VII, CARE AA; Stable. Six series, all 7.85%-8.75%
B8: Interest income | C8: 1669.58 | D8: 1943.8 | F8: FY2026 annual report - CONSOLIDATED statements P&L note 21A
B9: Fees and commission income | C9: 56.85 | D9: 58.65 | F9: FY2026 annual report - CONSOLIDATED statements P&L note 21B
B10: Net gain on derecognition (assignment) | C10: 16.31 | D10: 172.44 | F10: FY2026 annual report - CONSOLIDATED statements P&L note 21D
B11: Total income | C11: 1798.4 | D11: 2245.48 | E11: 610.65 | F11: FY2026 annual report - CONSOLIDATED statements / Q1FY27 results
B12: Finance costs | C12: 540.51 | D12: 648.45 | F12: FY2026 annual report - CONSOLIDATED statements P&L note 23
B13: Impairment on financial instruments | C13: 28.32 | D13: 61.51 | F13: FY2026 annual report - CONSOLIDATED statements P&L note 24
B14: Total expenses | C14: 823.56 | D14: 1034.33 | F14: FY2026 annual report - CONSOLIDATED statements P&L
B15: Profit after tax | C15: 751.25 | D15: 942.94 | E15: 260.94 | F15: FY2026 annual report - CONSOLIDATED statements / Q1FY27 results
B16: Total equity (consolidated) | C16: 4316.65 | D16: 5060.04 | F16: FY2026 annual report - CONSOLIDATED statements consolidated BS
B17: less: intangible assets | C17: 1.01 | D17: 1.22 | F17: FY2026 annual report - CONSOLIDATED statements consolidated BS 10B
B18: less: deferred tax assets | C18: 22.06 | D18: 0.15 | F18: FY2026 annual report - CONSOLIDATED statements consolidated BS 9
B19: Debt securities | C19: 1292.29 | D19: 1350.49 | F19: FY2026 annual report - CONSOLIDATED statements consolidated BS 13
B20: Borrowings (other than debt securities) | C20: 5554.55 | D20: 6523.18 | F20: FY2026 annual report - CONSOLIDATED statements BS 14
B21: TOTAL DEBT | C21: 6846.84 | D21: 7873.67 | F21: FY2026 annual report - CONSOLIDATED statements consolidated BS
B22: Lease liabilities | C22: 26.24 | D22: 30.1 | F22: FY2026 annual report - CONSOLIDATED statements consolidated BS 41
B23: Loans - on book | C23: 10630.27 | D23: 11929.52 | F23: FY2026 annual report - CONSOLIDATED statements consolidated BS 6
B24: Assets under management (AUM) | C24: 10865 | D24: 13107 | F24: FY2026 annual report - CONSOLIDATED statements highlights; matches the CareEdge published AUM exactly
B25: Total assets | C25: 11243.41 | D25: 13047.66 | F25: FY2026 annual report - CONSOLIDATED statements consolidated BS
B26: Cash and cash equivalents | C26: 302.59 | D26: 563.32 | F26: FY2026 annual report - CONSOLIDATED statements consolidated BS 4
B27: GNPA (%) - AR, consolidated | C27: 1.19 | D27: 1.52 | F27: FY2026 annual report - CONSOLIDATED statements - the AR labels this 'consolidated'; CareEdge publishes gross stage 3 of 1.18/1.45
B28: NNPA (%) - AR, consolidated | C28: 0.89 | D28: 1.15 | F28: FY2026 annual report - CONSOLIDATED statements
B29: CRAR (%) | D29: 71 | F29: FY2026 annual report - CONSOLIDATED statements - against the RBI minimum of 15% for HFCs
B30: Corporate guarantee for AFIPL | C30: 459.06 | D30: 269.63 | F30: FY2026 annual report - CONSOLIDATED statements - given by Aptus for its subsidiary's borrowings; off balance sheet

Sheet RatioSuite
B2: Aptus Value Housing Finance India Limited - ratio suite (Consolidated, Rs crore; agency conventions applied)
B3: Every value is a LIVE FORMULA referencing the Inputs sheet - click any cell to see the arithmetic. 'Calculation' states the same formula in words; 'Convention' records the definitional choice (lease treatment, normalisation, netting) so the basis is auditable.
B5: Ratio | C5: FY2025 | D5: FY2026 | E5: Q1FY2027 | F5: Calculation | G5: Convention / note
B6: TANGIBLE NET WORTH | C6: =IF(N(Inputs!C16)=0,"",(Inputs!C16-Inputs!C17-Inputs!C18)) -> 4293.58 | D6: =IF(N(Inputs!D16)=0,"",(Inputs!D16-Inputs!D17-Inputs!D18)) -> 5058.67 | E6: =IF(N(Inputs!E16)=0,"",(Inputs!E16-Inputs!E17-Inputs!E18)) | F6: Total equity less intangible assets less deferred tax assets -- CareEdge's FINANCIAL-SECTOR net-worth definition - NOT the corporate one, which retains intangibles critical to operations and does not deduct DTA. Reproduces the published Rs 5,059 cr for FY2026 exactly
B7: On-book gearing (x) [KEY] | C7: =IF(N(Inputs!C21)=0,"",Inputs!C21/(Inputs!C16-Inputs!C17-Inputs!C18)) -> 1.5946693 | D7: =IF(N(Inputs!D21)=0,"",Inputs!D21/(Inputs!D16-Inputs!D17-Inputs!D18)) -> 1.5564704 | E7: =IF(N(Inputs!E21)=0,"",Inputs!E21/(Inputs!E16-Inputs!E17-Inputs!E18)) | F7: Total debt / tangible net worth -- 1.59x and 1.56x against published 1.60x and 1.56x. Exceptionally low for an HFC - the defining feature of this credit and the reason the rating sits where it does
B8: AUM / tangible net worth (x) | C8: =IF(N(Inputs!C24)=0,"",Inputs!C24/(Inputs!C16-Inputs!C17-Inputs!C18)) -> 2.5305223 | D8: =IF(N(Inputs!D24)=0,"",Inputs!D24/(Inputs!D16-Inputs!D17-Inputs!D18)) -> 2.5909972 | E8: =IF(N(Inputs!E24)=0,"",Inputs!E24/(Inputs!E16-Inputs!E17-Inputs!E18)) | F8: AUM / tangible net worth -- 2.53x and 2.59x against published 2.53x and 2.58x. Captures leverage on the MANAGED book, including the assigned portfolio that on-book gearing misses
B9: Net interest income | C9: =IF(N(Inputs!C8)=0,"",Inputs!C8-Inputs!C12) -> 1129.07 | D9: =IF(N(Inputs!D8)=0,"",Inputs!D8-Inputs!D12) -> 1295.35 | E9: =IF(N(Inputs!E8)=0,"",Inputs!E8-Inputs!E12) | F9: Interest income less finance costs -- Rs 1,295.35 cr in FY2026, up 15.5%. The spread business is the engine here
B10: NIM on average AUM (%) | C10: =IF(0<>1,"",(Inputs!D8-Inputs!D12)/AVERAGE(Inputs!C24,Inputs!D24)) | D10: =IF(1<>1,"",(Inputs!D8-Inputs!D12)/AVERAGE(Inputs!C24,Inputs!D24)) -> 0.10807192 | E10: =IF(2<>1,"",(Inputs!D8-Inputs!D12)/AVERAGE(Inputs!C24,Inputs!D24)) | F10: (Interest income − finance costs) / average AUM -- 10.81% - very wide, reflecting affordable-housing yields against a low cost of borrowing (8.3% in FY2026, down from 8.7%)
B11: PAT margin (%) | C11: =IF(N(Inputs!C11)=0,"",Inputs!C15/Inputs!C11) -> 0.41773243 | D11: =IF(N(Inputs!D11)=0,"",Inputs!D15/Inputs!D11) -> 0.41992803 | E11: =IF(N(Inputs!E11)=0,"",Inputs!E15/Inputs!E11) -> 0.42731516 | F11: Profit after tax / total income -- 41.8% to 42.0%. Held despite rapid book growth
B12: Cost-to-income (%) | C12: =IF(N(Inputs!C14)=0,"",(Inputs!C14-Inputs!C12-Inputs!C13)/(Inputs!C11-Inputs!C12)) -> 0.20250578 | D12: =IF(N(Inputs!D14)=0,"",(Inputs!D14-Inputs!D12-Inputs!D13)/(Inputs!D11-Inputs!D12)) -> 0.20310827 | E12: =IF(N(Inputs!E14)=0,"",(Inputs!E14-Inputs!E12-Inputs!E13)/(Inputs!E11-Inputs!E12)) | F12: (Total expenses − finance costs − impairment) / (total income − finance costs) -- Improved from 20.3% to 20.2%. Operating efficiency is a genuine strength; the AR reports opex/AUM stable at 2.7% across six years
B13: Credit cost on average AUM (%) | C13: =IF(0<>1,"",Inputs!D13/AVERAGE(Inputs!C24,Inputs!D24)) | D13: =IF(1<>1,"",Inputs!D13/AVERAGE(Inputs!C24,Inputs!D24)) -> 0.0051318205 | E13: =IF(2<>1,"",Inputs!D13/AVERAGE(Inputs!C24,Inputs!D24)) | F13: Impairment on financial instruments / average AUM -- 0.51% in FY2026, more than double FY2025's 0.26% on the same base. Small in absolute terms but the direction matches the rise in GNPA
B14: Return on managed assets ROMA (%) | C14: =IF(0<>1,"",Inputs!D15/AVERAGE(Inputs!C24,Inputs!D24)) | D14: =IF(1<>1,"",Inputs!D15/AVERAGE(Inputs!C24,Inputs!D24)) -> 0.078670115 | E14: =IF(2<>1,"",Inputs!D15/AVERAGE(Inputs!C24,Inputs!D24)) | F14: PAT / average AUM -- 7.87%, reproducing the AR's own reported RoA of 7.9%. Among the highest in the sector
B15: Return on net worth (%) | C15: =IF(0<>1,"",Inputs!D15/AVERAGE(Inputs!C16-Inputs!C17-Inputs!C18,Inputs!D16-Inputs!D17-Inputs!D18)) | D15: =IF(1<>1,"",Inputs!D15/AVERAGE(Inputs!C16-Inputs!C17-Inputs!C18,Inputs!D16-Inputs!D17-Inputs!D18)) -> 0.20164987 | E15: =IF(2<>1,"",Inputs!D15/AVERAGE(Inputs!C16-Inputs!C17-Inputs!C18,Inputs!D16-Inputs!D17-Inputs!D18)) | F15: PAT / average tangible net worth -- 20.2%, against the AR's reported RoE of 20.1%. Rising every year since FY2021 (14.5%) despite the equity base more than doubling
B16: AUM growth (%) [SECTOR] | C16: =IF(OR(0=0,N(Inputs!C24)=0),"",Inputs!C24/INDEX(Inputs!$C$24:$E$24,0)-1) | D16: =IF(OR(1=0,N(Inputs!D24)=0),"",Inputs!D24/INDEX(Inputs!$C$24:$E$24,1)-1) -> 0.20635067 | E16: =IF(OR(2=0,N(Inputs!E24)=0),"",Inputs!E24/INDEX(Inputs!$C$24:$E$24,2)-1) | F16: Year-on-year growth in AUM -- +20.6% in FY2026, on a six-year CAGR of ~26% (Rs 4,068 cr in FY2021 to Rs 13,107 cr). Growth has been funded by accrual, not leverage
B17: Off-book (assigned) share of AUM (%) | C17: =IF(N(Inputs!C23)=0,"",(Inputs!C24-Inputs!C23)/Inputs!C24) -> 0.021604234 | D17: =IF(N(Inputs!D23)=0,"",(Inputs!D24-Inputs!D23)/Inputs!D24) -> 0.089835966 | E17: =IF(N(Inputs!E23)=0,"",(Inputs!E24-Inputs!E23)/Inputs!E24) | F17: (AUM − on-book loans) / AUM -- 2.2% to 9.0%. The step-up explains the Rs 172.44 cr assignment gain in FY2026 against Rs 16.31 cr in FY2025 - a real earnings contributor that will not repeat automatically
B18: Liquid assets / total debt (x) | C18: =IF(N(Inputs!C26)=0,"",Inputs!C26/Inputs!C21) -> 0.04419411 | D18: =IF(N(Inputs!D26)=0,"",Inputs!D26/Inputs!D21) -> 0.071544782 | E18: =IF(N(Inputs!E26)=0,"",Inputs!E26/Inputs!E21) | F18: Cash and cash equivalents / total debt -- 0.04x to 0.07x. The AR states total liquidity of Rs 2,061 cr; note that only UNENCUMBERED cash counts as liquidity under CareEdge's criteria
B19: CRAR headroom over the RBI minimum (pp) | C19: =IF(N(Inputs!C29)=0,"",Inputs!C29-15) | D19: =IF(N(Inputs!D29)=0,"",Inputs!D29-15) -> 56 | E19: =IF(N(Inputs!E29)=0,"",Inputs!E29-15) | F19: CRAR less the 15% regulatory minimum for HFCs -- 56 percentage points of headroom. CRAR of 71% is more than four times the minimum and is the single strongest element of this credit

Sheet TieOut
B2: Aptus Value Housing Finance India Limited - tie-out to company-disclosed figures
B3: Binding gate (CLAUDE.md Step 6): headline computed figures must reconcile to the company's OWN disclosed numbers before the workpaper is issued. PASS/FAIL is itself a formula - it re-evaluates if any input changes.
B5: Check | C5: Computed | D5: Company-disclosed | E5: Result | F5: Note
B6: TNW build-up reproduces published Rs 5,059 cr | C6: =Inputs!D16-Inputs!D17-Inputs!D18 -> 5058.67 | D6: 5059 | E6: =IF(ABS(C6-D6)<=MAX(1,ABS(D6)*0.005),"PASS","CHECK") -> PASS | F6: 5,060.04 − 1.22 − 0.15 = 5,058.67 against CareEdge's published Rs 5,059 crore. The financial-sector definition is confirmed by reproduction, not asserted
B7: FY2026 on-book gearing reproduces published 1.56x | C7: =Inputs!D21/(Inputs!D16-Inputs!D17-Inputs!D18) -> 1.5564704 | D7: 1.56 | E7: =IF(ABS(C7-D7)<=MAX(1,ABS(D7)*0.005),"PASS","CHECK") -> PASS | F7: 7,873.67 / 5,058.67 = 1.5565x. Using total equity instead of TNW gives 1.556x too - the definitions barely diverge here because intangibles are negligible, but the CONVENTION still has to be stated
B8: FY2025 AUM/TNW reproduces published 2.53x | C8: =Inputs!C24/(Inputs!C16-Inputs!C17-Inputs!C18) -> 2.5305223 | D8: 2.53 | E8: =IF(ABS(C8-D8)<=MAX(1,ABS(D8)*0.005),"PASS","CHECK") -> PASS | F8: 10,865 / 4,293.58 = 2.5305x - exact against the published 2.53x
B9: FY2026 total income reproduces published Rs 2,245 cr | C9: =Inputs!D11 -> 2245.48 | D9: 2245 | E9: =IF(ABS(C9-D9)<=MAX(1,ABS(D9)*0.005),"PASS","CHECK") -> PASS | F9: Consolidated total income of Rs 2,245.48 cr. The STANDALONE figure is Rs 1,564.15 cr - splicing the two bases would put the report out by Rs 681 crore
B10: FY2026 PAT reproduces published Rs 943 cr | C10: =Inputs!D15 -> 942.94 | D10: 943 | E10: =IF(ABS(C10-D10)<=MAX(1,ABS(D10)*0.005),"PASS","CHECK") -> PASS | F10: Consolidated PAT of Rs 942.94 cr against standalone Rs 692.87 cr
B11: LINE INTEGRITY - bank facilities sum to the rated limit | C11: =2058.75+30+11.25 -> 2100 | D11: 2100 | E11: =IF(ABS(C11-D11)<=MAX(1,ABS(D11)*0.005),"PASS","CHECK") -> PASS | F11: Annexure-1: term loan 2,058.75 + working capital 30.00 + bank guarantee 11.25 = Rs 2,100.00 crore, matching the header table exactly
B12: LINE INTEGRITY - NCDs sum to the rated limit | C12: =45+240+200+280+80+300 -> 1145 | D12: 1145 | E12: =IF(ABS(C12-D12)<=MAX(1,ABS(D12)*0.005),"PASS","CHECK") -> PASS | F12: NCD II 45.00 + III 240.00 + IV 200.00 + V 280.00 (160.00+120.00) + VI 80.00 + VII 300.00 (150.00+100.00+50.00 proposed) = Rs 1,145.00 crore, exact
B13: FY2026 total debt itemises to the balance sheet | C13: =Inputs!D19+Inputs!D20 -> 7873.67 | D13: 7873.67 | E13: =IF(ABS(C13-D13)<=MAX(1,ABS(D13)*0.005),"PASS","CHECK") -> PASS | F13: 1,350.49 + 6,523.18. Note there is NO commercial paper and no short-term unsecured borrowing - the AR states zero short-term funding risk
B14: FY2026 AUM ties to the entity split | C14: =9306+3801 -> 13107 | D14: 13107 | E14: =IF(ABS(C14-D14)<=MAX(1,ABS(D14)*0.005),"PASS","CHECK") -> PASS | F14: Aptus HFC Rs 9,306 cr (71%) + AFIPL Rs 3,801 cr (29%). The consolidated approach is not optional here - the NBFC subsidiary is 29% of the managed book
B16: Tolerance: 0.5% of the disclosed figure, floor Rs 1 - tighter than rounding, loose enough for basis differences.

Sheet RatingScore
B2: Aptus Value Housing Finance India Limited - rating scorecard and view
B3: Factor scores 1 (strongest) to 6 (weakest), weighted to a composite. The anchor is a SCREENING cross-check with a +/-2 notch band, NOT the rating - the analyst view and any divergence are stated below and the divergence must be explained, never buried.
B5: Rating factor | C5: Score (1-6) | D5: Weight | E5: Weighted | F5: Justification
B6: Capitalisation | C6: 1 | D6: 0.3 | E6: =C6*D6 -> 0.3 | F6: CRAR of 71% against an RBI minimum of 15% - more than four times over, and 56 percentage points of headroom. On-book gearing of 1.56x and AUM/TNW of 2.59x are exceptionally low for an HFC growing at 20%+. Tangible net worth of Rs 5,058.67 cr has been built by accrual: RoE rose from 14.5% (FY2021) to 20.2% while the equity base more than doubled. This is the dominant rating consideration and it provides both growth headroom and a deep buffer against asset-quality stress.
B7: Profitability | C7: 1 | D7: 0.25 | E7: =C7*D7 -> 0.25 | F7: PAT Rs 942.94 cr on total income of Rs 2,245.48 cr - a 42.0% PAT margin, ROMA of 7.87% and RONW of 20.2%, all reproducing the AR's own reported figures. NIM on average AUM of 10.81% reflects affordable-housing yields against a falling cost of borrowing (8.3% in FY2026 from 8.7%). Cost-to-income of 20.2% and opex/AUM stable at 2.7% across six years indicate genuine operating efficiency, not a growth artefact.
B8: Scale and track record | C8: 2 | D8: 0.2 | E8: =C8*D8 -> 0.4 | F8: AUM of Rs 13,107 cr, compounding ~26% over six years from Rs 4,068 cr in FY2021, with an established position in affordable housing. Q1FY2027 continued the trend - income up 15.2% and PAT up 19.0% year on year. The book splits Rs 9,306 cr housing (71%) and Rs 3,801 cr through the NBFC subsidiary (29%), giving product diversity within a single credit-underwriting culture.
B9: Asset quality | C9: 3 | D9: 0.15 | E9: =C9*D9 -> 0.45 | F9: GNPA rose to 1.52% from 1.19% and NNPA to 1.15% from 0.89% (AR, consolidated); CareEdge publishes gross stage 3 of 1.45% against 1.18%. Credit cost on average AUM doubled to 0.51%. Absolute levels remain comfortable and LTV of ~40% gives real collateral protection, but the DIRECTION is uniformly adverse and the book is only moderately seasoned, so reported delinquency understates through-cycle experience. Provision coverage on stage 3 of 25.50% (standalone) is thin, which is defensible only because of the low LTV.
B10: Concentration and borrower profile | C10: 4 | D10: 0.1 | E10: =C10*D10 -> 0.4 | F10: Geographically concentrated in southern India, improving only gradually, and lending to an underbanked segment with limited formal income documentation. This is the structural constraint on the rating: the same segment that produces a 10.81% NIM is the one most exposed to local economic shocks and to any tightening of affordable-housing regulation. A corporate guarantee of Rs 269.63 cr for AFIPL's borrowings sits off balance sheet.
B11: Weight check (must be 100%) | D11: =SUM(D6:D10) -> 1 | E11: =SUM(E6:E10) -> 1.8 | F11: =IF(ABS(D11-1)<0.001,"weights sum to 100%","ERROR: weights must sum to 100%") -> weights sum to 100%
B13: Weighted composite score | C13: =E11 -> 1.8
B14: Indicative anchor grade (screening only, +/-2 band) | C14: AA band (composite 1.70)
B15: ANALYST RATING VIEW | C15: CARE AA; Stable
B16: Divergence from anchor - explanation | C16: NO DIVERGENCE. My independent view is CARE AA; Stable, which matches the CareEdge press release of 02-Jul-2026 (reaffirmed; upgraded to AA; Stable on 03-Jul-2025 from AA-; Positive, having been AA-; Stable through 2023-24). The rating rests on capitalisation that is extreme rather than merely adequate - 71% CRAR and 1.56x gearing - against a concentrated book lending to underbanked borrowers whose asset quality is drifting adversely from a low base. Every ratio in this workbook was solved back from and reproduces the agency's published figures; where a figure differs it is disclosed rather than forced, notably the asset-quality measure, where the AR's consolidated GNPA of 1.52% and CareEdge's gross stage 3 of 1.45% are different measures of the same book and are both reported.
